Workbook

Sheet Collections_v2
A1: COL-id | B1: rang | C1: nom | D1: slogan | E1: description | F1: couleur_hex | G1: photo_url | H1: photo_noel_url
A2: COL-001 | B2: 1 | C2: SAPONICA | D2: Simplement la nature qui prend soin de vous | E2: SAPONICA, c'est le savon dans sa forme la plus pure. Huile de tournesol, huile de coco, beurre de karité — une base généreuse, soigneusement surgraissée, qui nettoie sans jamais décaper. Sa mousse crémeuse enveloppe, sa glycérine naturelle hydrate, et votre peau ressort douce, sans avoir besoin de rien d'autre. Sur cette base, chaque savon devient une histoire. Boréal sent la forêt boréale et ses grands espaces. Délicat murmure la pivoine et la lavande. Étreinte gourmande réunit l'avoine, le miel et l'amande. D'un savon à l'autre, la même âme — des personnalités radicalement différentes. | F2: #8A7A4A | G2: https://res.cloudinary.com/dfasrauyy/image/upload/v1773699699/saponica_yvg3if.jpg
A3: COL-002 | B3: 2 | C3: PETIT NUAGE | D3: Simplement la nature qui dorlote vos tout-petits | E3: La peau des tout-petits mérite ce qu'il y a de plus doux. PETIT NUAGE est formulé sans compromis pour les épidermes les plus fragiles — surgraissé à 10%, avec des ingrédients choisis un à un pour leur douceur. Un savon qui prend soin sans jamais irriter. Câlin sent la poudre de bébé, Fleuri évoque un matin de printemps, Rosé murmure la tendresse quotidienne. Chaque savon a sa douceur, sa couleur, son caractère — tous pensés pour les peaux les plus précieuses. | F3: #E8D8E0 | G3: https://res.cloudinary.com/dfasrauyy/image/upload/v1773699700/nuage_tn6a3j.jpg
A4: COL-003 | B4: 3 | C4: CAPRIN | D4: Simplement la nature et la douceur de la chèvre | E4: Le lait de chèvre, c'est une douceur qu'on reconnaît au premier contact. Riche en vitamines et en acides gras, il nourrit, apaise, respecte même les peaux les plus réactives. Dans chaque savon CAPRIN, il s'unit aux huiles végétales et au beurre de karité pour une mousse crémeuse, lactée, qui prend soin sans jamais agresser. Pomme verte, melon d'eau, cerise — CAPRIN joue avec les fraîcheurs fruitées sur cette base douce et constante. Des savons qui sentent bon, qui font du bien, et qui donnent envie de recommencer. | F4: #957A6A | G4: https://res.cloudinary.com/dfasrauyy/image/upload/v1773699700/Caprin_wbqg5n.jpg
A5: COL-004 | B5: 4 | C5: ÉMOLIA | D5: Simplement la nature dédiée à votre bien-être | E5: ÉMOLIA, c'est la collection pour ceux qui prennent soin d'eux avec intention. Pas juste se laver — se choyer. Des baumes qui réparent, des bombes de bain qui transforment le bain en rituel, des soins qui restent sur la peau longtemps après le rinçage. L'essentiel du bien-être, pensé avec la même philosophie que nos savons. Des lèvres aux talons, ÉMOLIA couvre tout. Baumes à lèvres nourrissants, bombes de bain effervescentes, baumes corporels enveloppants, savon exfoliant revitalisant. Chaque produit est une invitation à ralentir, à s'offrir un moment rien qu'à soi. | F5: #C4956A | G5: https://res.cloudinary.com/dfasrauyy/image/upload/v1774629279/a-minimalist-still-life-photograph-featu_OmMoSBO5T2WkphsZCBhDQA_DSW-Hw_cTSqI_Is56u75Dg_aesvzs.jpg | H5: https://res.cloudinary.com/dfasrauyy/image/upload/v1774629280/a-serene-still-life-photograph-showcasin_RGQ_K97WRBix5vsk004MBg_XyOEAMnuTrO2d-vs37jRYg_vl9eo0.jpg
A6: COL-005 | B6: 5 | C6: ÉPURE | D6: Simplement la nature entre vos mains | E6: ÉPURE, c'est le savon qu'on garde près de l'évier. Cubique, solide, sans fioritures — mais pas sans soin. Formulé pour les mains qui travaillent, cuisinent, jardinent, bricolent. Il nettoie en profondeur, décroche la graisse, et laisse les mains douces sans avoir besoin de crème après. Grain d'acier pour les mains marquées d'huile et de métal. Mousse d'espresso pour réveiller les sens au café du matin. Herbe douce pour la fraîcheur du jardin. Murmure d'Oliva pour un souffle méditerranéen près du fourneau. Chacun a son caractère — tous ont la même solidité. | F6: #6A6A50 | G6: https://res.cloudinary.com/dfasrauyy/image/upload/v1773699700/epure_tvqlz0.jpg
A7: COL-006 | B7: 6 | C7: KÉRYS | D7: Simplement la nature qui veille sur vos cheveux | E7: KÉRYS, c'est le soin capillaire repensé en barre. Concentré, efficace, sans eau inutile — il lave, nourrit et respecte le cuir chevelu en un seul geste. Pas de compromis sur les ingrédients, pas de contenant plastique à jeter. Juste ce qu'il faut, là où ça compte. Trois lignes, trois natures de cheveux. PURÉLIA pour les cheveux gras qui cherchent la légèreté. ÉQUILIBRA pour les cheveux normaux qui veulent rester équilibrés. HYDRABOUCLE pour les boucles qui réclament hydratation et définition. Chaque ligne a ses formules, ses ingrédients, sa promesse. | F7: #5A9A7A | G7: https://res.cloudinary.com/dfasrauyy/image/upload/v1773699700/kerys_tan8yy.jpg
A8: COL-007 | B8: 7 | C8: CASA | D8: Simplement la nature pour votre maison | E8: CASA, c'est la même philosophie que pour votre peau — appliquée à votre maison. Des produits pensés avec les mêmes exigences : ingrédients choisis, efficacité réelle, sans compromis. Parce que prendre soin de son intérieur, c'est aussi prendre soin de soi. Un cake vaisselle qui dégraisse sans agresser les mains. Une bruine d'ambiance qui transforme l'air en un souffle parfumé. Une eau de linge qui dépose une douceur discrète sur chaque fibre. Le quotidien, sublimé. | F8: #9AAF60 | G8: https://res.cloudinary.com/dfasrauyy/image/upload/v1774629280/a-serene-still-life-photograph-capturing_eNdcu-T-QwOlCQFoxMnZoA_QGE0w6WwRdKH6816Kjky-w_oxu2k1.jpg
A9: COL-008 | B9: 8 | C9: LUI | D9: Simplement la nature au masculin | E9: Prendre soin de soi n'est pas une question de genre, mais d'exigence. LUI rassemble des produits pensés pour les hommes qui choisissent le naturel sans sacrifier l'efficacité. Les mêmes ingrédients, le même soin artisanal — avec des parfums boisés, frais, affirmés. Savons pour le corps et les mains, huile à barbe nourrissante, savon à raser en développement. Cèdre bleu, patchouli, bois de santal, romarin — des parfums qui parlent d'eux-mêmes. | F9: #3A5A6A | G9: https://res.cloudinary.com/dfasrauyy/image/upload/v1773716071/IMG_3026_gngdtk.jpg
A10: COL-009 | B10: 9 | C10: ANIMA | D10: Simplement la nature pour pattes et museaux | E10: Nos compagnons méritent le même soin que nous. ANIMA est formulé avec la même rigueur que nos savons pour la peau humaine — saponifié à froid, surgraissé, avec des ingrédients choisis pour leurs bienfaits. Argile purifiante, avoine apaisante, sans huiles essentielles ni parfum ajouté. Parce que l'odorat d'un chien ou d'un chat est bien trop précieux pour être brusqué. Pattes blanches, le seul et unique pour l'instant — mais pensé avec autant d'attention que toute la gamme. Un bain qui nettoie en douceur, respecte la peau sous le pelage, et laisse votre compagnon propre sans l'incommoder. | F10: #C4845A | G10: https://res.cloudinary.com/dfasrauyy/image/upload/v1773699700/Anima_iacrow.jpg

Sheet Gammes_v2
A1: GAM-id | B1: COL-id | C1: rang | D1: nom | E1: description | F1: couleur_hex | G1: photo_url | H1: photo_noel_url
A2: GAM-001 | B2: COL-001 | C2: 1 | D2: SAVON
A3: GAM-002 | B3: COL-002 | C3: 1 | D3: SAVON
A4: GAM-003 | B4: COL-003 | C4: 1 | D4: SAVON AU LAIT DE CHÈVRE
A5: GAM-004 | B5: COL-004 | C5: 1 | D5: BAUME
A6: GAM-005 | B6: COL-004 | C6: 2 | D6: BOMBES DE BAIN | E6: Une boule, un plongeon, et le bain se transforme. L'effervescence du bicarbonate, le sel d'Epsom qui détend les muscles, l'huile d'amande qui soyeuse la peau — tout ça en un seul geste. Un rituel simple qui fait toute la différence. Même magie, formule adaptée aux tout-petits. Sans sel d'Epsom, sans huiles essentielles — juste l'effervescence joyeuse et la douceur de l'amande et du karité. Le bain devient une fête.
A7: GAM-006 | B7: COL-004 | C7: 3 | D7: BAUME À LÈVRES | E7: Une caresse nourrissante qui protège et répare. L'huile de noix de coco hydrate en profondeur, la cire d'abeille crée un voile protecteur, la vitamine E préserve, tandis que le beurre de mangue apporte une douceur veloutée. Des lèvres douces, naturellement sublimées.
A8: GAM-007 | B8: COL-004 | C8: 4 | D8: SAVON
A9: GAM-008 | B9: COL-004 | C9: 5 | D9: SAVON EXFOLIANT
A10: GAM-009 | B10: COL-005 | C10: 1 | D10: SAVON À MAIN
A11: GAM-010 | B11: COL-006 | C11: 1 | D11: ÉQUILIBRA | E11: L'équilibre au quotidien. Des formules douces qui respectent le cuir chevelu naturellement bien réglé — pour qu'il le reste, lavage après lavage.
A12: GAM-011 | B12: COL-006 | C12: 2 | D12: PURÉLIA | E12: La source limpide où les cheveux retrouvent leur légèreté. Argiles absorbantes et ingrédients purifiants dissolvent l'excès sans décaper, sans alourdir. Le cuir chevelu respire, les cheveux brillent.
A13: GAM-012 | B13: COL-006 | C13: 3 | D13: HYDRABOUCLE | E13: Les boucles ont leurs propres besoins. HYDRABOUCLE les nourrit, les hydrate, les enlace d'une douceur protectrice — sans jamais les alourdir ni les dompter.
A14: GAM-013 | B14: COL-007 | C14: 1 | D14: BRUINE D'AMBIANCE | E14: L'atmosphère en bouteille. Ce spray délicat transforme instantanément l'air de votre intérieur en une invitation à la détente. Formulée à base d'eau distillée et de fragrances naturelles, la bruine d'ambiance enveloppe chaque pièce d'un voile olfactif subtil et éphémère. Une impulsion, et l'espace se métamorphose.
A15: GAM-014 | B15: COL-007 | C15: 2 | D15: CAKE VAISSELLE | E15: Dans la continuité de notre collection de savons pour les mains, Épure Vaisselle apporte la même philosophie d'authenticité à l'évier. Un pain solide qui mousse généreusement au contact de l'eau et de l'éponge. Son pouvoir dégraissant naturel ce savon vaisselle fait disparaître les résidus alimentaires sans laisser de traces. Sa texture ferme et compacte lui confère une longévité exceptionnelle : un seul pain remplace plusieurs flacons de liquide vaisselle.
A16: GAM-015 | B16: COL-007 | C16: 3 | D16: EAU DE LINGE | E16: Le linge comme une seconde peau. Vaporisée sur vos tissus avant ou après le repassage, cette eau délicatement parfumée prolonge la fraîcheur et laisse sur draps, vêtements et linges de maison un sillage doux et naturel. Parce que la douceur commence dès le matin, au contact du tissu.
A17: GAM-016 | B17: COL-007 | C17: 4 | D17: BOUGIE | E17: LUMINA, c'est l'atmosphère en cire. Des chandelles artisanales à base de cire de soya qui brûlent doucement, proprement, longtemps. La flamme danse, le parfum s'installe, la pièce se transforme. Lessive fraîche, Pivoine et Poire — des fragrances exclusives aux chandelles, disponibles en tout temps. Club privé, Feu d'automne, Nuage de lavande de SAPONICA, disponibles régulièrement.
A18: GAM-017 | B18: COL-008 | C18: 1 | D18: SAVAGE SAVONNERIE
A19: GAM-018 | B19: COL-008 | C19: 2 | D19: SAVON À RASER
A20: GAM-019 | B20: COL-009 | C20: 1 | D20: SAVON
A21: GAM-1775511367298 | B21: COL-008 | C21: 1 | D21: HUILE À BARBE
A22: GAM-1775518159265 | B22: COL-007 | C22: 5 | D22: SAVON DU PAYS

Sheet Familles_v2
A1: FAM-id | B1: COL-id | C1: rang | D1: nom | E1: description | F1: couleur_hex | G1: photo_url | H1: photo_noel_url
A2: FAM-001 | B2: COL-008 | C2: 1 | D2: BARBE ET MOUSTACHE | E2: Tout pour votre visage
A3: FAM-1775511526523 | B3: COL-008 | C3: 2 | D3: SÉRIE - EN COLLABORATION | E3: Pour vous faire découvrir d’autres artisans
A4: FAM-1775732950384 | B4: COL-004 | C4: 1 | D4: BAUME HIVER | E4: Pour affronter le froid et la sécheresse

Sheet Produits_v2
A1: PRO-id | B1: COL-id | C1: GAM-id | D1: FAM-id | E1: nom | F1: description | G1: desc_emballage | H1: couleur_hex | I1: surgras | J1: nb_unites | K1: cure | L1: instructions | M1: notes | N1: image_url | O1: image_noel_url | P1: statut | Q1: collections_secondaires
A2: PRO-014 | B2: COL-001 | C2: GAM-001 | E2: BRISE DES LAGUNES | F2: Il y a des endroits qu'on ne visite qu'en rêve. Brise des lagunes capture cet instant suspendu. L'argile blanche purifie en douceur tandis que la brise marine et le cèdre bleu s'enlacent dans une mousse soyeuse. | G2: La fraîcheur des eaux secrètes, la caresse des vents marins. | H2: #3EAF85 | I2: 0.08 | J2: 9 | K2: 28 | M2: Huile aromatique Jasmin, Huile aromatique Lotus, HE Christe marine, Huile aromatique Bois de santal, HE Romarin, HE Bois de Hô, HE Citron / ½ sarcelle, ½ Argile blanche | N2: https://res.cloudinary.com/dfasrauyy/image/upload/v1773418760/Brisedeslagunes_nurrcu.jpg | O2: https://res.cloudinary.com/dfasrauyy/image/upload/v1773418760/BrisedeslagunesNoel_whufa1.jpg | P2: public | Q2: COL-008
A3: PRO-041 | B3: COL-001 | C3: GAM-001 | E3: ÉCLAT FLORAL | F3: Éclat floral célèbre la beauté simple et lumineuse du naturel. L'Argile Multani mutti illumine, les confettis de fleurs couronnent chaque barre d'une touche unique et poétique. | G3: Un savon mosaïque, doré d'Argile jaune et parsemé de fleurs, où chaque fragment renaît en douceur. | H3: #FFB400 | I3: 0.08 | J3: 9 | K3: 28 | M3: 17.5g Argile Multani mutti = 5 c. à thé / Fleurs confettis sur le dessus | N3: https://res.cloudinary.com/dfasrauyy/image/upload/v1773448829/Eclatfloral_rqh0ry.jpg | O3: https://res.cloudinary.com/dfasrauyy/image/upload/v1773448784/Eclatfloralnoel_om51gw.jpg | P3: public
A4: PRO-042 | B4: COL-001 | C4: GAM-001 | E4: ÉCLAT TROPICAL | F4: Ferme les yeux et laisse la mandarine, l'orange douce et la pêche t'emporter quelque part entre un marché tropical et un verger en plein soleil. | G4: Mangue, pêche, mandarine. Un été qui ne finit jamais. | H4: #FF6735 | I4: 0.08 | J4: 9 | K4: 28 | M4: 10.5g Argile blanche = 3 c. à thé / Restes de savon coco-mangue en petits morceaux | N4: https://res.cloudinary.com/dfasrauyy/image/upload/v1773448785/Eclatfloral_lg1ysi.jpg | O4: https://res.cloudinary.com/dfasrauyy/image/upload/v1773448370/Eclattropicalnoel_iggl8h.jpg | P4: public
A5: PRO-053 | B5: COL-001 | C5: GAM-001 | E5: JARDIN D'AURORE | F5: Le concombre frais du potager s'unit à la menthe qui borde les allées, comme un hommage aux mains qui ont cultivé ces merveilles. | G5: Fraîcheur de concombre, souffle de menthe, un jardin qui respire entre les mains. | H5: #65791A | I5: 0.08 | J5: 9 | K5: 28 | M5: Un p'tit clin d'œil à ma grand-mère que j'aurais voulu connaître. | N5: https://res.cloudinary.com/dfasrauyy/image/upload/v1773449232/Jardindaurore_vtpqvp.jpg | O5: https://res.cloudinary.com/dfasrauyy/image/upload/v1773449232/Jardindaurorenoel_vitnor.jpg | P5: public
A6: PRO-073 | B6: COL-001 | C6: GAM-001 | E6: SOLEIL DE PROVENCE | F6: Le citron et les agrumes éclatent sous le soleil, le romarin sauvage pousse entre les pierres chaudes. Soleil de Provence capture cette simplicité lumineuse. | G6: Agrumes et romarin sauvage. Le sud de la France dans chaque mousse. | H6: #FD791A | I6: 0.08 | J6: 9 | K6: 28 | M6: Orange | N6: https://res.cloudinary.com/dfasrauyy/image/upload/v1773448369/Soleildeprovence_pue3as.jpg | O6: https://res.cloudinary.com/dfasrauyy/image/upload/v1773448369/Soleildeprovencenoel_hbh9lb.jpg | P6: public
A7: PRO-078 | B7: COL-001 | C7: GAM-001 | E7: VOILE DE POIRE | F7: Il y a des savons tout en légèreté. La poire juteuse ouvre le bal, le thé vert apporte sa subtilité végétale, la bergamote signe d'une touche florale et citronnée. | G7: Poire juteuse, thé vert, bergamote. Une douceur qui glisse. | H7: #91D129 | I7: 0.08 | J7: 9 | K7: 28 | M7: Vert kiwi / 11g Argile blanche = 1 c. à table | N7: https://res.cloudinary.com/dfasrauyy/image/upload/v1773448369/Voiledepoire_ue6ufc.jpg | O7: https://res.cloudinary.com/dfasrauyy/image/upload/v1773448370/Voiledepoirenoel_xg6jef.jpg | P7: public
A8: PRO-066 | B8: COL-002 | C8: GAM-002 | E8: PETIT NUAGE CÂLIN | F8: Sa mousse légère rappelle le parfum délicat du linge frais, une senteur poudrée qui apaise et réconforte. | G8: Un savon tendre comme une étreinte, pensé pour envelopper la peau d'une douceur rassurante. | H8: #B7DCC4 | I8: 0.1 | J8: 9 | K8: 28 | M8: 1 c. à thé argile blanche ou rose = 5g | N8: https://res.cloudinary.com/dfasrauyy/image/upload/v1773083346/univers-caresse/produits/vw5bdqa4j1dumkwjodzr.jpg | P8: public
A9: PRO-067 | B9: COL-002 | C9: GAM-002 | E9: PETIT NUAGE DOUCE BAIE | F9: Un savon tendre et fruité, comme une caresse mauve venue des sous-bois. Sa mousse délicate s'imprègne de la douceur des mûres. | G9: Un souffle mauve et fruité, velouté comme un smoothie d'été, doux comme une caresse de mûre. | H9: #5A4657 | I9: 0.1 | J9: 9 | K9: 28 | M9: 1 c. à thé argile blanche ou rose = 5g | N9: https://res.cloudinary.com/dfasrauyy/image/upload/v1773083394/univers-caresse/produits/gncwgz5xektcburqtpzr.jpg | P9: public
A10: PRO-068 | B10: COL-002 | C10: GAM-002 | E10: PETIT NUAGE FLEURI | F10: Sa mousse douce s'imprègne de la fraîcheur du pois de senteur, une odeur naturelle, légère et florale qui évoque les bouquets d'enfance. | G10: Un savon lumineux et joyeux, comme un matin de printemps. | H10: #F8E7A1 | I10: 0.1 | J10: 9 | K10: 28 | M10: 1 c. à thé argile blanche ou rose = 5g | N10: https://res.cloudinary.com/dfasrauyy/image/upload/v1773083428/univers-caresse/produits/qiea1clad0wsqu8x4v1r.jpg | P10: public
A11: PRO-069 | B11: COL-002 | C11: GAM-002 | E11: PETIT NUAGE ROSÉ | F11: Un voile tendre et aérien, comme une caresse de l'aube. La douceur de l'huile végétale amande douce et du karité se marie à la légèreté de l'olive. | G11: Une bulle de tendresse, une invitation à la douceur quotidienne. | H11: #F7DDE6 | I11: 0.1 | J11: 9 | K11: 28 | M11: 1 c. à thé argile blanche ou rose = 5g | N11: https://res.cloudinary.com/dfasrauyy/image/upload/v1773083525/univers-caresse/produits/kdrgqwki1vaclkhjln4c.jpg | P11: public
A12: PRO-028 | B12: COL-003 | C12: GAM-003 | E12: CAPRICE FRAISÉ | F12: Le lait de chèvre enveloppe, la fraise éveille. Un savon gourmand qui prend soin de la peau avec une douceur crémeuse et un parfum fruité irrésistible. | G12: L'alliance gourmande du lait onctueux et de la fraise sucrée. | H12: #A2414D | I12: 0.08 | J12: 12 | K12: 42 | M12: Utiliser de l'eau glacée pour ralentir la réaction avec le lait de chèvre. | P12: public
A13: PRO-029 | B13: COL-003 | C13: GAM-003 | E13: CERISE DE VELOURS | F13: La cerise, juteuse et sucrée, apporte sa douceur fruitée à une mousse crémeuse et veloutée. Dans ce savon au lait de chèvre, elle s'unit à l'argile blanche purifiante. | G13: Savon gourmand au lait de chèvre et cerises, douceur fruitée et peau satinée. | H13: #BF0E24 | I13: 0.08 | J13: 12 | K13: 42 | M13: Utiliser de l'eau glacée pour ralentir la réaction avec le lait de chèvre. | P13: public
A14: PRO-043 | B14: COL-003 | C14: GAM-003 | E14: ÉCLOSION DE SOIE | F14: La spiruline apporte sa richesse végétale, le jasmin envoûte, le thé vert protège. Éclosion de soie est un savon au lait de chèvre qui prend soin de la peau avec une douceur florale et végétale. | G14: Un savon velouté où le jasmin s'ouvre doucement sur un fond de thé vert et de lait crémeux. Une caresse soyeuse, presque textile. | H14: #476B33 | I14: 0.08 | J14: 12 | K14: 42 | M14: Utiliser de l'eau glacée pour ralentir la réaction avec le lait de chèvre. | P14: public
A15: PRO-049 | B15: COL-003 | C15: GAM-003 | E15: FRAÎCHEUR DE MELON | F15: Le melon d'eau apporte sa légèreté aquatique et sucrée à la richesse crémeuse du lait de chèvre. | G15: La douceur crémeuse du lait de chèvre épouse la légèreté rafraîchissante du melon d'eau. | H15: #BF705E | I15: 0.08 | J15: 12 | K15: 42 | M15: Utiliser de l'eau glacée pour ralentir la réaction avec le lait de chèvre. | P15: public
A16: PRO-062 | B16: COL-003 | C16: GAM-003 | E16: ORANGE SAUVAGE | F16: L'orange douce s'embrase au contact de la cannelle, du gingembre et du clou de girofle. Le curcuma illumine, l'écorce d'orange texturise légèrement. | G16: Éclat d'agrume et souffle d'épices, comme une chaleur libre qui danse sur la peau. | H16: #C67D26 | I16: 0.08 | J16: 12 | K16: 42 | M16: Utiliser de l'eau glacée pour ralentir la réaction avec le lait de chèvre. | P16: public
A17: PRO-070 | B17: COL-003 | C17: GAM-003 | E17: POMME D'ÉMERAUDE | F17: La pomme verte apporte sa fraîcheur acidulée et légère à la douceur crémeuse du lait de chèvre. Le mica vert illumine chaque barre d'un éclat naturel. | G17: Savon délicat au lait de chèvre et pomme verte, fraîcheur et douceur en un seul geste. | H17: #51EB4E | I17: 0.08 | J17: 12 | K17: 42 | M17: Utiliser de l'eau glacée pour ralentir la réaction avec le lait de chèvre. | P17: public
A18: PRO-044 | B18: COL-004 | C18: GAM-004 | E18: EFFLUVE APAISANT | F18: Un souffle clair qui libère la respiration, une chaleur douce qui réconforte. Effluve apaisant dépose sur la peau un nuage aromatique qui apaise l'hiver. | G18: Un baume aromatique qui dégage, réchauffe et réconforte — le souffle de l'hiver apprivoisé. | H18: #E7B539 | I18: 0 | J18: 1 | K18: 0 | M18: **Version courte :** Un baume aromatique qui dégage, réchauffe et réconforte — le souffle de l'hiver apprivoisé. | P18: public
A19: PRO-064 | B19: COL-004 | C19: GAM-004 | E19: PETIT BOUCLIER | F19: Un voile de douceur qui enveloppe la peau d'un confort rassurant, comme un nuage qui veille. Pour les petits bobos du quotidien. | G19: Un voile protecteur tout en douceur, pour les petites peaux qui ont besoin d'être chouchoutées. | H19: #519A9C | I19: 0 | J19: 1 | K19: 0 | M19: Les zones comme les fesses sont plus sensibles / Pour utilisation externe seulement | P19: public
A20: PRO-006 | B20: COL-004 | C20: GAM-005 | E20: BOMBE BAIN BRISE DES LAGUNES | F20: Laissez l'effervescence dessiner des lagunes dans votre bain. Brise des lagunes capture l'air salin des eaux turquoise, le souffle tiède du cèdre bleu qui s'attarde sur la peau. | G20: Une escapade aquatique — la brise marine et le cèdre bleu pour un bain qui sent l'horizon. | H20: #3EAF85 | I20: 0 | J20: 3 | K20: 0 | M20: 10g Eau = 2 c. à thé / 45g Huile végétale amande douce = 3 c. à table / 6g fleurs = 1 c. à table / Colorant ⚠️ à confirmer avec Chantal / 6g fleurs si désiré | P20: public
A21: PRO-007 | B21: COL-004 | C21: GAM-005 | E21: BOMBE BAIN DÉLICAT | F21: Délicat invite la pivoine et la lavande à danser dans votre bain. L'effervescence libère un voile floral subtil et apaisant. | G21: Pivoine, lavande et thé vert — une effervescence florale toute en douceur. | H21: #AF99A4 | I21: 0 | J21: 3 | K21: 0 | M21: 10g Eau = 2 c. à thé / 45g Huile végétale amande douce = 3 c. à table / 6g fleurs = 1 c. à table / Colorant ⚠️ à confirmer avec Chantal / 6g fleurs si désiré | P21: public
A22: PRO-008 | B22: COL-004 | C22: GAM-005 | E22: BOMBE BAIN DOUCE PENSÉE | F22: Douce pensée transforme le bain en un rituel floral et sensuel. Le géranium rosat équilibre, l'ylang-ylang enveloppe d'une chaleur presque tropicale. | G22: Géranium rosat et ylang-ylang — une effervescence florale chaude et enveloppante. | H22: #E76877 | I22: 0 | J22: 3 | K22: 0 | M22: 10g Eau = 2 c. à thé / 45g Huile végétale amande douce = 3 c. à table / 6g fleurs = 1 c. à table / Colorant ⚠️ à confirmer avec Chantal / 6g fleurs si désiré | P22: public
A23: PRO-009 | B23: COL-004 | C23: GAM-005 | E23: BOMBE BAIN NUAGE DE LAVANDE | F23: Nuage de lavande n'a pas besoin de complices. La lavande se déploie dans l'effervescence, enveloppe le bain d'un voile apaisant et profond. | G23: La lavande à l'état pur — une effervescence douce pour un bain tout en quiétude. | H23: #7F68CA | I23: 0 | J23: 3 | K23: 0 | M23: 10g Eau = 2 c. à thé / 45g Huile végétale amande douce = 3 c. à table / 6g fleurs = 1 c. à table / Colorant ⚠️ à confirmer avec Chantal / 6g fleurs si désiré | P23: public
A24: PRO-010 | B24: COL-004 | C24: GAM-005 | E24: BOMBE BAIN VANILLE ET CITRON | F24: Vanille et citron, c'est le duo inattendu qui réchauffe et éveille à la fois. | G24: La douceur de la vanille rencontre le pétillement du citron — un bain gourmand et lumineux. | H24: #FFF8DC | I24: 0 | J24: 3 | K24: 0 | M24: 10g Eau = 2 c. à thé / 45g Huile végétale amande douce = 3 c. à table / 6g fleurs = 1 c. à table / Colorant ⚠️ à confirmer avec Chantal / arôme de vanille à confirmer avec Chantal | P24: public
A25: PRO-011 | B25: COL-004 | C25: GAM-005 | E25: BOMBES DE BAIN PETIT NUAGE | F25: L'heure du bain devient une fête. Ces bombes douces et colorées transforment l'eau en une bulle de tendresse parfumée. Sans huile essentielle, sans sel d'Epsom. | I25: 0 | J25: 24 | K25: 0 | M25: Pas de sel d'Epsom ni de HE / 26g Huile végétale amande douce = 2 c. à table / 13g Beurre de karité fondu = 1 c. à table | P25: public
A26: PRO-001 | B26: COL-004 | C26: GAM-006 | E26: BAISER FRUITÉ | F26: Ferme les yeux et laisse-toi porter par les vergers en fleurs ! Fraise et cerise se mêlent en un duo gourmand et envoûtant. Un baume qui hydrate, protège et donne envie d'être embrassée. | G26: La douceur des fruits rouges, un brillant qui fait tout dire. | H26: #5A1C37 | I26: 0 | J26: 18 | K26: 0 | M26: Colore les lèvres / 2-4g Allantoine selon sensibilité | P26: public
A27: PRO-002 | B27: COL-004 | C27: GAM-006 | E27: NUAGE FRAISE | F27: Les petites lèvres méritent les meilleurs soins. Nuage Fraise est formulé sans huile essentielle, sans mica, avec des ingrédients doux et non toxiques pensés pour les tout-petits. | G27: Doux comme un nuage, sucré comme une fraise — un baume sécuritaire pour les petites lèvres. | H27: #9C1E45 | I27: 0 | J27: 18 | K27: 0 | M27: Zéro HE, Zéro Mica, Comestibles et non toxiques | P27: public
A28: PRO-003 | B28: COL-004 | C28: GAM-006 | E28: PETIT NUAGE DOUILLET | F28: L'hiver est rude, même pour les plus petits. Petit Nuage Douillet est une version hivernale plus enveloppante, avec davantage de cire d'abeille et de karité pour protéger les lèvres fragilisées par le froid. | G28: Un câlin pour les petites lèvres quand le froid arrive — doux, sécuritaire et réconfortant. | H28: #519A9C | J28: 18 | K28: 0 | M28: Zéro HE, Zéro Mica, Comestibles et non toxiques | P28: public | Q28: COL-002
A29: PRO-050 | B29: COL-004 | C29: GAM-006 | E29: FRAISE ET BASILIC | F29: Qui aurait pensé marier la fraise et le basilic ? La douceur sucrée de la fraise rencontre le caractère herbacé du basilic pour créer quelque chose d'unique et d'inoubliable. | G29: L'audace d'un duo inattendu, la douceur d'un instant gourmand. | H29: #B60F31 | I29: 0 | J29: 18 | K29: 0 | M29: 5g Vitamine E = 1 c. à thé / 10g Sirop de fraise = 2 c. à thé | P29: public
A30: PRO-055 | B30: COL-004 | C30: GAM-006 | E30: LAVANDE - ROMARIN | F30: Fermez les yeux et respirez. La lavande apaise, le romarin vivifie. Ensemble ils forment un duo intemporel qui nourrit les lèvres en profondeur. | G30: La sérénité de la lavande, la vigueur du romarin. La Provence dans un baume. | H30: #908ED3 | I30: 0 | J30: 18 | K30: 0 | M30: 100% naturel, 100% essentiel | P30: public
A31: PRO-057 | B31: COL-004 | C31: GAM-006 | E31: MENTHE POIVRÉE | F31: Vive, pétillante et sans compromis, menthe poivrée réveille les lèvres et les sens d'un seul geste. | G31: Un frisson de fraîcheur, même en plein hiver. | H31: #90FAD3 | I31: 0 | J31: 18 | K31: 0 | M31: 5g Vitamine E = 1 c. à thé / 5g arôme naturel de menthe poivrée = 1 c. à thé / Vérifier nom — Menthe poivrée ou Frisson de menthe ? | P31: public
A32: PRO-075 | B32: COL-004 | C32: GAM-006 | E32: SOUFFLE D'ÉTÉ | F32: Quand le soleil brûle et dessèche, Souffle d'été prend soin de tes lèvres avec douceur. Un baume réparateur et nacré, enrichi en karité, calendula et allantoine. | G32: Un souffle de fraîcheur pour des lèvres réparées par le soleil. | H32: #F1FFBB | I32: 0 | J32: 18 | K32: 0 | M32: Nacré blanc sans trop. | P32: public
A33: PRO-076 | B33: COL-004 | C33: GAM-006 | E33: SOUFFLE D'HIVER | F33: Quand le froid mord et que l'air se fait lourd, Souffle d'hiver veille. Ses vapeurs d'eucalyptus, de menthe et de ravintsara dégagent les narines et apaisent les lèvres gercées. | G33: Un souffle chaud qui libère, répare et protège au cœur de l'hiver. | J33: 18 | K33: 0 | M33: 5 gouttes colorant bleu | P33: public
A34: PRO-077 | B34: COL-004 | C34: GAM-006 | E34: VENT FRAIS | F34: Inspiré des grands espaces et des matins clairs. Vent frais est un baume sans artifice, pour elle comme pour lui. Menthe, eucalyptus et tea tree se fondent en une sensation de fraîcheur immédiate. | G34: La nature à l'état pur, sur tes lèvres. | H34: #609C6A | I34: 0 | J34: 18 | K34: 0 | M34: Déconseillé aux femmes enceintes et enfants de moins de 6 ans | P34: public
A35: PRO-021 | B35: COL-004 | C35: GAM-008 | E35: BRUME DE ROSÉE | F35: Comme une promenade matinale après la pluie, ce savon exfoliant capture la fraîcheur de l'aube. | G35: Le luffa réveille, la menthe vivifie. Une fraîcheur verte pour une peau neuve. | H35: #9EBD7C | I35: 0 | J35: 9 | K35: 28 | M35: Micas à fleurs bleues ⚠️ quantité à confirmer / Couleur vert grass / 9 Luffa (1 par savon) | P35: public
A36: PRO-051 | B36: COL-005 | C36: GAM-009 | E36: GRAIN D'ACIER | F36: Les mains qui travaillent méritent un savon à leur mesure. Grain d'acier nettoie en profondeur sans agresser, la pierre ponce retire les salissures tenaces. | G36: Un savon robuste et épuré, conçu pour les mains marquées d'huile et de métal. Sa mousse dense décroche la graisse et laisse la peau nette. | H36: #545454 | I36: 0.05 | J36: 10 | K36: 42 | M36: 7g Pierre ponce = 2 c. à thé / 3.5g Argile blanche = 1 c. à thé / Savon gris pâle avec mouchette de charbon activé végétal pour rappeler le métal. | N36: https://res.cloudinary.com/dfasrauyy/image/upload/v1773085030/univers-caresse/produits/dgskttwylxoqxh1x689n.jpg | P36: public | Q36: LUI
A37: PRO-052 | B37: COL-005 | C37: GAM-009 | E37: HERBE DOUCE | F37: Il y a des savons qui ne font pas de bruit. Herbe douce est de ceux-là. Le pin blanc apporte sa fraîcheur résineuse, la poire sa douceur juteuse. | G37: Un savon clair et apaisant, où le pin blanc et la poire se mêlent à une lumière douce. Une fraîcheur verte, simple et pure, comme un matin tranquille. | H37: #425B00 | I37: 0 | J37: 10 | K37: 42 | M37: 3.5g Argile blanche = 1 c. à thé / Vert sauge dans une petite quantité de pâte, ajouté sans trop mêler | N37: https://res.cloudinary.com/dfasrauyy/image/upload/v1773085101/univers-caresse/produits/p0dsiibm02qrmhuluhok.jpg | P37: public
A38: PRO-058 | B38: COL-005 | C38: GAM-009 | E38: MOUSSE D'ESPRESSO | F38: Pour ceux qui commencent leur journée avec un café et la terminent avec un autre. Le marc de café exfolie en douceur, le cacao enveloppe d'une chaleur gourmande. | G38: Un parfum mocha, une mousse chaleureuse, des grains qui réveillent la peau. | H38: #3F2300 | I38: 0 | J38: 10 | K38: 42 | M38: 22g Marc de café = 2 c. à table / 11g Cacao en poudre = 1 c. à table | N38: https://res.cloudinary.com/dfasrauyy/image/upload/v1773085149/univers-caresse/produits/gewk6wpfn1tet13vzsnc.jpg | P38: public
A39: PRO-059 | B39: COL-005 | C39: GAM-009 | E39: MURMURE D'OLIVA | F39: L'huile d'olive vierge est l'ancêtre des savons. Ici, elle est à l'honneur, accompagnée du romarin et du citron qui lui donnent une vivacité méditerranéenne. | G39: Un souffle doux venu de la Méditerranée. | H39: #A2AF0E | I39: 0 | J39: 10 | K39: 42 | M39: 17.5g Argile verte = 5 c. à thé / 10g Romarin séché = 5 c. à thé / Verser moules en cubes avec une demie tranche de citron dans chaque cube | N39: https://res.cloudinary.com/dfasrauyy/image/upload/v1773085196/univers-caresse/produits/m5gjwtn5cfdctygdzawl.jpg | P39: public
A40: PRO-015 | B40: COL-006 | C40: GAM-010 | E40: BRISE MATINALE | F40: Ce shampoing solide Équilibra réveille la chevelure d'une fraîcheur délicate et enveloppante. | G40: Sous sa caresse, le cuir chevelu s'illumine comme au lever du jour. | H40: #6787FF | I40: 0 | J40: 1 | K40: 0 | M40: Ce savon est beige / 8-10 gouttes HE menthe poivrée | N40: https://res.cloudinary.com/dfasrauyy/image/upload/v1773084533/univers-caresse/produits/dk74oyfcggmp3qgcmhpl.png | P40: public
A41: PRO-030 | B41: COL-006 | C41: GAM-011 | E41: CLARTÉ VERTE | F41: Sous la mousse légère de Clarté verte, le cuir chevelu respire comme une clairière après la pluie. L'argile purifie, l'ortie fortifie, le romarin réveille. | G41: La chevelure respire comme une clairière purifiée. | H41: #366d1f | J41: 1 | K41: 0 | M41: Ce savon est vert foncé / 8-10 gouttes HE tea tree | P41: public
A42: PRO-072 | B42: COL-006 | C42: GAM-011 | E42: RAYON LUMINEUX | F42: Chaque lavage devient une aurore pétillante. La mousse s'ouvre comme un zeste lumineux, l'argile et la bardane absorbent les ombres grasses. | G42: La chevelure s'illumine d'une fraîcheur solaire et pétillante. | H42: #79b547 | J42: 1 | K42: 0 | M42: 8-10 gouttes HE citron ou pamplemousse | P42: public
A43: PRO-016 | B43: COL-007 | C43: GAM-013 | E43: BRUINE AGRUMES ET ROMARIN | F43: L'atmosphère en bouteille. Ce spray délicat transforme instantanément l'air de votre intérieur en une invitation à la détente. | G43: Un souffle délicat qui transforme l'air de votre intérieur. | I43: 0 | J43: 5 | K43: 0 | M43: Recette originale : 60 ml alcool 70%, 190 ml eau, 15 gouttes HE | P43: public
A44: PRO-017 | B44: COL-007 | C44: GAM-013 | E44: BRUINE BRISE DES LAGUNES | F44: L'atmosphère en bouteille. Ce spray délicat transforme instantanément l'air de votre intérieur en une invitation à la détente. | G44: Un souffle délicat qui transforme l'air de votre intérieur. | I44: 0 | J44: 5 | K44: 0 | M44: Recette originale : 60 ml alcool 70%, 190 ml eau, 15 gouttes HE | P44: public
A45: PRO-018 | B45: COL-007 | C45: GAM-013 | E45: BRUINE LAVANDE | F45: L'atmosphère en bouteille. Ce spray délicat transforme instantanément l'air de votre intérieur en une invitation à la détente. | G45: Un souffle délicat qui transforme l'air de votre intérieur. | I45: 0 | J45: 5 | K45: 0 | M45: Recette originale : 60 ml alcool 70%, 190 ml eau, 15 gouttes HE | P45: public
A46: PRO-020 | B46: COL-007 | C46: GAM-013 | E46: BRUINE POIRE | F46: L'atmosphère en bouteille. Ce spray délicat transforme instantanément l'air de votre intérieur en une invitation à la détente. | G46: Un souffle délicat qui transforme l'air de votre intérieur. | I46: 0 | J46: 5 | K46: 0 | M46: Recette originale : 60 ml alcool 70%, 190 ml eau, 15 gouttes HE | P46: public
A47: PRO-024 | B47: COL-007 | C47: GAM-016 | E47: BOUGIE FEU D'AUTOMNE | H47: #FC6B33 | I47: 0 | J47: 1 | K47: 0 | M47: La quantité par lot dépend du format de contenant choisi. | P47: public
A48: PRO-025 | B48: COL-007 | C48: GAM-016 | E48: BOUGIE LESSIVE FRAÎCHE | H48: #F1FFEF | I48: 0 | J48: 1 | K48: 0 | M48: La quantité par lot dépend du format de contenant choisi. | P48: public
A49: PRO-026 | B49: COL-007 | C49: GAM-016 | E49: BOUGIE NUAGE DE LAVANDE | H49: #7F68CA | I49: 0 | J49: 1 | K49: 0 | M49: La quantité par lot dépend du format de contenant choisi. | P49: public
A50: PRO-027 | B50: COL-007 | C50: GAM-016 | E50: BOUGIE PIVOINE ET POIRE | H50: #A26B83 | I50: 0 | J50: 1 | K50: 0 | M50: La quantité par lot dépend du format de contenant choisi. | P50: public
A51: PRO-074 | B51: COL-007 | C51: GAM-016 | E51: SOUFFLE DE SAPIN | F51: Il y a des produits qui ne cherchent pas à plaire — ils travaillent, tout simplement. Souffle de Sapin s'attaque aux taches tenaces, dégraisse les surfaces, détache les tissus. | G51: Un savon rustique au parfum de forêt, puissant et authentique, créé pour détacher les tissus et nettoyer la maison avec la force simple du sapin. | H51: #4A6126 | I51: 0 | J51: 30 | K51: 0 | M51: 1 c. à soupe Sel = 15g / 1 c. à soupe Argile blanche = 15g | P51: public
A52: PRO-079 | B52: COL-008 | C52: GAM-018 | D52: FAM-001 | E52: L'INSTANT DU BARBIER | F52: Ce savon enveloppe le visage d'une crème dense et soyeuse qui prépare le poil, protège la peau et invite la lame à glisser sans résistance. | G52: Un savon qui transforme le rasage en rituel. Une mousse onctueuse qui prend soin du poil et de la peau, du premier geste au dernier. | H52: #AA7513 | I52: 0 | J52: 1 | K52: 6 | P52: public
A53: PRO-063 | B53: COL-009 | C53: GAM-019 | E53: PATTES BLANCHES | F53: Nos compagnons méritent le même soin que nous. Ce savon artisanal est le complice des retours de balade et des pelages en désordre. | G53: Le savon des petits aventuriers, pour effacer les traces d'aventure et retrouver un pelage de velours. | H53: #E6DEDF | I53: 0.1 | J53: 9 | K53: 42 | M53: **Version courte :** Le savon des petits aventuriers, pour effacer les traces d'aventure et retrouver un pelage de velours. | P53: public
A54: PRO-080 | B54: COL-008 | C54: GAM-018 | D54: FAM-001 | E54: CLUB PRIVÉ (SAVON À BARBE) | F54: Ce savon enveloppe le visage d'une crème dense et soyeuse qui prépare le poil, protège la peau et invite la lame à glisser sans résistance. | G54: Un savon qui transforme le rasage en rituel. Une mousse onctueuse qui prend soin du poil et de la peau, du premier geste au dernier. | H54: #AA7513 | J54: 1 | K54: 6 | P54: public
A55: PRO-045 | B55: COL-008 | C55: GAM-1775511367298 | D55: FAM-001 | E55: L'ÉLIXIR DU MATIN | F55: La barbe mérite qu'on s'en occupe. L'Élixir du matin est une alliance de trois huiles soigneusement choisies. | G55: Trois huiles nobles, un souffle de lavande, un fond de cèdre. Une huile légère qui nourrit, assouplit et sublime la barbe. | H55: #C57513 | J55: 6 | K55: 0 | P55: public
A56: PRO-056 | B56: COL-008 | C56: GAM-017 | D56: FAM-1775511526523 | E56: LICHEN | F56: Conçu pour l'été québécois. Formulé pour nettoyer sans compromis, coco et ricin génèrent une mousse abondante qui rince la chaleur et la transpiration. | G56: Savon d'été rafraîchissant. Formulé avec olive, coco et ricin pour une mousse généreuse. Spiruline naturelle, senteur de sous-bois après la pluie. | H56: #7A9B76 | I56: 0.06 | J56: 1 | K56: 42 | M56: 1-1.5 c. à thé Spiruline / 1-1.5 c. à thé Spiruline dispersée dans huile | P56: public
A57: PRO-060 | B57: COL-008 | C57: GAM-017 | D57: FAM-1775511526523 | E57: NORDET | F57: Conçu pour affronter la rigueur de l'hiver québécois. Formulé avec karité, olive et amande douce, ce savon surgras 10% protège intensément les peaux agressées par le froid. | G57: Pour ceux qui ne négocient pas avec l'hiver. | H57: #2C4A6B | I57: 0.1 | J57: 6 | K57: 42 | M57: Karité + indigo accélèrent la trace / 6g Flocons d'avoine mixés fins = 1 c. à soupe / 4.5g Miel = 1 c. à thé / 1.5-2 c. à thé Indigo dispersé dans huile 30 min avant | P57: public
A58: PRO-004 | B58: COL-001 | C58: GAM-001 | E58: BOIS DE CARACTÈRE | F58: Il y a des savons qu'on remarque avant même de les toucher. Bois de caractère s'impose avec son graphisme tranché, gris profond et blanc pur, comme une signature. | G58: L'élégance brute de la forêt. Notes boisées et épicées pour une force tranquille. | H58: #363636 | I58: 0.08 | J58: 9 | K58: 28 | M58: ¾ Charbon activé végétal = 1 à 2 c. à thé / ¼ blanc / ¾ → Charbon activé végétal / Couleur gris foncé et blanc, effet graphique | N58: https://res.cloudinary.com/dfasrauyy/image/upload/v1773448451/Boisdecaractere_hbi5xd.jpg | O58: https://res.cloudinary.com/dfasrauyy/image/upload/v1773448369/Boisdecaracterenoel_tww5tv.jpg | P58: public | Q58: COL-008
A59: PRO-012 | B59: COL-001 | C59: GAM-001 | E59: BORÉAL | F59: Un savon qui semble né entre la lumière pâle du Nord et la respiration profonde des forêts anciennes. | G59: C'est la rencontre entre la fraîcheur des grands espaces et la chaleur intime du foyer. | H59: #7F6811 | I59: 0.08 | J59: 9 | K59: 28 | M59: 10g Argile jaune = 3 c. à thé / 11g Charbon activé végétal = 1 c. à thé / Moitié Sunset yellow et moitié Matcha | N59: https://res.cloudinary.com/dfasrauyy/image/upload/v1773418760/Bor%C3%A9al_iemqim.jpg | O59: https://res.cloudinary.com/dfasrauyy/image/upload/v1773418760/BorealNoel_bgg7as.jpg | P59: public | Q59: COL-008
A60: PRO-031 | B60: COL-001 | C60: GAM-001 | E60: CLUB PRIVÉ | F60: Il y a des savons qui racontent une histoire avant même d'être utilisés. Club privé s'annonce avec ses marbrures crème et chocolat, son parfum de tabac blond et de bois ambrés. | G60: Une vanille suave traversée d'un souffle de cigare. | H60: #6B5229 | I60: 0.08 | J60: 9 | K60: 28 | M60: **Version courte :** Une vanille suave traversée d'un souffle de cigare. | N60: https://res.cloudinary.com/dfasrauyy/image/upload/v1773449731/Clubprive_vatlos.jpg | O60: https://res.cloudinary.com/dfasrauyy/image/upload/v1773449731/Clubprive_vatlos.jpg | P60: public | Q60: COL-008
A61: PRO-032 | B61: COL-001 | C61: GAM-001 | E61: DÉLICAT | F61: Pivoine et lavande se rencontrent dans une danse florale toute en délicatesse. L'argile blanche purifie en douceur, le thé vert protège. | G61: Pivoine et Lavande. L'élégance d'un voile parfumé. | H61: #AF99A4 | I61: 0.08 | J61: 9 | K61: 28 | M61: Fleurs de lavande sur le dessus | N61: https://res.cloudinary.com/dfasrauyy/image/upload/v1773418760/D%C3%A9licat_vdewef.jpg | O61: https://res.cloudinary.com/dfasrauyy/image/upload/v1773418761/DelicatNoel_b8setp.jpg | P61: public
A62: PRO-033 | B62: COL-001 | C62: GAM-001 | E62: DOUCE PENSÉE | F62: Un bouquet déposé sur la peau. Le géranium rosat équilibre, le ylang-ylang enveloppe d'une chaleur florale presque tropicale. | G62: Savon qui apaise l'esprit autant qu'il embellit la peau, un bouquet délicat déposé sur le cœur. | H62: #E76877 | I62: 0.08 | J62: 9 | K62: 28 | M62: 17.5g Argile rose = 5 c. à thé / Pétales de roses sur le dessus / ¼ blanc, ¾ rose, mélanger à la main | N62: https://res.cloudinary.com/dfasrauyy/image/upload/v1773418761/Doucepensee_jgnf8a.jpg | O62: https://res.cloudinary.com/dfasrauyy/image/upload/v1773418761/DoucepenseeNoel_tygoxv.jpg | P62: public
A63: PRO-040 | B63: COL-001 | C63: GAM-001 | E63: ÉCLAT DE MER | F63: Fraîcheur marine et citronnée, relevée d'un souffle de menthe poivrée. Un savon qui respire l'air salin, la clarté de l'horizon et la liberté des vagues. | G63: Une mousse claire qui réveille la peau comme un matin au bord de l'océan. | H63: #32EDFF | I63: 0.08 | J63: 9 | K63: 28 | M63: Couleur sarcelle / 11g Argile blanche = 1 c. à table / ~300g éclats de savon Brise des lagunes | N63: https://res.cloudinary.com/dfasrauyy/image/upload/v1773448653/Eclatdemer_gn5fap.jpg | O63: https://res.cloudinary.com/dfasrauyy/image/upload/v1773448370/Eclatdemernoel_tyev2l.jpg | P63: public
A64: PRO-047 | B64: COL-001 | C64: GAM-001 | E64: ÉTREINTE GOURMANDE | F64: L'avoine apaise, l'amande nourrit, le miel retient l'eau et la douceur. Ensemble ils forment une recette presque comestible, généreuse et réconfortante comme un matin de dimanche. | G64: La transparence d'une caresse. Avoine et miel enlacés, l'amande en lumière. | H64: #A4894A | I64: 0.08 | J64: 9 | K64: 28 | M64: 22g Avoine colloïdale = 2 c. à table / 22g Amande moulue = 2 c. à table / 22g Miel = 2 c. à table / Flocons d'avoine et amande sur le dessus / Moitié blanc, moitié or | N64: https://res.cloudinary.com/dfasrauyy/image/upload/v1773418762/etreinte_nknqua.jpg | O64: https://res.cloudinary.com/dfasrauyy/image/upload/v1773418762/etreinteNoel_szipsq.jpg | P64: public
A65: PRO-048 | B65: COL-001 | C65: GAM-001 | E65: FEU D'AUTOMNE | F65: Quand les feuilles virent au cuivre et que l'air sent la résine, Feu d'automne arrive. La canneberge apporte son acidité lumineuse, le pin blanc sa fraîcheur boisée. | G65: Teintes cuivrées de canneberge, résine de pin blanc et essence de romarin. L'âme des forêts automnales dans un savon vibrant et vivifiant. | H65: #FC6B33 | I65: 0.08 | J65: 9 | K65: 28 | M65: Romarin sur le dessus en petite quantité | N65: https://res.cloudinary.com/dfasrauyy/image/upload/v1773448368/Feudautomne_etjdou.jpg | O65: https://res.cloudinary.com/dfasrauyy/image/upload/v1773449076/Feudautomnenoel_fmh0ss.jpg | P65: public
A66: PRO-054 | B66: COL-001 | C66: GAM-001 | E66: JARDIN DE ROSES | F66: La rose est l'ingrédient le plus ancien du soin de la peau. Ici, elle est partout, dans l'huile, dans la poudre de pétales, dans l'Argile rouge qui illumine. | G66: L'essence même de la rose dans sa plus belle simplicité. Délicate et envoûtante. | H66: #9E3E3E | I66: 0.08 | J66: 9 | K66: 28 | M66: 6-12g Pétales de rose en poudre = 1-2 c. à table / 11-22g Argile rouge = 1-2 c. à table / Une rose à ajouter à chaque savon à la fin | N66: https://res.cloudinary.com/dfasrauyy/image/upload/v1773448370/Jardideroses_c0mjii.jpg | O66: https://res.cloudinary.com/dfasrauyy/image/upload/v1773448369/Eclatderosenoel_nliqmx.jpg | P66: public
A67: PRO-061 | B67: COL-001 | C67: GAM-001 | E67: NUAGE DE LAVANDE | F67: La lavande n'a pas besoin de complices. Elle arrive, elle apaise, elle installe une quiétude douce et profonde. | G67: Un champ de lavande, le soir. Rien de plus, rien de moins. | H67: #7F68CA | I67: 0.08 | J67: 9 | K67: 28 | M67: 14g Argile blanche = 4 c. à thé / Moitié blanc et moitié lavande | N67: https://res.cloudinary.com/dfasrauyy/image/upload/v1773418762/Nuagedelavande_kwncrq.jpg | P67: public
A68: PRO-065 | B68: COL-002 | C68: GAM-002 | E68: PETIT NUAGE BONBON | F68: Un savon espiègle et joyeux, comme un éclat de rire qui s'envole. Sa mousse orange libère une odeur de gomme balloune, sucrée et légère. | G68: Un nuage espiègle et sucré, gomme balloune et rires d'enfants dans une mousse joyeuse. | H68: #B64679 | I68: 0.1 | J68: 9 | K68: 28 | M68: 1 c. à thé argile blanche ou rose = 5g | N68: https://res.cloudinary.com/dfasrauyy/image/upload/v1773083581/univers-caresse/produits/ywvtdsbkjhww65hyhrcv.jpg | O68: https://res.cloudinary.com/dfasrauyy/image/upload/v1773083581/univers-caresse/produits/ywvtdsbkjhww65hyhrcv.jpg | P68: public
A69: PRO-034 | B69: COL-006 | C69: GAM-012 | E69: DOUCEUR DES ÎLES | F69: Ce shampoing solide Hydraboucle enveloppe les cheveux d'une hydratation généreuse inspirée des îles lointaines. | G69: Les boucles s'imprègnent de chaleur exotique, comme caressées par des vents tropicaux et les fruits solaires. | H69: #CF8E56 | J69: 1 | K69: 0 | M69: Ce savon est crème / Vérifier si hydrolat | P69: public
A70: PRO-013 | B70: COL-006 | C70: GAM-012 | E70: BOTANICA | F70: Les boucles se dessinent, souples et rebondies, comme réveillées par la rosée d'un matin paisible, bercées par le parfum délicat de la lavande. | G70: Les boucles s'ancrent dans la force des plantes, retrouvant vigueur et harmonie au cœur de la nature. | H70: #547956 | J70: 1 | K70: 0 | M70: Ce savon est beige | N70: https://res.cloudinary.com/dfasrauyy/image/upload/v1773084252/univers-caresse/produits/ftivtqm8akpeeij6zdxg.jpg | P70: public
A71: PRO-071 | B71: COL-006 | C71: GAM-010 | E71: PURE HARMONIE | F71: Ce shampoing solide Équilibra nettoie en douceur sans brusquer le cuir chevelu. La lavande apaise, l'avoine adoucit, le shikakaï démêle naturellement. | G71: La lavande apaise, l'avoine équilibre. Un souffle de douceur pour les cheveux de tous les jours. | H71: #2387FF | J71: 1 | K71: 0 | M71: Ce savon est brun | N71: https://res.cloudinary.com/dfasrauyy/image/upload/v1773084403/univers-caresse/produits/yihx6ik4giouqmror9qx.png | P71: public
A72: PRO-046 | B72: COL-008 | C72: GAM-017 | D72: FAM-1775511526523 | E72: ESKER | F72: Conçu pour le printemps nordique. Formulé léger, olive et tournesol oléique nettoient sans alourdir, coco et ricin créent une mousse fraîche qui rince l'hiver. | G72: Savon de printemps léger. Formulé avec olive, coco et ricin pour fraîcheur et mousse douce. Spiruline et indigo évoquent l'eau glaciaire. Senteur végétale de sauge, petitgrain et bergamote. | H72: #7AAFAF | I72: 0.07 | J72: 6 | K72: 42 | M72: ½ c. à thé Spiruline + ½ c. à thé Indigo / ½ c. à thé Spiruline + ½ c. à thé Indigo — dispersé dans huile (couleur turquoise) | P72: public
A73: PRO-039 | B73: COL-007 | C73: GAM-014 | E73: ÉCLAT CITRONNÉ | F73: Dans la continuité de notre philosophie, Éclat citronné apporte la même authenticité à l'évier. Ce pain solide mousse généreusement au contact de l'eau et de l'éponge. | G73: Un cake dégraissant au citron, efficace et naturel. Une longévité exceptionnelle qui remplace plusieurs flacons. | H73: #FFF816 | J73: 1 | K73: 0 | M73: **Version courte :** Un cake dégraissant au citron, efficace et naturel. Une longévité exceptionnelle qui remplace plusieurs flacons. | P73: public
A74: PRO-038 | B74: COL-007 | C74: GAM-015 | E74: EAU DE LINGE SÉRÉNITÉ PURE | F74: Il y a des parfums qui apaisent avant même qu'on les nomme. Sérénité Pure marie la lavande à la fraîcheur du linge propre. | G74: La douceur de la lavande sur un fond de linge propre — une sérénité textile, du matin au soir. | H74: #74df5b | I74: 0 | J74: 1 | K74: 0 | M74: Recette originale : 110 ml alcool 70%, 380 ml eau, 80-100 gouttes HE | P74: public
A75: PRO-035 | B75: COL-007 | C75: GAM-015 | E75: GRAND AIR | F75: Fermez les yeux et respirez. Le citron éclate, l'eucalyptus ouvre l'espace, la menthe arrive comme une brise sur les draps encore chauds du repassage. | G75: Un souffle d'air pur sur vos tissus — citron, eucalyptus et menthe pour un linge qui sent le grand dehors. | H75: #68dedf | J75: 1 | K75: 0 | M75: Recette originale : 110 ml alcool 70%, 380 ml eau, 80-100 gouttes HE | P75: public
A76: PRO-036 | B76: COL-007 | C76: GAM-015 | E76: EAU DE LINGE LAVANDE | F76: Le linge comme une seconde peau. Vaporisée sur vos tissus avant ou après le repassage, cette eau délicatement parfumée prolonge la fraîcheur. | G76: Une eau délicatement parfumée qui dépose sur vos tissus un sillage doux et naturel, du matin au soir. | H76: #7400e7 | J76: 1 | K76: 0 | M76: Recette originale : 110 ml alcool 70%, 380 ml eau, 80-100 gouttes HE | P76: public
A77: PRO-005 | B77: COL-004 | C77: GAM-005 | E77: BORÉAL | F77: Fermez les yeux et laissez l'effervescence vous emporter. Boréal plonge le bain dans une atmosphère forestière et nordique. | G77: Le grand air du Nord dans un bain effervescent — bois, verdure et musc pour une détente profonde. | H77: #7F6811 | J77: 3 | K77: 0 | M77: 10g Eau = 2 c. à thé / 45g Huile végétale amande douce = 3 c. à table / 6g fleurs = 1 c. à table / Colorant ⚠️ à confirmer avec Chantal / Musc blanc à confirmer avec Chantal / 6g fleurs si désiré | P77: public
A78: PRO-037 | B78: COL-007 | C78: GAM-015 | E78: LESSIVE FRAÎCHE | F78: Lessive Fraîche capture ce parfum unique du linge qui a séché dehors, bercé par le vent, chauffé par le soleil. | G78: L'odeur du linge séché au grand air — comme si la corde à linge avait tout fait le travail. | H78: #ce8fe7 | J78: 1 | K78: 0 | M78: Recette originale : 110 ml alcool 70%, 380 ml eau, 80-100 gouttes HE | P78: public
A79: PRO-019 | B79: COL-007 | C79: GAM-013 | E79: LESSIVE FRAÎCHE | F79: L'atmosphère en bouteille. Ce spray délicat transforme instantanément l'air de votre intérieur en une invitation à la détente. | G79: Un souffle délicat qui transforme l'air de votre intérieur. | H79: #ce8fe7 | J79: 5 | K79: 0 | M79: Recette originale : 60 ml alcool 70%, 190 ml eau, 15 gouttes HE | P79: public
A80: PRO-022 | B80: COL-007 | C80: GAM-016 | E80: BRISE DES LAGUNES | J80: 1 | K80: 0 | M80: La quantité par lot dépend du format de contenant choisi. | P80: public

Sheet  Gammes_Ingredients_v2
A1: GAM-id | B1: ING-id | C1: nom_ingredient | D1: quantite_g
A2: GAM-1775518159265 | B2: ING-132 | C2: Saindoux | D2: 2500
A3: GAM-1775518159265 | B3: ING-004 | C3: Eau | D3: 1000
A4: GAM-1775518159265 | B4: ING-005 | C4: Soude caustique (NaOH) | D4: 340
A5: GAM-1775518159265 | B5: ING-051 | C5: HE sapin | D5: 40
A6: GAM-1775518159265 | B6: ING-014 | C6: Argile blanche | D6: 15
A7: GAM-1775518159265 | B7: ING-133 | C7: Sel | D7: 15
A8: GAM-001 | B8: ING-002 | C8: Huile de tournesol oléique | D8: 325
A9: GAM-001 | B9: ING-006 | C9: Huile de coco | D9: 260
A10: GAM-001 | B10: ING-004 | C10: Eau | D10: 184
A11: GAM-001 | B11: ING-005 | C11: Soude caustique (NaOH) | D11: 92
A12: GAM-001 | B12: ING-003 | C12: Beurre de karité | D12: 65
A13: GAM-002 | B13: ING-001 | C13: Huile d'olive | D13: 250
... A23: GAM-003 | B23: ING-005 | C23: Soude caustique (NaOH) | D23: 98
F24: GAM-004
F25: GAM-005
F26: GAM-006
F27: GAM-007
F28: GAM-008
F29: GAM-009
F30: GAM-010
F31: GAM-011
F32: GAM-012
F33: GAM-013
F34: GAM-014
F35: GAM-015
... F41: GAM-1775518159265

Sheet Produits_Formats_v2
A1: PRO-id | B1: poids | C1: unite | D1: prix_vente | E1: EMB-id
A2: PRO-028 | B2: 72 | C2: g | D2: 7 | G2: =VLOOKUP(A2,Produits_v2!A:C,2,FALSE) -> COL-003 | H2: =VLOOKUP(G2,Collections_v2!A:C,2,FALSE) -> 3 | I2: =VLOOKUP(G2,Collections_v2!A:C,3,FALSE) -> CAPRIN | J2: =VLOOKUP(A2,Produits_v2!A:E,5,FALSE) -> CAPRICE FRAISÉ
A3: PRO-029 | B3: 72 | C3: g | D3: 7 | G3: =VLOOKUP(A3,Produits_v2!A:C,2,FALSE) -> COL-003 | H3: =VLOOKUP(G3,Collections_v2!A:C,2,FALSE) -> 3 | I3: =VLOOKUP(G3,Collections_v2!A:C,3,FALSE) -> CAPRIN | J3: =VLOOKUP(A3,Produits_v2!A:E,5,FALSE) -> CERISE DE VELOURS
A4: PRO-042 | B4: 90 | C4: g | D4: 7 | G4: =VLOOKUP(A4,Produits_v2!A:C,2,FALSE) -> COL-001 | H4: =VLOOKUP(G4,Collections_v2!A:C,2,FALSE) -> 1 | I4: =VLOOKUP(G4,Collections_v2!A:C,3,FALSE) -> SAPONICA | J4: =VLOOKUP(A4,Produits_v2!A:E,5,FALSE) -> ÉCLAT TROPICAL
A5: PRO-043 | B5: 72 | C5: g | D5: 7 | G5: =VLOOKUP(A5,Produits_v2!A:C,2,FALSE) -> COL-003 | H5: =VLOOKUP(G5,Collections_v2!A:C,2,FALSE) -> 3 | I5: =VLOOKUP(G5,Collections_v2!A:C,3,FALSE) -> CAPRIN | J5: =VLOOKUP(A5,Produits_v2!A:E,5,FALSE) -> ÉCLOSION DE SOIE
A6: PRO-052 | B6: 125 | C6: g | D6: 7 | G6: =VLOOKUP(A6,Produits_v2!A:C,2,FALSE) -> COL-005 | H6: =VLOOKUP(G6,Collections_v2!A:C,2,FALSE) -> 5 | I6: =VLOOKUP(G6,Collections_v2!A:C,3,FALSE) -> ÉPURE | J6: =VLOOKUP(A6,Produits_v2!A:E,5,FALSE) -> HERBE DOUCE
A7: PRO-079 | B7: 330 | C7: g | D7: 30 | G7: =VLOOKUP(A7,Produits_v2!A:C,2,FALSE) -> COL-008 | H7: =VLOOKUP(G7,Collections_v2!A:C,2,FALSE) -> 8 | I7: =VLOOKUP(G7,Collections_v2!A:C,3,FALSE) -> LUI | J7: =VLOOKUP(A7,Produits_v2!A:E,5,FALSE) -> L'INSTANT DU BARBIER
A8: PRO-079 | B8: 200 | C8: g | D8: 20 | G8: =VLOOKUP(A8,Produits_v2!A:C,2,FALSE) -> COL-008 | H8: =VLOOKUP(G8,Collections_v2!A:C,2,FALSE) -> 8 | I8: =VLOOKUP(G8,Collections_v2!A:C,3,FALSE) -> LUI | J8: =VLOOKUP(A8,Produits_v2!A:E,5,FALSE) -> L'INSTANT DU BARBIER
A9: PRO-058 | B9: 125 | C9: g | D9: 7 | G9: =VLOOKUP(A9,Produits_v2!A:C,2,FALSE) -> COL-005 | H9: =VLOOKUP(G9,Collections_v2!A:C,2,FALSE) -> 5 | I9: =VLOOKUP(G9,Collections_v2!A:C,3,FALSE) -> ÉPURE | J9: =VLOOKUP(A9,Produits_v2!A:E,5,FALSE) -> MOUSSE D'ESPRESSO
A10: PRO-059 | B10: 125 | C10: g | D10: 7 | G10: =VLOOKUP(A10,Produits_v2!A:C,2,FALSE) -> COL-005 | H10: =VLOOKUP(G10,Collections_v2!A:C,2,FALSE) -> 5 | I10: =VLOOKUP(G10,Collections_v2!A:C,3,FALSE) -> ÉPURE | J10: =VLOOKUP(A10,Produits_v2!A:E,5,FALSE) -> MURMURE D'OLIVA
A11: PRO-062 | B11: 72 | C11: g | D11: 7 | G11: =VLOOKUP(A11,Produits_v2!A:C,2,FALSE) -> COL-003 | H11: =VLOOKUP(G11,Collections_v2!A:C,2,FALSE) -> 3 | I11: =VLOOKUP(G11,Collections_v2!A:C,3,FALSE) -> CAPRIN | J11: =VLOOKUP(A11,Produits_v2!A:E,5,FALSE) -> ORANGE SAUVAGE
A12: PRO-063 | B12: 125 | C12: g | D12: 7 | G12: =VLOOKUP(A12,Produits_v2!A:C,2,FALSE) -> COL-009 | H12: =VLOOKUP(G12,Collections_v2!A:C,2,FALSE) -> 9 | I12: =VLOOKUP(G12,Collections_v2!A:C,3,FALSE) -> ANIMA | J12: =VLOOKUP(A12,Produits_v2!A:E,5,FALSE) -> PATTES BLANCHES
A13: PRO-070 | B13: 72 | C13: g | D13: 7 | G13: =VLOOKUP(A13,Produits_v2!A:C,2,FALSE) -> COL-003 | H13: =VLOOKUP(G13,Collections_v2!A:C,2,FALSE) -> 3 | I13: =VLOOKUP(G13,Collections_v2!A:C,3,FALSE) -> CAPRIN | J13: =VLOOKUP(A13,Produits_v2!A:E,5,FALSE) -> POMME D'ÉMERAUDE
... A36: PRO-049 | B36: 72 | C36: g | D36: 7 | G36: =VLOOKUP(A36,Produits_v2!A:C,2,FALSE) -> COL-003 | H36: =VLOOKUP(G36,Collections_v2!A:C,2,FALSE) -> 3 | I36: =VLOOKUP(G36,Collections_v2!A:C,3,FALSE) -> CAPRIN | J36: =VLOOKUP(A36,Produits_v2!A:E,5,FALSE) -> FRAÎCHEUR DE MELON
A37: PRO-074 | B37: 125 | C37: g | D37: 7
A38: PRO-004 | B38: 90 | C38: g | D38: 7
A39: PRO-032 | B39: 90 | C39: g | D39: 7
A40: PRO-033 | B40: 90 | C40: g | D40: 7
A41: PRO-040 | B41: 90 | C41: g | D41: 7
A42: PRO-047 | B42: 90 | C42: g | D42: 7
A43: PRO-048 | B43: 90 | C43: g | D43: 7
A44: PRO-054 | B44: 90 | C44: g | D44: 7
A45: PRO-061 | B45: 90 | C45: g | D45: 7
A46: PRO-065 | B46: 75 | C46: g | D46: 5
A47: PRO-034 | B47: 90 | C47: g | D47: 10
A48: PRO-013 | B48: 90 | C48: g | D48: 10
... A52: PRO-039 | B52: 200 | C52: g | D52: 15
A53: PRO-038 | B53: 500 | C53: ml
A54: PRO-035 | B54: 500 | C54: ml | D54: 0
A55: PRO-036 | B55: 500 | C55: ml | D55: 0
A56: PRO-037 | B56: 500 | C56: ml | D56: 0
A57: PRO-019 | B57: 500 | C57: ml
A58: PRO-022 | B58: 10 | C58: g | D58: 1
A59: PRO-022 | B59: 135 | C59: g | D59: 8
A60: PRO-022 | B60: 240 | C60: g | D60: 15
A61: PRO-023 | B61: 10 | C61: g | D61: 1
A62: PRO-023 | B62: 135 | C62: g | D62: 8
A63: PRO-023 | B63: 240 | C63: g | D63: 15
A64: PRO-012 | B64: 90 | C64: g | D64: 7
A65: PRO-031 | B65: 90 | C65: g | D65: 7
A66: PRO-014 | B66: 90 | C66: g | D66: 7
A67: PRO-072 | B67: 95 | C67: g | D67: 19
A68: PRO-030 | B68: 85 | C68: g | D68: 10

Sheet Produits_Ingredients_v2
A1: PRO-id | B1: ING-id | C1: nom_ingredient | D1: quantite_g
A2: PRO-001 | B2: ING-107 | C2: Allantoine | D2: 4
A3: PRO-001 | B3: ING-098 | C3: Arôme cerise | D3: 0.6
A4: PRO-001 | B4: ING-089 | C4: Arôme de fraises | D4: 0.6
A5: PRO-001 | B5: ING-003 | C5: Beurre de karité | D5: 30
A6: PRO-001 | B6: ING-013 | C6: Beurre de mangue | D6: 14
A7: PRO-001 | B7: ING-091 | C7: Cire de carnauba | D7: 20
A8: PRO-001 | B8: ING-080 | C8: Huile de calendula | D8: 25
A9: PRO-001 | B9: ING-010 | C9: Huile végétale jojoba | D9: 25
A10: PRO-001 | B10: ING-104 | C10: Mica rose-rouge | D10: 1.5
A11: PRO-001 | B11: ING-092 | C11: Vitamine E | D11: 1.5
A12: PRO-002 | B12: ING-089 | C12: Arôme de fraises | D12: 0.5
A13: PRO-002 | B13: ING-003 | C13: Beurre de karité | D13: 30
... A578: PRO-030 | B578: ING-130 | C578: Poudre ortie | D578: 5

Sheet Emballages_v2
A1: EMB-id | B1: nom | C1: type

Sheet Lots_v2
A1: LOT-id | B1: PRO-id | C1: multiplicateur | D1: nb_unites | E1: date_fabrication | F1: date_disponibilite | G1: cout_ingredients | H1: cout_emballages | I1: cout_revient_total | J1: cout_par_unite | K1: statut | L1: format_poids | M1: format_unite
A2: LOT-1775524552326 | B2: PRO-048 | C2: 1 | D2: 1 | E2: 46023 | F2: 46051 | G2: 0 | H2: 0 | I2: 0 | J2: 0 | K2: en_cure | L2: 95 | M2: g

Sheet Ingredients_INCI_v2
A1: ING-id | B1: CAT-id | C1: nom_fournisseur | D1: nom_UC | E1: INCI | F1: nom_botanique | G1: source | H1: note_olfactive | I1: statut | J1: date_ajout
A2: ING-001 | B2: CAT-007 | C2: Huile végétale Olive | D2: Huile d'olive | E2: Olea europaea oil | G2: PA | I2: ✅ Validé | J2: 46109
A3: ING-002 | B3: CAT-007 | C3: Huile végétale Tournesol | D3: Huile de tournesol oléique | E3: Helianthus Annuus (Sunflower) Seed Oil (High Oleic, 80%) | G3: PA | I3: ✅ Validé | J3: 46109
A4: ING-003 | B4: CAT-002 | C4: Beurre Karité | D4: Beurre de karité | E4: Butyrospermum parkii (Shea) Butter | G4: PA | I4: ✅ Validé | J4: 46109
A5: ING-004 | B5: CAT-011 | C5: Eau | D5: Eau | E5: Aqua | G5: PA | I5: ✅ Validé | J5: 46109
A6: ING-005 | B6: CAT-012 | C6: Soude Caustique (NaOH) | D6: Soude caustique (NaOH) | E6: Sodium Hydroxide | G6: PA | I6: ✅ Validé | J6: 46112
A7: ING-006 | B7: CAT-007 | C7: Huile végétale Noix de Coco | D7: Huile de coco | E7: Cocos nucifera (Coconut) Oil | G7: PA | I7: ✅ Validé | J7: 46111
A8: ING-007 | B8: CAT-007 | C8: Huile végétale Amande douce | D8: Huile végétale amande douce | E8: Prunus amygdalus | G8: PA | I8: ✅ Validé | J8: 46109
A9: ING-008 | B9: CAT-007 | C9: Huile végétale Ricin | D9: Huile de ricin | E9: Ricinus Communis (Castor) Seed Oil | G9: PA | I9: ✅ Validé | J9: 46109
A10: ING-009 | B10: CAT-007 | C10: Huile végétale Argan | D10: Huile d'argan | E10: Argania spinosa | G10: PA | I10: ✅ Validé | J10: 46109
A11: ING-010 | B11: CAT-007 | C11: Huile végétale Jojoba | D11: Huile végétale jojoba | E11: Simmondsia Sinensis | G11: PA | I11: ✅ Validé | J11: 46109
A12: ING-011 | B12: CAT-007 | C12: Huile végétale Pépins de raisin | D12: Huile végétale de pépins de raisin | E12: Vitis vinifera (grape) seed oil | G12: PA | I12: ✅ Validé | J12: 46109
A13: ING-012 | B13: CAT-002 | C13: Beurre de Cacao brut | D13: Beurre de cacao brut | E13: Theobroma cacao (Cocoa) Seed Butter | G13: PA | I13: ✅ Validé | J13: 46109
A14: ING-013 | B14: CAT-002 | C14: Beurre de mangue | D14: Beurre de mangue | E14: Mangifera indica seed butter | F14: Mangifera indica | G14: MH | I14: ✅ Validé | J14: 46109
A15: ING-014 | B15: CAT-001 | C15: Argile blanche (Kaolin) | D15: Argile blanche | E15: Kaolin (Bolus Alba) | G15: PA | I15: ✅ Validé | J15: 46109
A16: ING-015 | B16: CAT-001 | C16: Argile rose | D16: Argile rose | E16: Kaolin (Bolus Alba) / Illite (Bolus Alba) | G16: PA | I16: ✅ Validé | J16: 46109
A17: ING-016 | B17: CAT-001 | C17: Argile rouge | D17: Argile rouge | E17: Illite red clay | G17: PA | I17: ✅ Validé | J17: 46109
A18: ING-017 | B18: CAT-001 | C18: Argile multani mitti | D18: Argile Multani mutti | E18: Solum fullonum | G18: PA | I18: ✅ Validé | J18: 46109
A19: ING-018 | B19: CAT-004 | C19: Charbon activé végétal | D19: Charbon activé végétal | E19: Activated charcoal | G19: PA | I19: ✅ Validé | J19: 46109
A20: ING-019 | B20: CAT-005 | C20: Smoothie aux mûres fragrance | D20: Smoothie aux mûres (fragrance) | E20: Fragrance | G20: PA | I20: ✅ Validé | J20: 46109
A21: ING-020 | B21: CAT-005 | C21: Gomme balloune fragrance | D21: Gomme balloune (fragrance) | E21: Fragrance | G21: PA | I21: ✅ Validé | J21: 46109
A22: ING-021 | B22: CAT-005 | C22: Poudre de bébé fragrance | D22: Fragrance poudre de bébé | E22: Fragrance | G22: PA | I22: ✅ Validé | J22: 46109
A23: ING-022 | B23: CAT-001 | C23: Argile verte | D23: Argile verte | E23: Montmorillonite | G23: MH | I23: ✅ Validé | J23: 46109
A24: ING-023 | B24: CAT-008 | C24: Huile aromatique O Masculin | D24: HA O'masculin | E24: Cedrus Atlantica (Atlas Cedar) Wood Oil; Jasminum Grandiflorum (Jasmine) Flower Oil; Michelia Alba (Magnolia) Flower Oil; Pogostemon Cablin (Patchouli) Leaf Oil; Rosmarinus Officinalis (Rosemary) Leaf Oil | G24: PA | I24: ✅ Validé | J24: 46109
A25: ING-024 | B25: CAT-012 | C25: Sodium cocoyl isethionate (SCI) | D25: SCI | E25: Sodium cocoyl isethionate | G25: MH | I25: ✅ Validé | J25: 46112
A26: ING-025 | B26: CAT-006 | C26: Fleurs de lavande | D26: Fleurs de lavande | E26: Lavandula angustifolia (lavender) flower | G26: PA | I26: ✅ Validé | J26: 46109
A27: ING-026 | B27: CAT-006 | C27: Pétales de roses | D27: Pétales de roses | E27: Rosa × damascena Flower Powder | F27: Rosa ×damascena | G27: PA | I27: ✅ Validé | J27: 46109
A28: ING-027 | B28: CAT-003 | C28: Cire de Soja | D28: Cire de soya | E28: Soy wax | G28: PA | I28: ✅ Validé | J28: 46109
A29: ING-028 | B29: CAT-012 | C29: Sel d'Epsom | D29: Sel d'Epsom | E29: Magnesium sulfate | G29: MH | I29: ✅ Validé | J29: 46109
A30: ING-029 | B30: CAT-010 | C30: Hydrolat Romarin | D30: Hydrolat romarin | E30: Rosmarinus officinalis Leaf Water | G30: PA | I30: ✅ Validé | J30: 46109
A31: ING-030 | B31: CAT-010 | C31: Hydrolat Lavande | D31: Hydrolat lavande | E31: Lavandula angustifolia (Lavender) Flower Water | G31: PA | I31: ✅ Validé | J31: 46109
A32: ING-031 | B32: CAT-010 | C32: Hydrolat Menthe Poivrée | D32: Hydrolat de menthe poivrée | E32: Mentha piperita (Peppermint) Leaf Water | G32: PA | I32: ✅ Validé | J32: 46109
A33: ING-032 | B33: CAT-006 | C33: Shikakai en poudre | D33: Shikakaï en poudre | E33: Acacia concinna Fruit Powder | G33: PA | I33: ✅ Validé | J33: 46109
A34: ING-033 | B34: CAT-006 | C34: Racine de guimauve en poudre | D34: Poudre de guimauve | E34: Althaea officinalis Root Powder | G34: PA | I34: ✅ Validé | J34: 46109
A35: ING-034 | B35: CAT-006 | C35: Poudre d'orange | D35: Poudre écorce orange | E35: Citrus sinensis | G35: PA | I35: ✅ Validé | J35: 46109
A36: ING-035 | B36: CAT-009 | C36: Huile essentielle Petitgrain bigarade | D36: HE petitgrain | E36: Citrus Aurantium ssp. aurantium (Petitgrain Bigarade) Leaf Oil | F36: Citrus aurantium ssp aurantium | G36: PA | I36: ✅ Validé | J36: 46109
A37: ING-036 | B37: CAT-009 | C37: Huile essentielle Cèdre feuilles | D37: HE cèdre feuilles | E37: thuja occidentalis leaf oil | G37: PA | I37: ✅ Validé | J37: 46109
A38: ING-037 | B38: CAT-009 | C38: Huile essentielle Cèdre atlas | D38: HE cèdre atlas | E38: cedrus atlantica bark oil | G38: PA | I38: ✅ Validé | J38: 46109
A39: ING-038 | B39: CAT-009 | C39: Huile essentielle Palmarosa | D39: HE palmarosa | E39: Cymbopogon Martini (Palmarosa) Oil | F39: Cymbopogon martinii var motia | G39: PA | I39: ✅ Validé | J39: 46109
A40: ING-039 | B40: CAT-009 | C40: Huile essentielle Lavande vraie | D40: HE lavande | E40: lavandula angustifolia (lavender) oil | G40: PA | I40: ✅ Validé | J40: 46109
A41: ING-040 | B41: CAT-009 | C41: Huile essentielle Géranium rosat | D41: HE géranium rosat | E41: pelargonium graveolens flower oil | G41: PA | I41: ✅ Validé | J41: 46109
A42: ING-041 | B42: CAT-009 | C42: Huile aromatique Cèdre bleu | D42: HE cèdre bleu | E42: Cedrus Atlantica (Atlas Cedar) Wood Oil | F42: Cedrus atlantica 'Glauca' | G42: PA | I42: ✅ Validé | J42: 46111
A43: ING-042 | B43: CAT-008 | C43: Huile aromatique Thé vert | D43: HA thé vert | E43: Camellia Sinensis (Green Tea) Leaf Oil | F43: Camellia sinensis | G43: PA | I43: ✅ Validé | J43: 46110
A44: ING-043 | B44: CAT-009 | C44: Huile essentielle Citron | D44: HE citron | E44: citrus limon (lemon) peel oil | G44: PA | I44: ✅ Validé | J44: 46109
A45: ING-044 | B45: CAT-009 | C45: Huile essentielle Menthe poivrée | D45: HE menthe poivrée | E45: Mentha × Piperita (Peppermint) Leaf Oil | F45: Mentha x piperita | G45: PA | I45: ✅ Validé | J45: 46109
A46: ING-045 | B46: CAT-009 | C46: Huile essentielle Orange douce | D46: HE orange douce | E46: Citrus Sinensis (Orange) Peel Oil | F46: Citrus sinensis | G46: PA | I46: ✅ Validé | J46: 46109
A47: ING-046 | B47: CAT-009 | C47: Huile essentielle Patchouli | D47: HE patchouli | E47: Pogostemon Cablin (Patchouli) Leaf Oil | F47: Pogostemon Cablin | G47: PA | I47: ✅ Validé | J47: 46109
A48: ING-047 | B48: CAT-009 | C48: Huile essentielle Eucalyptus Radiata | D48: HE eucalyptus radiata | E48: eucalyptus oil | G48: PA | I48: ✅ Validé | J48: 46109
A49: ING-048 | B49: CAT-009 | C49: Huile essentielle Bergamote | D49: HE bergamote | E49: citrus aurantium bergamia (bergamot) fruit oil | G49: PA | I49: ✅ Validé | J49: 46109
A50: ING-049 | B50: CAT-008 | C50: Huile aromatique Brise de mer | D50: HA brise de mer | E50: Jasminum grandiflorum (Jasmine) Flower Extract; Nelumbo nucifera (Lotus) Flower Extract; Cistus ladaniferus (Cistus) Oil; Santalum album (Sandalwood) Oil; Rosmarinus officinalis (Rosemary) Leaf Oil; Cinnamomum camphora (Ho) Wood Oil; Citrus limon (Lemon) Peel Oil | G50: PA | I50: ✅ Validé | J50: 46109
A51: ING-050 | B51: CAT-009 | C51: Huile essentielle Poivre noir | D51: HE poivre noir | E51: Piper Nigrum (Black Pepper) Fruit Oil | G51: PA | I51: ✅ Validé | J51: 46109
A52: ING-051 | B52: CAT-009 | C52: Sapin Baumier | D52: HE sapin | E52: ABIES BALSAMEA | F52: Abies Balsamea | G52: Arbressence | I52: ✅ Validé | J52: 46109
A53: ING-052 | B53: CAT-008 | C53: Huile aromatique Ylang Ylang | D53: HE ylang-ylang | E53: Cananga Odorata (Ylang Ylang) Flower Oil | F53: Cananga Odorata | G53: PA | I53: ✅ Validé | J53: 46110
A54: ING-053 | B54: CAT-008 | C54: Huile aromatique Pêche | D54: HE pêche | E54: Prunus Persica (Peach) Kernel Oil | F54: Prunus Persica | G54: PA | I54: ✅ Validé | J54: 46110
A55: ING-054 | B55: CAT-009 | C55: Jasmin 100% Absolue | D55: HA jasmin | E55: JASMINUM GRANDIFLORUM | F55: Jasminum grandiflorum | G55: DE | I55: ✅ Validé | J55: 46110
A56: ING-055 | B56: CAT-009 | C56: Huile essentielle Basilic | D56: HE basilic | E56: ocimum basilicum (basil) oil | G56: PA | I56: ✅ Validé | J56: 46110
A57: ING-056 | B57: CAT-009 | C57: Huile essentielle Romarin | D57: HE romarin | E57: rosmarinus officinalis (rosemary) leaf oil | G57: PA | I57: ✅ Validé | J57: 46110
A58: ING-057 | B58: CAT-009 | C58: Pin Blanc | D58: HE pin blanc | E58: Pinus Strobus | G58: Arbressence | I58: ✅ Validé | J58: 46110
A59: ING-058 | B59: CAT-008 | C59: Huile aromatique Pivoine | D59: HA pivoine | E59: Paeonia Lactiflora (Peony) Flower Oil | F59: Paeonia lactiflora | G59: PA | I59: ✅ Validé | J59: 46110
A60: ING-059 | B60: CAT-008 | C60: Huile aromatique Concombre | D60: HA concombre | E60: Cucumis Sativus (Cucumber) Fruit Oil | F60: Cucumis sativus | G60: PA | I60: ✅ Validé | J60: 46110
A61: ING-060 | B61: CAT-008 | C61: Huile aromatique Poire | D61: HA poire | E61: Pyrus Communis (Pear) Fruit Oil | F61: Pyrus communis L. | G61: PA | I61: ✅ Validé | J61: 46110
A62: ING-061 | B62: CAT-008 | C62: Huile aromatique Mangue & Noix de coco | D62: HA mangue-coco | E62: Mangifera Indica (Mango) Fruit Oil; Cocos Nucifera (Coconut) Oil | F62: Mangifera indica & Cocos nucifera | G62: PA | I62: ✅ Validé | J62: 46110
A63: ING-062 | B63: CAT-005 | C63: Cigare fragrance | D63: HA cigare | E63: Fragrance | G63: PA | I63: ✅ Validé | J63: 46110
A64: ING-063 | B64: CAT-005 | C64: Agrumes / Romarin fragrance | D64: HA agrumes et romarin | E64: Fragrance | G64: PA | H64: Citron, lime, pamplemousse, orange, romarin | I64: ✅ Validé | J64: 46110
A65: ING-064 | B65: CAT-005 | C65: Vanille fragrance | D65: HA vanille | E65: Fragrance | G65: PA | H65: Vanille | I65: ✅ Validé | J65: 46112
A66: ING-065 | B66: CAT-005 | C66: Thé Matcha fragrance | D66: Matcha | E66: Fragrance | G66: PA | I66: ✅ Validé | J66: 46110
A67: ING-066 | B67: CAT-008 | C67: Huile aromatique Amande amère | D67: HA amande amère | E67: Prunus Amygdalus Dulcis (Sweet Almond) Oil | F67: Prunus amygdalus | G67: PA | I67: ✅ Validé | J67: 46112
A68: ING-067 | B68: CAT-004 | C68: Colorant liquide Rouge | D68: Colorant rouge | E68: Food colouring | G68: PA | I68: ✅ Validé | J68: 46110
A69: ING-068 | B69: CAT-002 | C69: Beurre Karité (Brut) | D69: Beurre Karité (Brut) | E69: Butyrospermum parkii (Shea) Butter | G69: PA | I69: ✅ Validé | J69: 46110
A70: ING-069 | B70: CAT-011 | C70: Miel | D70: Miel | E70: Mel | G70: Manuel | I70: ✅ Validé | J70: 46110
A71: ING-070 | B71: CAT-007 | C71: Huile végétale Rose musquée | D71: Huile de rose | E71: Rosa rubiginosa seed oil | G71: PA | I71: ✅ Validé | J71: 46110
A72: ING-071 | B72: CAT-008 | C72: Huile aromatique Canneberge | D72: HA canneberge | E72: Vaccinium Macrocarpon (Cranberry) Fruit Extract | F72: Vaccinium macrocarpon | G72: PA | I72: ✅ Validé | J72: 46110
A73: ING-072 | B73: CAT-006 | C73: Pétales de roses en poudre | D73: Pétales de rose en poudre | E73: Rosa × damascena Flower Powder | F73: Rosa ×damascena | G73: PA | I73: ✅ Validé | J73: 46110
A74: ING-073 | B74: CAT-006 | C74: Boutons de rose | D74: Rose entière | E74: Rosa damascena Flower | G74: PA | I74: ✅ Validé | J74: 46110
A75: ING-074 | B75: CAT-012 | C75: Avoine colloïdale | D75: Avoine colloïdale | E75: Avena sativa (oat) | G75: PA | I75: ✅ Validé | J75: 46110
A76: ING-075 | B76: CAT-006 | C76: Fleurs immortelles | D76: Fleurs confettis | E76: Helichrysum italicum flower | G76: PA | I76: ✅ Validé | J76: 46110
A77: ING-076 | B77: CAT-006 | C77: Feuilles de romarin | D77: Romarin séché | E77: Rosmarinus officinalis (rosemary) leaf | G77: PA | I77: ✅ Validé | J77: 46110
A78: ING-077 | B78: CAT-012 | C78: Flocons d'avoine | D78: Flocons d'avoine | E78: Avena Sativa Kernel Meal. | G78: IGA | I78: ✅ Validé | J78: 46110
A79: ING-078 | B79: CAT-001 | C79: Argile jaune | D79: Argile jaune | E79: Illite | G79: cocoéco | I79: ✅ Validé | J79: 46110
A80: ING-079 | B80: CAT-012 | C80: Amande moulue | D80: Amande moulue | E80: Prunus Amygdalus Dulcis Seed Meal | G80: iga | I80: ✅ Validé | J80: 46110
A81: ING-080 | B81: CAT-007 | C81: Huile infusée de Calendula | D81: Huile de calendula | E81: Helianthus annuus (sunflower) seed oil (and) Calendula officinalis flower extract | G81: PA | I81: ✅ Validé | J81: 46110
A82: ING-081 | B82: CAT-008 | C82: HE mandarine | D82: HE mandarine | E82: Citrus Reticulata Peel Oil | G82: divers | I82: ✅ Validé | J82: 46111
A83: ING-082 | B83: CAT-005 | C83: musc blanc | D83: Musc blanc | E83: Fragrance | G83: divers | I83: ✅ Validé | J83: 46110
A84: ING-083 | B84: CAT-004 | C84: Colorant PINK | D84: Colorant PINK | E84: Aqua, Sorbitol, Glycerin, Cellulose Gum, CI 45430, Potassium Sorbate | G84: Amazon | I84: ✅ Validé | J84: 46110
A85: ING-084 | B85: CAT-004 | C85: Colorant matcha | D85: Colorant matcha | E85: Aqua, Sorbitol, Glycerin, Cellulose Gum, CI 19140, CI 42090, Potassium Sorbate | G85: amazon | I85: ✅ Validé | J85: 46110
... A88: ING-087 | B88: CAT-004 | C88: Colorant sarcelle | D88: Colorant sarcelle | E88: Aqua, Sorbitol, Glycerin, Cellulose Gum, CI 42090, CI 19140, Potassium Sorbate. | G88: Amazon | I88: ✅ Validé | J88: 46110
A89: ING-088 | B89: CAT-005 | C89: Huile aromatique Pois de senteur | D89: Pois de senteur (fragrance) | E89: Lathyrus Odoratus (Sweet Pea) Flower Oil | F89: Lathyrus odoratus | G89: PA | I89: ✅ Validé | J89: 46111
A90: ING-089 | B90: CAT-013 | C90: Fraise saveur naturelle | D90: Arôme de fraises | E90: Vegetable Oil | G90: PA | I90: ✅ Validé | J90: 46112
A91: ING-090 | B91: CAT-012 | C91: Lait de chèvre en poudre | D91: Lait de chèvre en poudre | E91: Capra hircus (goat) milk powder | G91: Amazone | I91: ✅ Validé | J91: 46111
A92: ING-091 | B92: CAT-003 | C92: Cire de Carnauba | D92: Cire de carnauba | E92: Copernicia Cerifera (carnauba) wax | G92: PA | I92: ✅ Validé | J92: 46111
A93: ING-092 | B93: CAT-011 | C93: Vitamine E | D93: Vitamine E | E93: Tocopherol | G93: PA | I93: ✅ Validé | J93: 46111
A94: ING-093 | B94: CAT-012 | C94: Bicarbonate de soude | D94: Bicarbonate de soude | E94: Sodium bicarbonate | G94: PA | I94: ✅ Validé | J94: 46111
A95: ING-094 | B95: CAT-012 | C95: Fécule de maÏs | D95: Fécule de maïs | E95: Zea mays (corn) starch | G95: PA | I95: ✅ Validé | J95: 46111
A96: ING-095 | B96: CAT-008 | C96: Huile aromatique Melon d'eau | D96: HA melon d'eau | E96: Citrullus Lanatus (Watermelon) Fruit Oil | F96: Citrullus lanatus | G96: PA | I96: ✅ Validé | J96: 46112
A97: ING-096 | B97: CAT-008 | C97: Huile aromatique Pomme verte | D97: HA pomme verte | E97: Malus Sylvestris (Apple) Fruit Oil | F97: Malus sylvestris | G97: PA | I97: ✅ Validé | J97: 46112
A98: ING-097 | B98: CAT-006 | C98: Spiruline en poudre | D98: Spiruline | E98: Spirulina platensis powder | G98: PA | I98: ✅ Validé | J98: 46112
A99: ING-098 | B99: CAT-013 | C99: Arôme cerise | D99: Arôme cerise | E99: FRAGRANCE | G99: amazon | I99: ✅ Validé | J99: 46112
A100: ING-099 | B100: CAT-012 | C100: Cannelle moulue | D100: Cannelle moulue | E100: CINNAMOMUM ZEYLANICUM BARK POWDER | G100: iga | I100: ✅ Validé | J100: 46112
A101: ING-100 | B101: CAT-012 | C101: Clou de girofle moulu | D101: Clou de girofle moulu | E101: EUGENIA CARYOPHYLLUS FLOWER POWDER | G101: iga | I101: ✅ Validé | J101: 46112
A102: ING-101 | B102: CAT-012 | C102: Curcuma | D102: Curcuma | E102: CURCUMA LONGA ROOT POWDER | G102: iga | I102: ✅ Validé | J102: 46112
...

Sheet Scraping_PA_v2
A1: Fournisseur | B1: Nom | C1: Catégorie | D1: INCI | E1: Nom_botanique | F1: Partie_plante | G1: Origine | H1: Methode_production | I1: Chemotype | J1: Culture | K1: Composantes_majoritaires | L1: Point_eclair | M1: Bio | N1: Odeur | O1: NPN | P1: Marque | Q1: URL | R1: Qualite | S1: Statut | T1: Date_scraping | U1: Texte_brut
A2: Pure Arôme | B2: Argile bentonite | C2: Argiles | D2: Sodium bentonite | Q2: https://www.purearome.com/fr/produit/argile-bentonite | T2: 46108
A3: Pure Arôme | B3: Argile blanche (Kaolin) | C3: Argiles | D3: Kaolin (Bolus Alba | Q3: https://www.purearome.com/fr/produit/argile-blanche-kaolin | R3: Propre | T3: 46108 | U3: Argile Kaolin Accueil Produits Argiles Argile blanche (Kaolin) Argile blanche (Kaolin) Sku: KAOLIN En stock Argile blanche (Kaolin) Sku: KAOLIN En stock 5,95 $ CAD Produit non disponible à l'achat en ligne Partager Argile blanche Kaolin Inci : Kaolin (Bolus Alba) CAS : 1332-58-7 Kaolin aussi appelée argile blanche, est naturellement riche en sels minéraux (fer, zinc, silicium, magnésium, potassium, calcium…). Réputée apaisante et purifiante, elle est idéale pour les peaux sèches, irritées et fragiles pour dégonfler la peau et apaiser le feu cutané. Utilisée en masque ou en cataplasme, elle convient parfaitement pour les petits bobos et les irritations. Elle est aussi reconnue pour adoucir la peau ou bien même renforcer les cheveux secs, ont l'emploi également dans la fabrication de savon et shampoing. Pour usage externe seulement
A4: Pure Arôme | B4: Argile ghassoul / rhassoul | C4: Argiles | D4: Marroccan lava clay | Q4: https://www.purearome.com/fr/produit/argile-ghassoul-rhassoul | R4: Propre | T4: 46108 | U4: Argile Ghassoul / Rhassoul Accueil Produits Argiles Argile ghassoul / rhassoul Argile ghassoul / rhassoul Sku: ARGHAS En stock Argile ghassoul / rhassoul Sku: ARGHAS En stock 8,50 $ CAD Produit non disponible à l'achat en ligne Partager Argile Rhassoul du Maroc (Ghassoul) Inci : Marroccan lava clay CAS : 12417-86-6 Véritable &quot;terre qui lave&quot;, le Rhassoul est une argile volcanique récoltée dans la région du Moyen Atlas au Maroc. Il s'utilise pour préparer des shampooings en pâte doux et purifiants grâce à son aptitude exceptionnelle à absorber les impuretés sans irriter la peau. C'est un élément incontournable des rituels du hammam. A la différence des shampooings et savons, le Rhassoul ne contient aucun tensioactif et nettoie selon un processus physique en absorbant les impuretés et les graisses. Il respecte ainsi le film hydrolipidique de la peau et du cheveu et n'irrite pas les glandes sébacées.
A5: Pure Arôme | B5: Argile multani mitti | C5: Argiles | D5: Solum fullonum | Q5: https://www.purearome.com/fr/produit/argile-multani-mitti | R5: Propre | T5: 46108 | U5: Argile Multani Mitti Accueil Produits Argiles Argile multani mitti Argile multani mitti Sku: MULTANI En stock Argile multani mitti Sku: MULTANI En stock 6,50 $ CAD Produit non disponible à l'achat en ligne Partager Argile Multani Mitti Inci : Solum fullonum CAS : 8031-18-3 Cette argile indienne s'utilise en association avec des poudres de plantes pour nettoyer et purifier la peau et les cheveux. Elle fait merveille notamment pour préparer des masques aux poudres ayurvédiques, ou des shampooing pâte "no poo". Particulièrement appréciée par les peaux et cheveux gras, elle élimine en douceur les impuretés et cellules mortes. Elle est aussi connue sous le nom de terre à foulon et peut s'utiliser comme produit ménager écologique pour absorber les taches de gras ou préparer une "pierre d'argile".
A6: Pure Arôme | B6: Argile rose | C6: Argiles | D6: Kaolin (Bolus Alba) / Illite (Bolus Alba) | Q6: https://www.purearome.com/fr/produit/argile-rose | R6: Propre | T6: 46108 | U6: Argile Rose Accueil Produits Argiles Argile rose Argile rose Sku: ARGROSE En stock Argile rose Sku: ARGROSE En stock 8,50 $ CAD Produit non disponible à l'achat en ligne Partager Argile Rose INCI : Kaolin (Bolus Alba) / Illite (Bolus Alba) CAS : 1332-58-7 L'argile Rose Pure arôme est reconnus pour adoucir la peau et renforce les cheveux secs, ont l'emploi également dans la fabrication de savon et shampoing. Apaisante et purifiante, elle est idéale pour les peaux sèches, irritées et fragiles pour dégonfler la peau et apaiser le feu cutané. Utilisée en masque ou en cataplasme, elle convient parfaitement pour les petits bobos et les irritations.
A7: Pure Arôme | B7: Argile rouge | C7: Argiles | D7: Illite red clay | Q7: https://www.purearome.com/fr/produit/argile-rouge | R7: Propre | T7: 46108 | U7: Argile Rouge Accueil Produits Argiles Argile rouge Argile rouge Sku: ARGROU En stock Argile rouge Sku: ARGROU En stock 11,50 $ CAD Produit non disponible à l'achat en ligne Partager Argile Rouge Inci : Illite red clay CAS : 12173-60-3 L'argile rouge est riche en oxyde de fer et en oligo-éléments. Elle fait partie de la famille des illites. L'argile illite rouge minéralise la peau et est idéale pour tout les types de peaux. Elle est idéale pour préparer des masques, cataplasmes, et enveloppements. Cette argile est un indispensable !
A8: Pure Arôme | B8: Argile verte surfine montmorillonite | C8: Argiles | D8: Illite (Bolus Alba | Q8: https://www.purearome.com/fr/produit/argile-verte-surfine-montmorillonite | R8: Propre | T8: 46108 | U8: Argile verte Surfine Montmorillonite Accueil Produits Argiles Argile verte surfine montmorillonite Argile verte surfine montmorillonite Sku: ARVERT En stock Argile verte surfine montmorillonite Sku: ARVERT En stock 9,99 $ CAD Produit non disponible à l'achat en ligne Partager Argile Verte Surfine Montmorillonite Inci : Illite (Bolus Alba) CAS : 1318-93-0 L'argile verte montmorillonite est connue depuis des centaines d'années ; son nom vient de la localité de Montmorillon, dans la Vienne. Notre argile montmorillonite verte surfine est extraite de carrières françaises. Riche en sels minéraux et oligo-éléments et dotée d'une forte capacité d'adsorption, cette argile a des vertus purifiantes sur la peau. Elle s'utilise à merveille pour préparer des soins nettoyants des peaux grasses ou à imperfections et des cuirs chevelus gras ou squameux.
A9: Pure Arôme | B9: Base Beurre de bain moussant | C9: Bases neutres | D9: Glycerin, Aqua, Sorbitol, Sodium Cocoyl Isethionate, Sodium Lauryl Sulfoacetate, Sodium Chloride, Phenoxyethanol, Ethylhexylglycerin. | Q9: https://www.purearome.com/fr/produit/base-beurre-de-bain-moussant | R9: Base | T9: 46108 | U9: Base Beurre de bain moussant Accueil Produits Base Beurre de bain moussant Base Beurre de bain moussant Sku: BEUBMOUSS En stock Base Beurre de bain moussant Sku: BEUBMOUSS En stock 32,95 $ CAD Produit non disponible à l'achat en ligne Partager Base Beurre de Bain Moussant Sans Parabènes et Sans Propylène Glycol Une belle alternative créative pour des bains luxueux Découvrez notre Beurre de Bain Moussant, une base unique et polyvalente pour vos créations cosmétiques. Idéale pour remplacer les bains moussants liquides ou en gel, cette base vous permet de réaliser des textures onctueuses, comme des beurres meringués, avec toutes les fantaisies de couleurs et de confettis que vous pouvez imaginer. Laissez libre cours à votre créativité et créez des produits de bain personnalisés et ludiques ! Caractéristiques : Sans parabènes et sans propylène glycol : Une composition douce pour la peau et respectueuse de l’environnement. Base non parfumée : Ajoutez vos propres arômes pour une expérience sensorielle unique et sur mesure. Texture crémeuse et moussante : Se transforme en une mousse riche et douce, parfaite pour un moment de relaxation au bain Conseils de Création : Cette base est conçue pour être parfumée selon vos préférences. Nous recommandons un dosage d’arôme entre **1 % et 2 % maximum** pour conserver la sécurité et l’intégrité du produit. Pour une touche spéciale, ajoutez des huiles essentielles / fragrances de votre choix. Que vous soyez un entrepreneur en cosmétique naturelle ou un passionné des soins faits maison, cette base Beurre de Bain Moussant apportera une touche luxueuse et créative à votre collection. Ingrédients : Glycerin, Aqua, Sorbitol, Sodium Cocoyl Isethionate, Sodium Lauryl Sulfoacetate, Sodium Chloride, Phenoxyethanol, Ethylhexylglycerin. Fabriqué au Canada Mise en Garde et Conformité : Avant de commercialiser votre produit fini, assurez-vous de respecter toutes les réglementations en vigueur et de soumettre le formulaire de déclaration des cosmétiques requis par Santé Canada. La conformité réglementaire est de votre responsabilité. . **Usage externe uniquement** : Ce produit est destiné à une utilisation externe. Document : Fiche Technique Base Beurre de bain moussant Pure arome Laboratoire.pdf
A10: Pure Arôme | B10: Base crème épaisse – Neutre | C10: Bases neutres | Q10: https://www.purearome.com/fr/produit/base-creme-epaisse-neutre | R10: À valider | T10: 46108 | U10: Base crème épaisse professionnelle – neutre prête à l’emploi Accueil Produits Base crème épaisse – Neutre Base crème épaisse – Neutre Sku: BCREME En stock Base crème épaisse – Neutre Sku: BCREME En stock 32,95 $ CAD Produit non disponible à l'achat en ligne Partager Base crème épaisse – Neutre Cette base crème épaisse est une base cosmétique professionnelle, hautement polyvalente et conçue pour être entièrement personnalisée. Sa texture riche, stable et homogène permet de créer une grande variété de produits : crème mains, crème corporelle, lotion fluide, gel-crème visage, soin parfumé, base massage, et bien plus. Elle ne doit pas être utilisée telle quelle. La base est intentionnellement concentrée pour permettre au client d’ajouter entre 5 à 75 % d’eau distillée selon la texture désirée. Vous pouvez la fluidifier, l’alléger, la doubler en volume ou la rendre encore plus riche selon vos besoins. Formulation douce, hydratante et stable, sans TEA, sans SLS, sans SLES, sans alcool , parfaitement compatible avec les huiles, fragrances, huiles essentielles, actifs liposolubles et hydrosolubles. Ingrédients (formule améliorée) Aqua (Water), Helianthus annuus (Sunflower) Seed Oil, Cetearyl Alcohol, Polysorbate 60, Simmondsia chinensis (Jojoba) Seed Oil, Limnanthes alba (Meadowfoam) Seed Oil, Aloe Barbadensis Leaf Juice, Glycerin, Cetyl Alcohol, Stearic Acid, Palmitic Acid, Tocopherol, Glycine soja (Soybean) Oil, Ascorbic Acid, Potassium Sorbate, Iodopropynyl Butylcarbamate, Diazolidinyl Urea. Caractéristiques techniques Aspect : crème blanche, épaisse, homogène Odeur : neutre Viscosité : élevée (texture crème épaisse) Modulable : peut être diluée avec jusqu’à 75 % d’eau distillée Compatibilité : huiles, actifs, fragrances, HE Qualité : sans TEA, sans alcool, sans SLS/SLES, non testé sur les animaux Conservation : 15–25 °C, à l’abri de l’humidité Provenance : Canada Mode d’emploi NE PAS utiliser la base telle quelle (base concentrée). Ajouter 5 à 75 % d’eau distillée selon la texture désirée. Ajouter fragrances ou huiles essentielles (1–3 %). Ajouter actifs hydrosolubles ou liposolubles compatibles. Mélanger doucement pour éviter l’aération. Emballer dans un contenant propre et stérile. Recettes exemples Crème pour les mains (riche) Base crème épaisse : 80 % Huile végétale : 5 % Eau distillée : 14 % Fragrance : 1 % Crème corporelle (moyenne) Base crème épaisse : 65 % Eau distillée : 30 % Huile végétale : 3 % Fragrance : 1–2 % Lotion hydratante (légère – peut être doublée) Base crème épaisse : 40 % Eau distillée : 55 % Huile végétale : 3 % Fragrance : 1–2 % Gel-crème visage (léger & frais) Base crème épaisse : 45 % Eau distillée : 45 % Gel Aloe : 8 % Fragrance douce : 1–2 % Mise en garde Usage externe uniquement. Ne pas utiliser la base telle quelle sans transformation. Ne pas ingérer. Éviter le contact avec les yeux. Tenir hors de portée des enfants. Ne pas surchauffer la base. Toujours tester vos ajouts sur une petite quantité. Pure Arôme Laboratoire décline toute responsabilité en cas de mauvaise utilisation ou réaction liée au produit fini créé par le client. Mise en garde et conformité Avant de commercialiser votre produit fini, assurez-vous de respecter toutes les réglementations en vigueur et de soumettre la déclaration cosmétique requise par Santé Canada. La conformité demeure sous votre responsabilité. Note importante, mais tout en douceur Les informations partagées ici sont proposées avec rigueur et bienveillance, basées sur les données scientifiques et notre expérience. Elles ne remplacent pas un avis médical. Nous t’encourageons à réaliser des tests en petite quantité dans tes formules. Pure Arôme Laboratoire reste à tes côtés pour t’accompagner 💛. Document : Ingrédients % Base crème épaisse - neutre.pdf
A11: Pure Arôme | B11: Base de savon à faire fondre – Miel | C11: Bases neutres | Q11: https://www.purearome.com/fr/produit/base-de-savon-a-faire-fondre-miel | R11: À valider | T11: 46108 | U11: Melt and Pour Miel – Base Premium Pure Arôme Accueil Produits Base de savon à faire fondre – Miel Base de savon à faire fondre – Miel Sku: MPMIEL Base de savon à faire fondre – Miel Sku: MPMIEL 13,50 $ CAD Produit non disponible à l'achat en ligne Partager Base de savon à faire fondre – Miel Cette base de savon au miel (melt and pour) est conçue pour offrir une mousse douce, crémeuse et délicatement nourrissante. Sa couleur naturellement dorée et sa douceur proviennent du véritable miel qu’elle contient. Formulée sans TEA et sans ingrédients agressifs, elle fond facilement, se travaille proprement et permet de créer des savons professionnels de haute qualité, que ce soit pour artisans, marques ou créateurs en production continue. Ingrédients Glycerin, Propylene Glycol, Cocos Nucifera (Coconut) Oil, Honey, Sodium Stearate, Sodium Laurate, Sodium Myristate, Sodium Cocoate, Sorbitol, Aminomethyl Propanol, Aqua Caractéristiques techniques Aspect : solide translucide, couleur miel Odeur : douce et neutre Point de fusion : 60–75 °C Solubilité : fond au bain-marie, insoluble dans l’eau Qualité : sans TEA, sans alcool, non testé sur les animaux Conservation : conserver à 15–25 °C, à l’abri de l’humidité Provenance : Canada Mode d’emploi Couper la base en petits cubes pour une fonte uniforme. Faire fondre doucement au bain-marie entre 60–75 °C . Ne jamais dépasser 80 °C (risque d’opacification). Ajouter colorants, exfoliants, huiles ou additifs compatibles. Fragrance : maximum 3 % pour éviter le suintement. Bien mélanger puis couler immédiatement dans un moule propre. Laisser refroidir complètement avant de démouler. Mise en garde Usage externe uniquement . Ne pas utiliser la base telle quelle sans transformation. Éviter tout contact avec les yeux. Ne pas ingérer. Ne pas chauffer dans un contenant fermé. Tenir hors de portée des enfants. Mise en garde et conformité Avant de commercialiser votre produit fini, assurez-vous de respecter toutes les réglementations en vigueur et de soumettre le formulaire de déclaration des cosmétiques requis par Santé Canada. La conformité réglementaire de votre produit fini est sous votre entière responsabilité. Note importante, mais tout en douceur Les informations partagées ici sont proposées avec rigueur et bienveillance, basées sur les données scientifiques et notre expérience. Elles ne remplacent pas un avis médical. Nous t’encourageons à réaliser des tests en petite quantité dans tes formules. Pure Arôme Laboratoire reste à tes côtés pour t’accompagner 💛. Document : Ingrédients % Base de savon à faire fondre – Miel.pdf
A12: Pure Arôme | B12: Base de savon à faire fondre – Olive | C12: Bases neutres | Q12: https://www.purearome.com/fr/produit/base-de-savon-a-faire-fondre-olive | R12: À valider | T12: 46108 | U12: Base Savon Olive Premium – Melt and Pour Accueil Produits Base de savon à faire fondre – Olive Base de savon à faire fondre – Olive Sku: MPOLIVE Base de savon à faire fondre – Olive Sku: MPOLIVE 13,50 $ CAD Produit non disponible à l'achat en ligne Partager Base de savon à faire fondre – Olive Cette base de savon melt and pour enrichie en huile d’olive offre une mousse douce, crémeuse et très hydratante. Formulée sans TEA, sans SLS et sans SLES, elle constitue une excellente option pour créer des savons de qualité supérieure, autant pour artisans que pour entreprises de soins corporels. Sa fusion homogène et sa facilité d’utilisation en font une base idéale pour les savons moulés, colorés, parfumés ou fonctionnels. Ingrédients Glycerin, Propylene Glycol, Olea Europaea (Olive) Fruit Oil, Cocos Nucifera (Coconut) Oil, Sodium Stearate, Sodium Laurate, Sodium Myristate, Sodium Cocoate, Sorbitol, Aminomethyl Propanol, Aqua. Caractéristiques techniques Aspect : solide translucide, légèrement jaunâtre Odeur : douce, neutre Point de fusion : 60–75 °C Solubilité : fond au bain-marie, insoluble dans l’eau Qualité : sans TEA, sans alcool, non testé sur les animaux Conservation : conserver à 15–25 °C, à l’abri de l’humidité Provenance : Canada Mode d’emploi Couper la base en petits cubes pour une fonte uniforme. Faire fondre doucement au bain-marie entre 60–75 °C . Ne jamais dépasser 80 °C (risque d’opacification). Ajouter colorants, exfoliants, huiles ou additifs compatibles. Fragrance : maximum 3 % pour éviter le suintement. Bien mélanger puis couler immédiatement dans un moule propre. Laisser refroidir complètement avant de démouler. Mise en garde Usage externe uniquement . Ne pas utiliser la base telle quelle sans transformation. Éviter tout contact avec les yeux. Ne pas ingérer. Ne pas chauffer dans un contenant fermé. Tenir hors de portée des enfants. Mise en garde et conformité Avant de commercialiser votre produit fini, assurez-vous de respecter toutes les réglementations en vigueur et de soumettre le formulaire de déclaration des cosmétiques requis par Santé Canada. La conformité réglementaire de votre produit fini est sous votre entière responsabilité. Note importante, mais tout en douceur Les informations partagées ici sont proposées avec rigueur et bienveillance, basées sur les données scientifiques et notre expérience. Elles ne remplacent pas un avis médical. Nous t’encourageons à réaliser des tests en petite quantité dans tes formules. Pure Arôme Laboratoire reste à tes côtés pour t’accompagner 💛. Document : Ingrédients % Base de savon à faire fondre – Olive.pdf
A13: Pure Arôme | B13: Base de savon à faire fondre – Ultra Transparent | C13: Bases neutres | Q13: https://www.purearome.com/fr/produit/base-de-savon-a-faire-fondre-ultra-transparent | R13: À valider | T13: 46108 | U13: Base de savon Melt and Pour Ultra Transparent | Sans SLS, SLES, TEA Accueil Produits Base de savon à faire fondre – Ultra Transparent Base de savon à faire fondre – Ultra Transparent Sku: MPULTRA Base de savon à faire fondre – Ultra Transparent Sku: MPULTRA 13,50 $ CAD Produit non disponible à l'achat en ligne Partager Base de savon à faire fondre – Ultra Transparent Cette base de savon (melt and pour) ultra-transparente ne contient ni alcool ni agents agressifs, et elle est entièrement exempte de TEA, SLS et SLES. Elle fond facilement, offre une clarté exceptionnelle et constitue une base idéale pour la création de savons professionnels, moulés, colorés ou parfumés. Sa texture lisse et stable assure des résultats constants et haut de gamme pour artisans, créateurs et manufacturiers. Ingrédients Glycerin, Propylene Glycol, Sodium Stearate, Sorbitol, Cocos Nucifera (Coconut) Oil, Sodium Myristate, Sodium Laurate, Sodium Cocoate, Aminomethyl Propanol, Aqua Caractéristiques techniques Aspect : solide translucide, ultra clair Odeur : neutre, légère Point de fusion : 60–75 °C Transparence : très élevée (effet cristal) Solubilité : fond au bain-marie, insoluble dans l’eau Qualité : sans TEA, SLS, SLES, sans alcool, non testé sur les animaux Conservation : conserver à 15–25 °C, à l’abri de l’humidité Provenance : Canada Mode d’emploi Couper la base en petits cubes pour une fonte uniforme. Faire fondre doucement au bain-marie entre 60–75 °C . Ne jamais dépasser 80 °C (risque d’opacification). Ajouter colorants, exfoliants, huiles ou additifs compatibles. Fragrance : maximum 3 % pour éviter le suintement. Bien mélanger puis couler immédiatement dans un moule propre. Laisser refroidir complètement avant de démouler. Mise en garde Usage externe uniquement . Ne pas utiliser la base telle quelle sans transformation. Éviter tout contact avec les yeux. Ne pas ingérer. Ne pas chauffer dans un contenant fermé. Tenir hors de portée des enfants. Mise en garde et conformité Avant de commercialiser votre produit fini, assurez-vous de respecter toutes les réglementations en vigueur et de soumettre le formulaire de déclaration des cosmétiques requis par Santé Canada. La conformité réglementaire de votre produit fini est sous votre entière responsabilité. Note importante, mais tout en douceur Les informations partagées ici sont proposées avec rigueur et bienveillance, basées sur les données scientifiques et notre expérience. Elles ne remplacent pas un avis médical. Nous t’encourageons à réaliser des tests en petite quantité dans tes formules. Pure Arôme Laboratoire reste à tes côtés pour t’accompagner 💛. Document : Ingrédients % Base de savon à faire fondre – Ultra Transparente.pdf
A14: Pure Arôme | B14: Base masque capillaire | C14: Bases neutres | D14: Aqua, Behenamidopropyl dimethylamine, Behentrimonium methosulfate, Stearyl alcohol, Cetearyl alcohol, Hydrolyzed wheat protein, Cetyl alcohol, Phenoxyethanol, Ethylhexylglycerin | Q14: https://www.purearome.com/fr/produit/base-masque-capillaire | R14: Base | T14: 46108 | U14: Base masque capillaire neutre Accueil Produits Base masque capillaire Base masque capillaire Sku: BMASC En stock Base masque capillaire Sku: BMASC En stock 15,95 $ CAD Produit non disponible à l'achat en ligne Partager Base neutre de Masque capillaire Sans Paraben et Sans Propylène Glycol Découvrez la base neutre de masque capillaire de qualité professionnelle, conçue pour nourrir, hydrater et renforcer les cheveux en profondeur. Enrichie en kératine hydrolysée, cette formulation douce et efficace offre un support parfait pour créer des masques capillaires personnalisés, répondant aux besoins spécifiques de chaque type de cheveux. Avec notre base de masque capillaire, donnez libre cours à votre créativité ! Que vous soyez professionnel, artisan ou passionné du DIY, vous pouvez ajouter vos huiles essentielles, macérats, ou autres actifs pour créer des soins capillaires uniques. Cette base neutre est également sans paraben et sans propylène glycol, assurant une formulation douce et adaptée même aux cuirs chevelus sensibles. Notre masque capillaire de base est un choix parfait pour créer des produits sur mesure, riches en bienfaits, adaptés aux tendances actuelles de soins capillaires naturels. Ajoutez notre base de masque capillaire neutre à votre routine de création pour offrir des soins capillaires naturels et personnalisés qui raviront vos clients ! Ingrédients : Aqua, Behenamidopropyl dimethylamine, Behentrimonium methosulfate, Stearyl alcohol, Cetearyl alcohol, Hydrolyzed wheat protein, Cetyl alcohol, Phenoxyethanol, Ethylhexylglycerin Fabriqué au Canada Mise en Garde et Conformité : Avant de commercialiser votre produit fini, assurez-vous de respecter toutes les réglementations en vigueur et de soumettre le formulaire de déclaration des cosmétiques requis par Santé Canada. La conformité réglementaire est de votre responsabilité. **Usage externe uniquement** : Ce produit est destiné à une utilisation externe. Document : Fiche Technique Base Masque capillaire Pure arome Laboratoire.pdf
A15: Pure Arôme | B15: Base neutre bain moussant | C15: Bases neutres | D15: Aqua, Cocoamidopropyl betaine, Carboxyméthylcellulose, Vegetable glycerin, D-panthenol, Tocopherol, sodium alginate, Xanthan Gum, Aloe Barbadensis | Q15: https://www.purearome.com/fr/produit/base-neutre-bain-moussant | R15: Base | T15: 46108 | U15: Base neutre bain moussant Accueil Produits Base neutre bain moussant Base neutre bain moussant Sku: BBAINM En stock Base neutre bain moussant Sku: BBAINM En stock 16,95 $ CAD Produit non disponible à l'achat en ligne Partager Base bain moussant sans arôme (sans de sulfates, d'alcool, de parabens, de gluten ni de phtalates) Qui n'adore pas les bains moussants pour se plonger, relaxer et décrocher. Maintenant ce n'est plus un mystère monsieur madame et enfants adorent. Notre base de bain moussant doit faire parti de votre collection de cosmétique. Créer toi ton moment ou les moments pour tes clients allez hop ! elle t'attend notre base de bain moussant Cette base est non parfumée pour que vous utilisiez vos propres arômes pour créer votre produit personnalisé ! En parfumant, n'oubliez pas de garder vos mélanges sous le marqueur de 2%. Nous parfumons généralement cette base avec une charge d'arôme de 1% ou 2% au maximum. Produit du Canada Ingrédients : Aqua, Cocoamidopropyl betaine, Carboxyméthylcellulose, Vegetable glycerin, D-panthenol, Tocopherol, sodium alginate, Xanthan Gum, Aloe Barbadensis Si vous prévoyez la vente de produit, il est de votre responsabilité de respecter toutes les réglementations et de remplir le formulaire de déclaration des cosmétiques Santé Canada. Mise en garde: Nos produits sont pour usage externe seulement.
A16: Pure Arôme | B16: Base neutre gel de douche | C16: Bases neutres | D16: Aqua, Cocoamidopropyl betaine. Carboxyméthylcellulose, Vegetable glycerin, D-panthenol, Tocopherol, Xanthan Gum, Sodium alginate, Aloe Barbadensis, Polyquaternium7, Citrus Grandis (Grapefruit) Seed Extract (and) Glycerin (Extrait pépins de pamplemousse), Citric acid | Q16: https://www.purearome.com/fr/produit/base-neutre-gel-de-douche-1 | R16: Base | T16: 46108 | U16: Base neutre gel douche Accueil Produits Base neutre gel de douche Base neutre gel de douche Sku: BGELD Base neutre gel de douche Sku: BGELD 16,95 $ CAD Produit non disponible à l'achat en ligne Partager Base gel douche neutre Notre base de gel douche est un des produits préfères à nos clients, homme - femme et enfant adore le savon sous forme de gel doux et hydratant à la fois. Un indispensable dans une gamme collection cosmétique. Cette base est non parfumée pour que vous utilisiez vos propres arômes pour créer votre produit personnalisé ! En parfumant, n'oubliez pas de garder vos mélanges sous le marqueur de 2%. Nous parfumons généralement cette base avec une charge d'arôme de 1% ou 2% au maximum. S'il vous plaît noter que pendant les mois d'hiver cet article pourrait se figer durant l'expédition. Si votre produit arrive super épais, laissez le produit se réchauffer naturellement en même temps que la bouteille dans une pièce à température ambiante normale. Quand la base est froide, la couleur est opaque et est à température ambiante, elle est nette plus visible. Produit du Canada Ingrédients : Aqua, Cocoamidopropyl betaine. Carboxyméthylcellulose, Vegetable glycerin, D-panthenol, Tocopherol, Xanthan Gum, Sodium alginate, Aloe Barbadensis, Polyquaternium7, Citrus Grandis (Grapefruit) Seed Extract (and) Glycerin (Extrait pépins de pamplemousse), Citric acid Si vous prévoyez la vente de produit, il est de votre responsabilité de respecter toutes les réglementations et de remplir le formulaire de déclaration des cosmétiques Santé Canada. Mise en garde: Nos produits sont pour usage externe seulement.
A17: Pure Arôme | B17: Base neutre parfum | C17: Bases neutres | D17: Alcohol Denat. (SDA-40B Anhydrous) USP | Q17: https://www.purearome.com/fr/produit/base-neutre-parfum | R17: Propre | T17: 46108 | U17: Base neutre parfum Accueil Produits Base neutre parfum Base neutre parfum Sku: BASPAF En rupture ! De retour bientôt Base neutre parfum Sku: BASPAF En rupture ! De retour bientôt 25,95 $ CAD Produit non disponible à l'achat en ligne Partager Base Neutre pour Parfum INCI : Alcohol Denat. (SDA-40B Anhydrous) USP CAS : 64-17-5 Laissez libre cours à votre créativité olfactive avec notre Base Neutre pour Parfum et Brume. Conçue spécialement pour faciliter la création de produits parfumés, cette base est idéale pour des applications variées : parfums corporels, eaux de toilette, brumes d'ambiance, brumes pour le corps, et bien plus encore. Formulée avec un alcool dénaturé SDA 40B de qualité USP, notre base offre une qualité optimale pour garantir une expérience sûre et hautement performante. À partir d'un alcool végétal sans phtalate et non de grade technique, nous avons ajouté des composants tels que le Bitrex et le Myristate d'isopropyle. Le Bitrex confère une légère amertume pour empêcher toute ingestion accidentelle, tandis que le myristate d'isopropyle assure la stabilité et une diffusion idéale de vos parfums. La légère odeur d'alcool initiale disparaît totalement quelques secondes après la vaporisation de votre produit fini, enrichi de vos fragrances préférées, permettant ainsi un rendu olfactif pur et fidèle. Avantages de la Base de Parfum Pure Arôme : 1. Qualité supérieure : Alcool dénaturé USP de haute qualité, exempt de phtalates, pour une application en toute confiance. 2. Fixation et Longévité : Enrichie pour agir comme un fixateur, cette base prolonge la tenue des huiles essentielles et des fragrances, garantissant une expérience parfumée durable. 3. Facilité d'utilisation : Permet une diffusion homogène des arômes pour des créations olfactives parfaitement équilibrées. Conseils d’utilisation : Réaliser votre propre parfum est simple ! Versez la base dans un récipient adapté, puis ajoutez votre huile essentielle ou fragrance préférée, en mélangeant doucement pour une dispersion parfaite. Cette méthode vous permet de doser précisément chaque parfum et de créer des combinaisons uniques et personnelles. Origine : Canada Mise en Garde et Conformité : Avant de commercialiser votre produit fini, assurez-vous de respecter toutes les réglementations en vigueur et de soumettre le formulaire de déclaration des cosmétiques requis par Santé Canada. La conformité réglementaire est de votre responsabilité. . **Usage externe uniquement** : Ce produit est destiné à une utilisation externe. **Attention** : Ce produit est inflammable. Tenez-le éloigné de toute source de chaleur, d’étincelles et hors de portée des enfants. En cas d’accident, de situation d’urgence, ou d’incendie, nous déclinons toute responsabilité quant aux conséquences potentielles. Utilisez-le de manière responsable, avec masque et gants, et dans un environnement bien ventilé. Document : FDS Base de parfum fr.pdf
A18: Pure Arôme | B18: Base neutre revitalisant | C18: Bases neutres | D18: Aqua, Aloe Barbadensis, Orbygnia oleifera seed oil, Behentrimonium methosulfate, Cetearyl alcohol, Olea Europaea, Prunus Armeniaca, Glycerin, Hydrolyzed Silk, Anthemis nobilis flower extract, Glyceryl stearate, Sodium stearoyl lactylate, Tocopheryl Acetate, Ascorbic acid, Niacin, Panthenol, Pyridoxine, propanediol, Ethylhexylglycerin, Potassium sorbate | Q18: https://www.purearome.com/fr/produit/base-neutre-revitalisant | R18: Base | T18: 46108 | U18: Base neutre revitalisant Accueil Produits Base neutre revitalisant Base neutre revitalisant Sku: BREVIT En stock Base neutre revitalisant Sku: BREVIT En stock 16,95 $ CAD Produit non disponible à l'achat en ligne Partager Base neutre revitalisant Une belle base de revitalisant doux et soyeux, quoi demander de mieux pour le soin capillaire. Créer une belle finition à votre collection cosmétique grâce à la base de revitalisant. Cette base est non parfumée pour que vous utilisiez vos propres arômes pour créer votre produit personnalisé ! En parfumant, n'oubliez pas de garder vos mélanges sous le marqueur de 2%. Nous parfumons généralement cette base avec une charge d'arôme de 1% ou 2% au maximum. S'il vous plaît noter que pendant les mois d'hiver cet article pourrait se figer durant l'expédition. Si votre produit arrive super épais, laissez le produit se réchauffer naturellement en même temps que la bouteille dans une pièce à température ambiante normale. Quand la base est froide, la couleur est opaque et est à température ambiante, elle est nette plus visible. Produit du Canada Ingrédients : Aqua, Aloe Barbadensis, Orbygnia oleifera seed oil, Behentrimonium methosulfate, Cetearyl alcohol, Olea Europaea, Prunus Armeniaca, Glycerin, Hydrolyzed Silk, Anthemis nobilis flower extract, Glyceryl stearate, Sodium stearoyl lactylate, Tocopheryl Acetate, Ascorbic acid, Niacin, Panthenol, Pyridoxine, propanediol, Ethylhexylglycerin, Potassium sorbate Si vous prévoyez la vente de produit, il est de votre responsabilité de respecter toutes les réglementations et de remplir le formulaire de déclaration des cosmétiques Santé Canada. Mise en garde: Nos produits sont pour usage externe seulement.
A19: Pure Arôme | B19: Base neutre savon castille liquide | C19: Bases neutres | D19: Aqua, Olea Europaea (Olive) Fruit Oil, Cocos Nucifera (Coconut) Oil, Potassium Hydroxide, Algin. | Q19: https://www.purearome.com/fr/produit/base-neutre-savon-castille-liquide | R19: Base | T19: 46108 | U19: Base savon de Castille liquide Accueil Produits Base neutre savon castille liquide Base neutre savon castille liquide Sku: NEBASE-CASTILLE Base neutre savon castille liquide Sku: NEBASE-CASTILLE 16,95 $ CAD Produit non disponible à l'achat en ligne Partager Base de Savon de Castille Liquide - Sans Arôme Optez pour l'authenticité avec notre Base de Savon de Castille Liquide Sans Arôme, une formulation inspirée de la tradition ancestrale de la région de Castille en Espagne. Cette base de savon est l’essence même de la simplicité et de la pureté : de l'eau, de l'huile d'olive extra-vierge et une petite touche d'huile de noix de coco, créant un savon naturel qui respecte les peaux sensibles. Idéale pour les soins de la peau et les projets DIY, cette base est prête à être personnalisée avec vos arômes préférés. Pourquoi Choisir la Base de Savon de Castille Pure Arôme ? Ingrédients d'Origine Naturelle : Fabriquée principalement avec de l'huile d'olive extra-vierge, notre base est exempte d’huiles de palme ou d’ingrédients agressifs. Elle est spécialement conçue pour offrir une mousse douce et émolliente, idéale pour les peaux sensibles, y compris celles des bébés. Polyvalence : Sans parfum ajouté, cette base est parfaite pour personnaliser vos créations avec vos huiles essentielles ou fragrances. Respectez un taux d'arôme de 1 % à 2 % pour un produit équilibré et adapté aux peaux les plus délicates. Inspiration Traditionnelle et Efficacité Moderne : Contrairement aux bases industrielles enrichies en huiles moins coûteuses, notre base respecte les standards d’un véritable savon de Castille, alliant tradition et soin de la peau. Conseils d'Utilisation : Cette base, bien que moussante, garde l’essence du savon de Castille original. Pour une mousse optimisée, appliquez-la avec une houppette, un loofa ou une éponge. Note : En hiver, cette base peut se figer en raison des températures basses durant le transport. Si le produit arrive plus épais que d'habitude, laissez-le simplement se réchauffer naturellement à température ambiante jusqu'à ce qu'il retrouve sa consistance fluide. Ingrédients : Aqua, Olea Europaea (Olive) Fruit Oil, Cocos Nucifera (Coconut) Oil, Potassium Hydroxide, Algin. Fabriqué au Canada Mise en Garde et Conformité : Avant de commercialiser votre produit fini, assurez-vous de respecter toutes les réglementations en vigueur et de soumettre le formulaire de déclaration des cosmétiques requis par Santé Canada. La conformité réglementaire est de votre responsabilité. . **Usage externe uniquement** : Ce produit est destiné à une utilisation externe. Document : Ingredients Base Savon Castille Liquide Pure Arome Laboratoire.pdf
A20: Pure Arôme | B20: Base neutre savon pour corps et mains | C20: Bases neutres | D20: Aqua, Coco-betaine, Carboxyméthylcellulose, Vegetable glycerin, D-panthenol, Tocopherol, Xanthan Gum, sodium alginate, Aloe Barbadensis, Polyquaternium 7, Citrus Grandis (Grapefruit) Seed Extract (and) Glycerin (Extrait pépins de pamplemousse), | Q20: https://www.purearome.com/fr/produit/base-neutre-savon-pour-corps-et-mains | R20: Base | T20: 46108 | U20: Base savon corps et mains Accueil Produits Base neutre savon pour corps et mains Base neutre savon pour corps et mains Sku: BCOMA En stock Base neutre savon pour corps et mains Sku: BCOMA En stock 16,95 $ CAD Produit non disponible à l'achat en ligne Partager Base neutre corps et mains Notre base neutre savon pour corps et mains est bien plus qu'un simple savon. C'est une base neutre de qualité qui offre une expérience personnalisée et adaptée à vos besoins spécifiques. Sa formule douce et hydratante nettoie et nourrit la peau en douceur, la laissant douce et hydratée, et convient aussi bien pour les mains que pour le corps. Notre base neutre est conçue avec des ingrédients de qualité, ce qui garantit son efficacité et sa douceur pour la peau. Elle est également une option idéale pour les personnes souhaitant personnaliser leur expérience en utilisant leurs propres arômes. Avec notre base non parfumée, vous pouvez libérer votre créativité et ajouter vos propres huiles essentielles, fragrances ou extraits de plantes pour créer un savon à main ou pour le corps personnalisé qui répond à vos préférences et besoins. Nous vous recommandons de garder vos mélanges de parfum en dessous de 3%. Nous parfumons généralement cette base avec une charge d'arôme de 1% ou 2% maximum. Veuillez noter qu'un produit en phase gel neutre peut passer en phase liquide après l'ajout d'huile essentielle, de fragrance ou d'arôme en raison d'une réaction chimique naturelle (changement de pH). Afin d'éviter tout désagrément, nous vous recommandons de tester chaque arôme en petite quantité avant de produire une série. Toutefois, même sous forme liquide, notre base de gel douche reste exceptionnelle et offre une expérience de bain / douche agréable. Gel douche Savon de corps Produit capillaire Produit du Canada Ingrédients : Aqua, Coco-betaine, Carboxyméthylcellulose, Vegetable glycerin, D-panthenol, Tocopherol, Xanthan Gum, sodium alginate, Aloe Barbadensis, Polyquaternium 7, Citrus Grandis (Grapefruit) Seed Extract (and) Glycerin (Extrait pépins de pamplemousse), Si vous prévoyez la vente de produit, il est de votre responsabilité de respecter toutes les réglementations et de remplir le formulaire de déclaration des cosmétiques Santé Canada. Mise en garde: Nos produits sont pour usage externe seulement.
A21: Pure Arôme | B21: Base neutre shampoing | C21: Bases neutres | D21: Aqua, Decyl glucoside, Cocoamidopropyl Betaine, Glycerin, Hydrolyzed Silk, Niacin, Panthenol, Tocopherol, Propanediol, Ethylhexylglycerin, Potassium sorbate, Titanium dioxide Produit du Canada | Q21: https://www.purearome.com/fr/produit/base-neutre-shampoing | R21: Base | T21: 46108 | U21: Base Shampoing Accueil Produits Base neutre shampoing Base neutre shampoing Sku: BSHAMP En stock Base neutre shampoing Sku: BSHAMP En stock 16,95 $ CAD Produit non disponible à l'achat en ligne Partager Base shampoing L'action moussante de cette base est riche et crémeuse, ce qui rend très doux pour le cuir chevelu et les cheveux. La texture est assez proche d'un produit acheté en magasin, en ce qui concerne l'épaisseur il a un bon corps et ne glisse pas entre les doigts comme le font certains shampoings naturels. Ajouter de l'eau, des beurres ou des huiles supplémentaires peut compromettre la durée de conservation et vos propres essais de conservation devrait être complétés. Les additifs à base d'huile réduisent rapidement la capacité de moussage, les ingrédients solubles dans l'eau n'entravent pas la formation de mousse mais peuvent nécessiter l'ajout de conservateurs supplémentaires avant d'être incorporés dans la base. Cette base est non parfumée pour que vous utilisiez vos propres arômes pour créer votre produit personnalisé ! En parfumant, n'oubliez pas de garder vos mélanges sous le marqueur de 2%. Nous parfumons généralement cette base avec une charge d'arôme de 1% ou 2% au maximum. S'il vous plaît noter que pendant les mois d'hiver cet article pourrait se figer durant l'expédition. Si votre produit arrive super épais, laissez le produit se réchauffer naturellement en même temps que la bouteille dans une pièce à température ambiante normale. Quand la base est froide, la couleur est opaque et est à température ambiante, elle est nette plus visible. Ingrédients : Aqua, Decyl glucoside, Cocoamidopropyl Betaine, Glycerin, Hydrolyzed Silk, Niacin, Panthenol, Tocopherol, Propanediol, Ethylhexylglycerin, Potassium sorbate, Titanium dioxide Produit du Canada Si vous prévoyez la vente de produit, il est de votre responsabilité de respecter toutes les réglementations et de remplir le formulaire de déclaration des cosmétiques Santé Canada. Mise en garde: Nos produits sont pour usage externe seulement.
A22: Pure Arôme | B22: Base savon aloe vera Melt and Pour | C22: Bases neutres | D22: Aqua, Glycerin, Sorbitol, Sodium stearate, Propylene glycol, Sodium oleate, Sodium myristate, barbadensis leaf juice (Aloes vera), Sodium chloride, Citric acid, Coco-betaine, Pentasodium Pentetate, Tetrasodium Etidronate . | Q22: https://www.purearome.com/fr/produit/base-savon-aloe-vera-melt-and-pour | R22: Base | T22: 46108 | U22: Base savon Aloe Vera Melt and Pour Accueil Produits Base savon aloe vera Melt and Pour Base savon aloe vera Melt and Pour Sku: MPALOE Base savon aloe vera Melt and Pour Sku: MPALOE 13,50 $ CAD Produit non disponible à l'achat en ligne Partager Base de savon Aloe vera fondre et verser (Melt and Pour) Cette base de savon ne contient pas d'alcool ou de produits nocifs, et elle est libre de tensioactifs SLS et SLES. Notre base de savon Aloès (aloe vera) est riche, grâce au Jus gel d'aloe vera utilisé lors de sa fabrication. Elle a une couleur transparente, alors pleines possibilités pour vos créations. Cette base est non parfumée pour que vous utilisiez vos propres arômes pour créer votre produit personnalisé ! En parfumant, n'oubliez pas de garder vos mélanges sous le marqueur de 2%. Nous parfumons généralement cette base avec une charge d'arôme de 1% ou 2% au maximum. Produit du Canada Ingrédients : Aqua, Glycerin, Sorbitol, Sodium stearate, Propylene glycol, Sodium oleate, Sodium myristate, barbadensis leaf juice (Aloes vera), Sodium chloride, Citric acid, Coco-betaine, Pentasodium Pentetate, Tetrasodium Etidronate . Si vous prévoyez la vente de produit, il est de votre responsabilité de respecter toutes les réglementations et de remplir le formulaire de déclaration des cosmétiques Santé Canada. Mise en garde: Nos produits sont pour usage externe seulement.
A23: Pure Arôme | B23: Base savon beurre de Karité Melt and Pour | C23: Bases neutres | D23: Aqua, Glycerin, Sodium stearate, Sorbitol, Sodium laurate, Propylene glycol, Sodium oleate, Sodium myristate, Sodium chloride, Citric acid, Glyceryl Monolaurate, Shea butter (Butyrospermum parkii), coco-betaine, Sodium thiosulfate, Titanium dioxide, Trisodium Sulfosuccinate, Pentasodium Pentetate, Tetrasodium Etidronate . | Q23: https://www.purearome.com/fr/produit/base-savon-beurre-de-karite-melt-and-pour | R23: Base | T23: 46108 | U23: Base savon beurre de Karité Melt and Pour Accueil Produits Base savon beurre de Karité Melt and Pour Base savon beurre de Karité Melt and Pour Sku: MPKARI Base savon beurre de Karité Melt and Pour Sku: MPKARI 13,50 $ CAD Produit non disponible à l'achat en ligne Partager Base de savon au beurre de Karité fondre et verser (Melt and Pour) Cette base de savon ne contient pas d'alcool ou de produits nocifs, et elle est libre de tensioactifs SLS et SLES. Notre base de savon au beurre de Karité est d'une qualité extraordinaire, retrouvé toutes les propriétés du beurre de Karité dans votre base de savon. Cette base est non parfumée pour que vous utilisiez vos propres arômes pour créer votre produit personnalisé ! En parfumant, n'oubliez pas de garder vos mélanges sous le marqueur de 2%. Nous parfumons généralement cette base avec une charge d'arôme de 1% ou 2% au maximum. Produit du Canada Ingrédients : Aqua, Glycerin, Sodium stearate, Sorbitol, Sodium laurate, Propylene glycol, Sodium oleate, Sodium myristate, Sodium chloride, Citric acid, Glyceryl Monolaurate, Shea butter (Butyrospermum parkii), coco-betaine, Sodium thiosulfate, Titanium dioxide, Trisodium Sulfosuccinate, Pentasodium Pentetate, Tetrasodium Etidronate . Si vous prévoyez la vente de produit, il est de votre responsabilité de respecter toutes les réglementations et de remplir le formulaire de déclaration des cosmétiques Santé Canada. Mise en garde: Nos produits sont pour usage externe seulement.
A24: Pure Arôme | B24: Base savon beurre de Mangue Melt and Pour | C24: Bases neutres | D24: Aqua, Glycerin, Sodium stearate, Sorbitol, Sodium laurate, Propylene glycol, Sodium oleate, Sodium myristate, Sodium chloride, Citric acid, Glyceryl Monolaurate, Mango butter (Mangifera indica), Coco-betaine, Sodium thiosulfate, Titanium dioxide, Trisodium Sulfosuccinate, Pentasodium Pentetate, Tetrasodium Etidronate . | Q24: https://www.purearome.com/fr/produit/base-savon-beurre-de-mangue-melt-and-pour | R24: Base | T24: 46108 | U24: Base savon beurre de Mangue Melt and Pour Accueil Produits Base savon beurre de Mangue Melt and Pour Base savon beurre de Mangue Melt and Pour Sku: MPMANG Base savon beurre de Mangue Melt and Pour Sku: MPMANG 13,50 $ CAD Produit non disponible à l'achat en ligne Partager Base de savon beurre de mangue fondre et verser (Melt and Pour) Cette base de savon ne contient pas d'alcool ou de produits nocifs, et elle est libre de tensioactifs SLS et SLES. Notre base de savon de mangue est d'une qualité extraordinaire, retrouvé toutes les propriétés du beurre de mangue dans votre base de savon. Cette base est non parfumée pour que vous utilisiez vos propres arômes pour créer votre produit personnalisé ! En parfumant, n'oubliez pas de garder vos mélanges sous le marqueur de 2%. Nous parfumons généralement cette base avec une charge d'arôme de 1% ou 2% au maximum. Produit du Canada Ingrédients : Aqua, Glycerin, Sodium stearate, Sorbitol, Sodium laurate, Propylene glycol, Sodium oleate, Sodium myristate, Sodium chloride, Citric acid, Glyceryl Monolaurate, Mango butter (Mangifera indica), Coco-betaine, Sodium thiosulfate, Titanium dioxide, Trisodium Sulfosuccinate, Pentasodium Pentetate, Tetrasodium Etidronate . Si vous prévoyez la vente de produit, il est de votre responsabilité de respecter toutes les réglementations et de remplir le formulaire de déclaration des cosmétiques Santé Canada. Mise en garde: Nos produits sont pour usage externe seulement.
A25: Pure Arôme | B25: Base savon blanc opaque Melt and Pour | C25: Bases neutres | D25: Aqua, Glycerin, Sodium stearate, Sorbitol, Sodium laurate, Propylene glycol, Sodium oleate, Sodium myristate, Sodium chloride, Citric acid, Glyceryl Monolaurate, Coco-betaine, Sodium thiosulfate, Titanium dioxide, Trisodium Sulfosuccinate, Pentasodium Pentetate, Tetrasodium Etidronate . | Q25: https://www.purearome.com/fr/produit/base-savon-blanc-opaque-melt-and-pour | R25: Base | T25: 46108 | U25: Base savon blanc opaque Melt and Pour Accueil Produits Base savon blanc opaque Melt and Pour Base savon blanc opaque Melt and Pour Sku: MPBLANC Base savon blanc opaque Melt and Pour Sku: MPBLANC 11,50 $ CAD Produit non disponible à l'achat en ligne Partager Base de savon blanc opaque fondre et verser (Melt and Pour) Cette base de savon ne contient pas d'alcool ou de produits nocifs, et elle est libre de tensioactifs SLS et SLES. Notre base de savon blanc opaque est utilisé dans toutes les sphères du melt and pour sans aucun ajout elle se colore super bien, très utile comme passe-partout avec son prix super abordable. Cette base est non parfumée pour que vous utilisiez vos propres arômes pour créer votre produit personnalisé ! En parfumant, n'oubliez pas de garder vos mélanges sous le marqueur de 2%. Nous parfumons généralement cette base avec une charge d'arôme de 1% ou 2% au maximum. Produit du Canada Ingrédients : Aqua, Glycerin, Sodium stearate, Sorbitol, Sodium laurate, Propylene glycol, Sodium oleate, Sodium myristate, Sodium chloride, Citric acid, Glyceryl Monolaurate, Coco-betaine, Sodium thiosulfate, Titanium dioxide, Trisodium Sulfosuccinate, Pentasodium Pentetate, Tetrasodium Etidronate . Si vous prévoyez la vente de produit, il est de votre responsabilité de respecter toutes les réglementations et de remplir le formulaire de déclaration des cosmétiques Santé Canada. Mise en garde: Nos produits sont pour usage externe seulement.
A26: Pure Arôme | B26: Base savon fouetté – Neutre | C26: Bases neutres | Q26: https://www.purearome.com/fr/produit/base-savon-fouette-neutre | R26: À valider | T26: 46108 | U26: Base savon fouetté neutre – Savon fouetté professionnel Accueil Produits Base savon fouetté – Neutre Base savon fouetté – Neutre Sku: SAVFO En stock Base savon fouetté – Neutre Sku: SAVFO En stock 8,50 $ CAD Produit non disponible à l'achat en ligne Partager Base savon fouetté – Neutre Cette base savon fouetté neutre est une base lavante professionnelle prête à être transformée en savon fouetté onctueux, stable et aérien. Sa texture dense permet de créer des produits nettoyants luxueux tels que : savon fouetté pour le corps, savon exfoliant, crème lavante parfumée, savon moussant pour les mains ou base lavante sensorielle. La base est volontairement neutre et concentrée afin de permettre une personnalisation complète : ajout de fragrances, huiles essentielles, colorants, exfoliants et actifs compatibles. Une fois fouettée, elle développe une mousse riche, crémeuse et adhérente, idéale pour un usage corporel quotidien. Formulation douce et performante, sans SLS, sans SLES, sans alcool, sans TEA , compatible avec la majorité des ajouts cosmétiques. Ingrédients Aqua (Water), Sodium Cocoyl Isethionate, Myristic Acid, Glycerin, Stearic Acid, Sorbitol, Sodium Chloride, Diazolidinyl Urea (and) Iodopropynyl Butylcarbamate. Caractéristiques techniques Aspect : pâte blanche, dense et homogène Odeur : neutre Texture initiale : pâte compacte Texture après fouettage : mousse crémeuse et aérienne Modulable : ajout possible d’huiles, fragrances, exfoliants Compatibilité : fragrances, huiles essentielles, poudres exfoliantes, pigments Qualité : sans SLS/SLES, sans alcool, sans TEA, non testé sur les animaux Conservation : 15–25 °C, contenant bien fermé, à l’abri de l’humidité Provenance : Canada Mode d’emploi – Savon fouetté Prélever la quantité désirée de base savon fouetté. Placer dans un bol propre et sec. Fouetter à vitesse moyenne à élevée (batteur ou mélangeur) jusqu’à obtenir une texture légère et mousseuse. Ajouter fragrance ou huile essentielle (1–3 %). Incorporer doucement les huiles végétales (1–3 % maximum). Ajouter exfoliants ou poudres si désiré. Fouetter légèrement pour homogénéiser sans écraser la mousse. Conditionner dans un pot propre et hermétique. Recettes exemples Savon fouetté classique Base savon fouetté : 98 % Fragrance : 2 % Savon fouetté exfoliant Base savon fouetté : 92 % Sucre ou poudre exfoliante : 5 % Huile végétale : 1 % Fragrance : 2 % Savon fouetté ultra-doux Base savon fouetté : 95 % Huile végétale : 3 % Fragrance douce : 1–2 % Mise en garde Usage externe uniquement. Ne pas ingérer. Éviter le contact avec les yeux. Tenir hors de portée des enfants. Ne pas surchauffer la base. Toujours tester vos ajouts sur une petite quantité. Pure Arôme Laboratoire décline toute responsabilité quant au produit fini transformé par le client. Mise en garde et conformité Avant toute mise en marché, le produit fini doit respecter la réglementation cosmétique en vigueur et faire l’objet d’une déclaration auprès de Santé Canada. La conformité du produit final demeure sous la responsabilité du fabricant. Note importante, mais tout en douceur Les informations partagées ici sont proposées avec rigueur et bienveillance, basées sur les données scientifiques et notre expérience. Elles ne remplacent pas un avis médical. Nous t’encourageons à réaliser des tests en petite quantité dans tes formules. Pure Arôme Laboratoire reste à tes côtés pour t’accompagner 💛. Document : Ingrédients % Base savon fouetté – Neutre.pdf
A27: Pure Arôme | B27: Base savon Lait d'Ânesse Melt and Pour | C27: Bases neutres | D27: Aqua, Glycerin, Sodium stearate, Sorbitol, Sodium laurate, Propylene glycol, Sodium oleate, Sodium myristate, Sodium chloride, Citric acid, Glyceryl Monolaurate, Equss asinus lac, coco-betaine, Sodium thiosulfate, Titanium dioxide, Trisodium Sulfosuccinate, Pentasodium Pentetate, Tetrasodium Etidronate . | Q27: https://www.purearome.com/fr/produit/base-savon-lait-d-anesse-melt-and-pour | R27: Base | T27: 46108 | U27: Base savon Lait d&#x27;Ânesse Melt and Pour Accueil Produits Base savon Lait d'Ânesse Melt and Pour Base savon Lait d'Ânesse Melt and Pour Sku: MPLAITA Base savon Lait d'Ânesse Melt and Pour Sku: MPLAITA 13,50 $ CAD Produit non disponible à l'achat en ligne Partager Base de savon Lait d'ânesse fondre et verser (Melt and Pour) Cette base de savon ne contient pas d'alcool ou de produits nocifs, et elle est libre de tensioactifs SLS et SLES. Une belle base de savon au lait d'ânesse avec toute sa splendeur/douceur remplie de bien fait du lait d'une belle couleur blanche. Cette base est non parfumée pour que vous utilisiez vos propres arômes pour créer votre produit personnalisé ! En parfumant, n'oubliez pas de garder vos mélanges sous le marqueur de 2%. Nous parfumons généralement cette base avec une charge d'arôme de 1% ou 2% au maximum. Produit du Canada Ingrédients: Aqua, Glycerin, Sodium stearate, Sorbitol, Sodium laurate, Propylene glycol, Sodium oleate, Sodium myristate, Sodium chloride, Citric acid, Glyceryl Monolaurate, Equss asinus lac, coco-betaine, Sodium thiosulfate, Titanium dioxide, Trisodium Sulfosuccinate, Pentasodium Pentetate, Tetrasodium Etidronate . Si vous prévoyez la vente de produit, il est de votre responsabilité de respecter toutes les réglementations et de remplir le formulaire de déclaration des cosmétiques Santé Canada. Mise en garde: Nos produits sont pour usage externe seulement.
A28: Pure Arôme | B28: Base savon Lait de chèvre Melt and Pour | C28: Bases neutres | D28: Aqua, Glycerin, Sodium stearate, Sorbitol, Sodium laurate, Propylene glycol, Sodium oleate, Sodium myristate, Sodium chloride, Citric acid, Glyceryl Monolaurate, Caprae lac (milk), coco-betaine, Sodium thiosulfate, Titanium dioxide, Trisodium Sulfosuccinate, Pentasodium Pentetate, Tetrasodium Etidronate . | Q28: https://www.purearome.com/fr/produit/base-savon-lait-de-chevre-melt-and-pour | R28: Base | T28: 46108 | U28: Base savon Lait de chèvre Melt and Pour Accueil Produits Base savon Lait de chèvre Melt and Pour Base savon Lait de chèvre Melt and Pour Sku: MPLAITC Base savon Lait de chèvre Melt and Pour Sku: MPLAITC 11,50 $ CAD Produit non disponible à l'achat en ligne Partager Base de savon lait de chèvre fondre et verser (Melt and Pour) Cette base de savon ne contient pas d'alcool ou de produits nocifs, et elle est libre de tensioactifs SLS et SLES. Cette base savon, lait de chèvre est une des incontournables, la favorite de tous avec sa richesse, douceur et sa couleur blanche opaque. Cette base est non parfumée pour que vous utilisiez vos propres arômes pour créer votre produit personnalisé ! En parfumant, n'oubliez pas de garder vos mélanges sous le marqueur de 2%. Nous parfumons généralement cette base avec une charge d'arôme de 1% ou 2% au maximum. Produit du Canada Ingrédients: Aqua, Glycerin, Sodium stearate, Sorbitol, Sodium laurate, Propylene glycol, Sodium oleate, Sodium myristate, Sodium chloride, Citric acid, Glyceryl Monolaurate, Caprae lac (milk), coco-betaine, Sodium thiosulfate, Titanium dioxide, Trisodium Sulfosuccinate, Pentasodium Pentetate, Tetrasodium Etidronate . Si vous prévoyez la vente de produit, il est de votre responsabilité de respecter toutes les réglementations et de remplir le formulaire de déclaration des cosmétiques Santé Canada. Mise en garde: Nos produits sont pour usage externe seulement.
A29: Pure Arôme | B29: Base savon Lait de coco Melt and Pour | C29: Bases neutres | D29: Aqua , Glycerin, Sodium stearate, Sorbitol, Sodium laurate, Propylene glycol, Sodium oleate, Sodium myristate, Sodium chloride, Citric acid, Glyceryl Monolaurate, Cocos Nucifera (milk), coco-betaine, Sodium thiosulfate, Titanium dioxide, Trisodium Sulfosuccinate, Pentasodium Pentetate. | Q29: https://www.purearome.com/fr/produit/base-savon-lait-de-coco-melt-and-pour | R29: Base | T29: 46108 | U29: Base savon Lait de coco fondre et verser (Melt and Pour) Accueil Produits Base savon Lait de coco Melt and Pour Base savon Lait de coco Melt and Pour Sku: MPCOCO Base savon Lait de coco Melt and Pour Sku: MPCOCO 13,50 $ CAD Produit non disponible à l'achat en ligne Partager Base savon lait de noix de coco fondre et verser (Melt and Pour) Cette base de savon ne contient pas d'alcool ou de produits nocifs, et elle est libre de tensioactifs SLS et SLES. Une base super douce, riche et hydratante, de couleur blanche elle laissera court à votre imagination pour une création facile de savon maison. Cette base est non parfumée pour que vous utilisiez vos propres arômes pour créer votre produit personnalisé ! En parfumant, n'oubliez pas de garder vos mélanges sous le marqueur de 2%. Nous parfumons généralement cette base avec une charge d'arôme de 1% ou 2% au maximum. Produit au Canada Ingrédients : Aqua , Glycerin, Sodium stearate, Sorbitol, Sodium laurate, Propylene glycol, Sodium oleate, Sodium myristate, Sodium chloride, Citric acid, Glyceryl Monolaurate, Cocos Nucifera (milk), coco-betaine, Sodium thiosulfate, Titanium dioxide, Trisodium Sulfosuccinate, Pentasodium Pentetate. Si vous prévoyez la vente de produit, il est de votre responsabilité de respecter toutes les réglementations et de remplir le formulaire de déclaration des cosmétiques Santé Canada. Mise en garde: Nos produits sont pour usage externe seulement.
A30: Pure Arôme | B30: Base savon suspension Melt and Pour | C30: Bases neutres | D30: Aqua, Glycerin, Silica, Sorbitol, Sodium stearate, Propylene glycol, Sodium oleate, Sodium myristate, Sodium chloride, Citric acid, Coco-betaine, Pentasodium Pentetate. | Q30: https://www.purearome.com/fr/produit/base-savon-suspension-melt-and-pour | R30: Base | T30: 46108 | U30: Base de savon transparente suspension fondre et verser (Melt and Pour) Accueil Produits Base savon suspension Melt and Pour Base savon suspension Melt and Pour Sku: MPSUS En stock Base savon suspension Melt and Pour Sku: MPSUS En stock 15,50 $ CAD Produit non disponible à l'achat en ligne Partager Base de savon transparente suspension fondre et verser (Melt and Pour) Cette base de savon ne contient pas d'alcool ou de produits nocifs, et elle est libre de tensioactifs SLS et SLES. La base &quot; suspension&quot; melt and pour est conçu spécialement pour maintenir vos ingrédients en suspension dans le savon. Parfait pour y déposer des fleurs séchées, pierre ponce, grains de pavots, et même faire un savon stylé, il suffit seulement attendre que le savon fondu refroidisse un petit peu et déposer vos couches et marbrer, les possibilités sont infinies libres cours à votre imagination. Cette base est non parfumée pour que vous utilisiez vos propres arômes pour créer votre produit personnalisé ! En parfumant, n'oubliez pas de garder vos mélanges sous le marqueur de 2%. Nous parfumons généralement cette base avec une charge d'arôme de 1% ou 2% au maximum. Produit du Canada Ingrédients : Aqua, Glycerin, Silica, Sorbitol, Sodium stearate, Propylene glycol, Sodium oleate, Sodium myristate, Sodium chloride, Citric acid, Coco-betaine, Pentasodium Pentetate. Si vous prévoyez la vente de produit, il est de votre responsabilité de respecter toutes les réglementations et de remplir le formulaire de déclaration des cosmétiques Santé Canada. Mise en garde: Nos produits sont pour usage externe seulement.
A31: Pure Arôme | B31: Base savon transparent Melt and Pour | C31: Bases neutres | D31: Aqua, Glycerin, Sorbitol, Sodium stearate, Propylene glycol, Sodium oleate, Sodium myristate, Sodium chloride, Citric acid, Coco-betaine, Pentasodium Pentetate. | Q31: https://www.purearome.com/fr/produit/base-savon-transparent-melt-and-pour | R31: Base | T31: 46108 | U31: Base savon transparent Melt and Pour Accueil Produits Base savon transparent Melt and Pour Base savon transparent Melt and Pour Sku: MPTRANS Base savon transparent Melt and Pour Sku: MPTRANS 11,50 $ CAD Produit non disponible à l'achat en ligne Partager Base de savon transparent fondre et verser (Melt and Pour) Cette base de savon ne contient pas d'alcool ou de produits nocifs, et elle est libre de tensioactifs SLS et SLES. La base de savon transparent Melt and Pour est la base la plus populaire pour les créations de couleurs, les possibilités sont infinies libres cours à votre imagination. Cette base est non parfumée pour que vous utilisiez vos propres arômes pour créer votre produit personnalisé ! En parfumant, n'oubliez pas de garder vos mélanges sous le marqueur de 2%. Nous parfumons généralement cette base avec une charge d'arôme de 1% ou 2% au maximum. Produit du Canada Ingrédients : Aqua, Glycerin, Sorbitol, Sodium stearate, Propylene glycol, Sodium oleate, Sodium myristate, Sodium chloride, Citric acid, Coco-betaine, Pentasodium Pentetate. Si vous prévoyez la vente de produit, il est de votre responsabilité de respecter toutes les réglementations et de remplir le formulaire de déclaration des cosmétiques Santé Canada. Mise en garde: Nos produits sont pour usage externe seulement.
A32: Pure Arôme | B32: Gel d'Aloe Vera | C32: Bases neutres | D32: Aqua, Glycerin, Aloe Barbadensis Leaf Juice Powder, Carbomer, Triethanolamine, Tocopherol, Euxyl Pe9010 | Q32: https://www.purearome.com/fr/produit/gel-d-aloe-vera | R32: Propre | T32: 46108 | U32: Gel d&#x27;Aloe Vera Accueil Produits Gel d'Aloe Vera Gel d'Aloe Vera Sku: GELALOE En stock Gel d'Aloe Vera Sku: GELALOE En stock 12,95 $ CAD Produit non disponible à l'achat en ligne Partager Le Gel Aloe Vera Pure Arôme Laboratoire est une base cosmétique concentrée, transparente, stable et facile à personnaliser, spécialement conçue pour les cosmétiques, soins du corps, et produits bien-être. Riche en Aloe Barbadensis concentré 200x, ce gel est reconnu pour ses propriétés hydratantes, apaisantes et réparatrices, idéales pour les peaux sensibles, irritées ou exposées au soleil. Sa texture légère, fraîche et non collante s'intègre facilement à vos créations personnalisées grâce à sa compatibilité avec les hydrolats, extraits botaniques, huiles essentielles, fragrances naturelles et actifs cosmétiques solubles. Caractéristiques principales : - Base prête à l’emploi : Facile à personnaliser avec vos actifs et extraits préférés. - Hydratation intense : Grâce à la glycérine et à l’aloe vera concentré. - Stabilité et clarté : Formule transparente et résistante aux ajouts cosmétiques. - Non collant et rafraîchissant : Parfait pour les soins visage ou corps. - Conservé avec Euxyl PE 9010 : Sûr, sans parabène, sans formaldéhyde. - Fabriqué au Québec : Qualité locale pour une traçabilité transparente. Spécifications techniques : Inci : Aqua, Glycerin, Aloe Barbadensis Leaf Juice Powder, Carbomer, Triethanolamine, Tocopherol, Euxyl Pe9010 Numéro CAS : disponibles sur la fiche technique Apparence : Gel clair à légèrement opalescent Solubilité : Soluble dans l’eau. pH : 5.5 à 6.5. Conservation : 12 mois – température réfrigérée Provenance : Québec, Canada Mise en garde et conformité Usage externe uniquement. Le port de gants, d’un masque et de lunettes de protection est fortement recommandé. Toujours travailler dans un endroit bien aéré pour garantir votre sécurité. Toujours effectuer un test cutané du produit fini sur une petite zone avant utilisation complète. Responsabilité : Pure Arôme Laboratoire ne peut être tenu responsable des incidents, accidents ou réactions liés à l’utilisation ou au produit fini créé par le client.
A33: Pure Arôme | B33: Savon Africain noir | C33: Bases neutres | D33: Potassium shea butterate, potassium cocoate potassium, palm kernelate, theobroma cacao pod ash (beurres de karité, de coco, de palme et de cacao | Q33: https://www.purearome.com/fr/produit/savon-africain-noir | R33: Propre | T33: 46108 | U33: Savon noir Africain 100% naturel Accueil Produits Savon Africain noir Savon Africain noir Sku: AFRISOAP En stock Savon Africain noir Sku: AFRISOAP En stock 5,00 $ CAD Produit non disponible à l'achat en ligne Partager Savon noir africain Inci : Potassium shea butterate, potassium cocoate potassium, palm kernelate, theobroma cacao pod ash (beurres de karité, de coco, de palme et de cacao) Provenance : Ghana Le savon noir africain est utilisé depuis des siècles en Afrique et fait partie intégrante des rituels de beauté dans cette région. Hommes, femmes et enfants l'utilisent au quotidien pour le soin de leur peau. Reconnu pour ses vertus purifiantes, le savon noir africain artisanal est l'ami des peaux à tendance acnéiques et des personnes souffrant d'eczéma. Aussi basique que le beurre de karité, le savon noir africain devrait avoir sa place dans toutes les salles de bains. Fabriqué à base de cendres de plantes et d'huile végétale, le savon noir artisanal purifie la peau sans la décaper. Il peut être utilisé sur le visage, le corps ou les cheveux. Certains l'utilisent tel quel, d'autres font leur recette maison en y ajoutant des ingrédients de leur choix pour un soin encore plus doux pour la peau/les cheveux. Certains l'utilisent simplement comme nettoyant quotidien, d'autres le laissent poser quelques minutes en guise de masque purifiant. Chacun l'utilise à sa manière, selon son type de peau et l'effet recherché. Cette savon est non parfumée pour que vous utilisiez vos propres arômes pour créer votre produit personnalisé ! En parfumant, n'oubliez pas de garder vos mélanges sous le marqueur de 2%. Nous parfumons généralement ce savon avec une charge d'arôme de 1% ou 2% au maximum. Les tailles de pièce de savon peuvent varier de petits à de grands morceaux. Si vous prévoyez la vente de produit, il est de votre responsabilité de respecter toutes les réglementations et de remplir le formulaire de déclaration des cosmétiques Santé Canada. Mise en garde: Nos produits sont pour usage externe seulement.
A34: Pure Arôme | B34: Acide stéarique | C34: Cires | D34: Stearic Acid | Q34: https://www.purearome.com/fr/produit/acide-stearique | R34: Propre | T34: 46108 | U34: Acide Stéarique Accueil Produits Acide stéarique Acide stéarique Sku: ACIDSTE En stock Acide stéarique Sku: ACIDSTE En stock 4,50 $ CAD Produit non disponible à l'achat en ligne Partager L’acide stéarique végétal est un ingrédient polyvalent, reconnu pour ses propriétés épaississantes, durcissantes et stabilisantes. Dérivé de matières premières végétales renouvelables, il est idéal pour vos formulations cosmétiques, vos savons artisanaux et vos chandelles, tout en offrant une qualité professionnelle et durable. Chez Pure Arôme Laboratoire, nous vous proposons un acide stéarique végétal de qualité pour vos créations cosmétiques et artisanales DIY. Simple d’utilisation et naturel, il apporte durabilité, stabilité et performance à vos produits finis. Utilisations recommandées : Acide stéarique pour cosmétiques : - Épaissis les crèmes et lotions pour une texture riche et soyeuse. - Stabilise les émulsions pour éviter la séparation des phases. - Idéal pour les baumes à lèvres, les beurres corporels et les déodorants solides. Acide stéarique pour savonnerie : - Durcit les savons artisanaux et prolonge leur durée de vie. - Améliore la mousse et la consistance dans les procédés à froid ou à chaud. Acide stéarique pour chandelles : - Renforce la cire végétale pour une meilleure tenue. - Assure une combustion plus lente et régulière pour une diffusion optimale de l’arôme. Caractéristiques principales : Polyvalent et compatible avec huiles, cires et bases naturelles. Naturel, sans parabènes ni phtalates. Facile à utiliser grâce à sa dissolution rapide dans les formulations chauffées. Qualité supérieure pour des produits solides, performants et durables. Spécifications techniques : Inci : Stearic Acid Numéro CAS : 57-11-4 Origine : 100 % végétale, issu de matières renouvelables. Apparence : Poudre ou perles blanches solides. Solubilité : Soluble dans les huiles chaudes et cires végétales. Point de fusion : Entre 55 °C et 70 °C. Dosage recommandé : 2-20 % Provenance : États-Unis. Mise en garde et conformité Usage externe uniquement. Le port de gants, d’un masque et de lunettes de protection est fortement recommandé. Toujours travailler dans un endroit bien aéré pour garantir votre sécurité. Responsabilité : Pure Arôme Laboratoire ne peut être tenu responsable des incidents, accidents ou réactions liés à l’utilisation ou au produit fini créé par le client.
A35: Pure Arôme | B35: Alcool Cétéaryl (Cétéarylique) | C35: Cires | D35: Cetearyl Alcohol | Q35: https://www.purearome.com/fr/produit/alcool-cetearyl-cetearylique | R35: Propre | T35: 46108 | U35: Alcool Cétéaryl (Cétéarylique) - Laboratoire Pure arôme - Fournissseur de matières premières cosmétiques DIY Accueil Produits Alcool Cétéaryl (Cétéarylique) Alcool Cétéaryl (Cétéarylique) Sku: ACETEAR En stock Alcool Cétéaryl (Cétéarylique) Sku: ACETEAR En stock 3,25 $ CAD Produit non disponible à l'achat en ligne Partager L’alcool cétéaryl, également appelé alcool cétéarylique, est un mélange d’alcools gras dérivés de matières premières végétales renouvelables. Reconnu pour ses propriétés épaississantes, émollientes et stabilisantes, il est idéal pour vos formulations de crèmes, lotions, baumes et soins capillaires, tout en offrant une qualité professionnelle et durable. Chez Pure Arôme Laboratoire, nous vous proposons un alcool cétéarylique de qualité pour vos créations cosmétiques et artisanales DIY. Simple d’utilisation et naturel, il apporte durabilité, stabilité et performance à vos produits finis. Utilisations recommandées : Alcool cétéaryl pour cosmétiques : - Épaissit les crèmes et lotions pour une texture riche et crémeuse. - Stabilise les émulsions pour éviter la séparation des phases. - Adoucit et nourrit la peau grâce à ses propriétés émollientes. - Idéal pour les baumes, beurres corporels et déodorants solides. Alcool cétéaryl pour soins capillaires : - Apporte une texture douce et onctueuse aux après-shampoings et masques. - Facilite le démêlage et laisse les cheveux soyeux et nourris. Caractéristiques principales : Polyvalent et compatible avec huiles, cires et bases naturelles. Naturel, sans parabènes ni phtalates. Facile à utiliser grâce à sa dissolution rapide dans les formulations chauffées. Qualité supérieure pour des produits solides, performants et durables. Spécifications techniques : Inci : Cetearyl Alcohol Numéro CAS : 67762-27-0 Origine : 100 % végétale, issue de matières renouvelables. Apparence : Solide blanc sous forme de pastilles. Solubilité : Soluble dans les huiles chaudes et cires végétales. Point de fusion : 48-55 °C. Dosage recommandé : 1-10 % selon la texture souhaitée. Provenance : États-Unis Mise en garde et conformité Usage externe uniquement. Le port de gants, d’un masque et de lunettes de protection est fortement recommandé. Toujours travailler dans un endroit bien aéré pour garantir votre sécurité. Responsabilité : Pure Arôme Laboratoire ne peut être tenu responsable des incidents, accidents ou réactions liés à l’utilisation ou au produit fini créé par le client.
A36: Pure Arôme | B36: Alcool cétylique | C36: Cires | D36: Cetyl Alcohol | Q36: https://www.purearome.com/fr/produit/alcool-cetylique | R36: Propre | T36: 46108 | U36: Alcool cétylique Accueil Produits Alcool cétylique Alcool cétylique Sku: ACETY En stock Alcool cétylique Sku: ACETY En stock 7,95 $ CAD Produit non disponible à l'achat en ligne Partager L’alcool cétylique est un ingrédient naturel dérivé de matières premières végétales renouvelables. Reconnu pour ses propriétés épaississantes, émollientes et stabilisantes, il est idéal pour vos formulations de crèmes, lotions, baumes et soins capillaires, tout en offrant une qualité professionnelle et durable. Chez Pure Arôme Laboratoire, nous vous proposons un alcool cétylique de qualité pour vos créations cosmétiques et artisanales DIY. Simple d’utilisation et naturel, il apporte durabilité, stabilité et douceur à vos produits finis. Utilisations recommandées : Alcool cétylique pour cosmétiques : - Épaissit les crèmes et lotions pour une texture riche et crémeuse. - Stabilise les émulsions pour éviter la séparation des phases. - Adoucit et nourrit la peau grâce à ses propriétés émollientes. - Idéal pour les baumes, beurres corporels et déodorants solides. Alcool cétylique pour soins capillaires : - Apporte une texture douce et soyeuse aux après-shampoings et masques. - Facilite le démêlage et laisse les cheveux hydratés et nourris. Caractéristiques principales : Polyvalent et compatible avec huiles, cires et bases naturelles. Naturel, sans parabènes ni phtalates. Facile à utiliser grâce à sa dissolution rapide dans les formulations chauffées. Qualité supérieure pour des produits solides, performants et durables. Spécifications techniques : Inci : Cetyl Alcohol Numéro CAS : 36653-82-4 Origine : 100 % végétale, issue de matières renouvelables. Apparence : Solide blanc sous forme de pastilles. Solubilité : Soluble dans les huiles chaudes et cires végétales. Point de fusion : 48-55 °C. Dosage recommandé : 1-5 % selon la texture souhaitée. Provenance : États-Unis. Mise en garde et conformité Usage externe uniquement. Le port de gants, d’un masque et de lunettes de protection est fortement recommandé. Toujours travailler dans un endroit bien aéré pour garantir votre sécurité. Responsabilité : Pure Arôme Laboratoire ne peut être tenu responsable des incidents, accidents ou réactions liés à l’utilisation ou au produit fini créé par le client.
A37: Pure Arôme | B37: BTMS 25 émulsifiant conditionneur | C37: Cires | D37: Behentrimonium Methosulfate (and) Cetearyl Alcohol | Q37: https://www.purearome.com/fr/produit/btms-25-emulsifiant-conditionneur | R37: Propre | T37: 46108 | U37: BTMS 25 émulsifiant conditionneur Accueil Produits BTMS 25 émulsifiant conditionneur BTMS 25 émulsifiant conditionneur Sku: BTMS25 En stock BTMS 25 émulsifiant conditionneur Sku: BTMS25 En stock 14,95 $ CAD Produit non disponible à l'achat en ligne Partager Le BTMS 25 est un émulsifiant végétal, reconnu pour ses propriétés conditionnant et émollient, idéal pour la formulation de crèmes, lotions et soins capillaires. Dérivé de matières premières végétales renouvelables, il facilite la création de produits doux, lissants et performants, tout en offrant une texture légère et onctueuse. Chez Pure Arôme Laboratoire, nous vous proposons un BTMS 25 de qualité pour vos créations cosmétiques et capillaires DIY. Simple d’utilisation et polyvalent, il apporte stabilité, douceur et performance à vos produits finis. Utilisations recommandées : BTMS 25 pour soins capillaires : - Facilite le démêlage des cheveux tout en réduisant les frisottis. - Laisse les cheveux doux, soyeux et nourris sans effet gras. - Parfait pour les après-shampoings, masques capillaires et crèmes coiffantes. BTMS 25 pour cosmétiques : - Émulsifie les crèmes et lotions tout en apportant une texture légère et veloutée. - Améliore l’effet hydratant des produits grâce à ses propriétés émollientes. - Idéal pour les soins de la peau et les baumes nourrissants. Caractéristiques principales : Émulsifiant doux pour la peau et les cheveux. Propriétés conditionnantes pour des cheveux démêlés et soyeux. Naturel, sans parabènes ni phtalates. Compatible avec huiles, cires et actifs cosmétiques. Qualité supérieure pour des produits stables et performants. Spécifications techniques : Inci : Behentrimonium Methosulfate (and) Cetearyl Alcohol Numéro CAS : 81646-13-1, 67762-27-0 Origine : Végétale, issue de matières renouvelables. Apparence : Solide blanc sous forme de pastilles ou flocons Solubilité : Soluble dans les huiles chaudes et cires végétales. Point de fusion : 55-60 °C. Dosage recommandé : 1-10 % selon la texture et l’effet souhaité. Provenance : États-Unis. Mise en garde et conformité Usage externe uniquement. Le port de gants, d’un masque et de lunettes de protection est fortement recommandé. Toujours travailler dans un endroit bien aéré pour garantir votre sécurité. Responsabilité : Pure Arôme Laboratoire ne peut être tenu responsable des incidents, accidents ou réactions liés à l’utilisation ou au produit fini créé par le client. Document : FDS BTMS-25 fr.pdf
A38: Pure Arôme | B38: Cire d'Abeilles en pastilles (Blanche) | C38: Cires | D38: Cera Alba | Q38: https://www.purearome.com/fr/produit/cire-d-abeilles-en-pastilles-blanche | R38: Propre | T38: 46108 | U38: Cire d&#x27;Abeilles en Pastilles (Blanche) Accueil Produits Cire d'Abeilles en pastilles (Blanche) Cire d'Abeilles en pastilles (Blanche) Sku: ABEIBLAN En stock Cire d'Abeilles en pastilles (Blanche) Sku: ABEIBLAN En stock 16,50 $ CAD Produit non disponible à l'achat en ligne Partager La cire d’abeilles en pastilles blanches est un ingrédient naturel polyvalent, idéal pour vos créations artisanales et cosmétiques. Raffinée pour un aspect uniforme et une qualité optimale, cette cire blanche offre une excellente stabilité et des propriétés hydratantes, épaississantes et protectrices. Elle est parfaite pour les baumes, les crèmes, les chandelles, et autres produits DIY, tout en répondant aux exigences d’une fabrication écologique et durable. Utilisations recommandées : Cire d’abeilles pour cosmétiques : - Épaissit les formulations pour une texture onctueuse et stable. - Forme une barrière protectrice qui aide à retenir l’hydratation. - Idéale pour les baumes à lèvres, crèmes et beurres corporels. Cire d’abeilles pour chandelles : - Offre une combustion propre et durable. - Mélange parfaitement avec des huiles essentielles et des fragrances pour une diffusion harmonieuse. - Idéale pour les chandelles moulées ou en contenants. Caractéristiques principales : Blanche (raffinée pour éliminer les impuretés et les pigments naturels). Pastilles faciles à manipuler et à mesurer. 100 % pure, sans additifs ni contaminants. Compatible avec les huiles, les beurres, les cires et autres bases naturelles. Spécifications techniques : Inci : Cera Alba Numéro CAS : 8012-89-3 Origine : Produite de manière éthique par des apiculteurs responsables. Apparence : Solide en pastilles blanches. Solubilité : Soluble dans les huiles et les solvants organiques. Point de fusion : 62-65 °C Dosage recommandé : 1-50 % selon l’utilisation. Provenance : États-Unis Mise en garde et conformité : Usage externe uniquement. Éviter tout contact avec les yeux. Toujours travailler dans un endroit bien aéré et utiliser des équipements de protection individuelle. Responsabilité : Pure Arôme Laboratoire ne peut être tenu responsable des incidents, accidents ou réactions liés à l’utilisation ou au produit fini créé par le client. Document : FDS Cire abeilles blanche pastilles fr.pdf
... A42: Pure Arôme | B42: Cire de Soja | C42: Cires | D42: Soy wax | Q42: https://www.purearome.com/fr/produit/cire-de-soja | R42: Propre | T42: 46108 | U42: Cire de Soja Accueil Produits Cire de Soja Cire de Soja Sku: WAX-SOY En stock Cire de Soja Sku: WAX-SOY En stock 15,50 $ CAD Produit non disponible à l'achat en ligne Partager CIre de soja naturel Inci : Soy wax Cette cire de soja d’excellente qualité peut être utilisée pour les chandelles en contenant, les crèmes, les beurres corporels et tout autre produit. C’est une cire douce pour la peau. Cette cire ne dégage pas d’émanations toxiques. À titre indicatif : Fondre à: 80°C Mouler à: 50°C
A43: Pure Arôme | B43: Cire émulsifiante | C43: Cires | Q43: https://www.purearome.com/fr/produit/cire-emulsifiante | R43: À valider | T43: 46108 | U43: Cire Émulsifiante Accueil Produits Cire émulsifiante Cire émulsifiante Sku: POLAWAX En stock Cire émulsifiante Sku: POLAWAX En stock 6,99 $ CAD Produit non disponible à l'achat en ligne Partager Cire émulsifiante Inci : Cetylstearyl Alcohol(and) Polysorbate 60 Polawax est une cire émulsifiante très classique en cosmétique. Elle permet la réalisation de très belles crèmes onctueuses, plutôt épaisses, dotées d'une excellente texture et d'une grande stabilité sur une large gamme de pH et de température. La Cire émulsifiante Polawax induit la formation, au sein de l'émulsion, de cristaux liquides et de structures lamellaires, favorisant ainsi une hydratation longue durée et une libération progressive des actifs, une hydratation des couches supérieures de l'épiderme. Procédé d'obtention : Association d'un alcool gras d'origine végétale (cetearyl alcool) et d'un dérivé de sucre (sorbitan) éthoxylé et estérifié par un alcool gras d'origine végétale. Fonction : émulsifiant, permet la formation et la tenue d'une émulsion (mélange crémeux ou laiteux d'une phase aqueuse et d'une phase huileuse) dans le temps. Qualité : Produit à partir de matières premières d'origine végétale. Présentation : Solide cireux en copeaux de couleur blanc cassé
A44: Pure Arôme | B44: Colorant à Bougie en Bloc Bleu Royal | C44: Cires | Q44: https://www.purearome.com/fr/produit/colorant-a-bougie-en-bloc-bleu-royal | R44: À valider | T44: 46108 | U44: Colorant à Bougie en Bloc Bleu Roya Accueil Produits Colorant à Bougie en Bloc Bleu Royal Colorant à Bougie en Bloc Bleu Royal Sku: CBB-BR En stock Colorant à Bougie en Bloc Bleu Royal Sku: CBB-BR En stock 5,99 $ CAD Produit non disponible à l'achat en ligne Partager Colorant à bougie en bloc Couleur : Bleu royal Grade : Cosmétique Les colorants à bougie Laboratoire Pure Arome est une sélection de colorant de coloration en blocs de cire aux couleurs soutenues. Les pigments naturels en blocs de cire Laboratoire Pure Arome sont non toxiques et sans danger pour l’environnement. Ils sont élaborés sur des bases de pigments naturels inorganiques, de minéraux et d’oxydes de métaux. Ils ont été développés pour obtenir un nuancier aux couleurs riches. Les colorants à bougie secs Laboratoire Pure Arome offrent une bonne résistance aux rayons UV Ils se dissolvent dans les cires. Utilisation des colorant à bougie Laboratoire Pure Arome en blocs de cire : Faire fondre le colorant avec la cire. Un carré de colorant peut colorer jusqu'à 10 lbs et plus de cire.
A45: Pure Arôme | B45: Colorant à Bougie en Bloc Brun | C45: Cires | Q45: https://www.purearome.com/fr/produit/colorant-a-bougie-en-bloc-brun | R45: À valider | T45: 46108 | U45: Colorant à Bougie en Bloc Brun Accueil Produits Colorant à Bougie en Bloc Brun Colorant à Bougie en Bloc Brun Sku: CBB-BN En stock Colorant à Bougie en Bloc Brun Sku: CBB-BN En stock 5,99 $ CAD Produit non disponible à l'achat en ligne Partager Colorant à bougie en bloc (2 blocs) Couleur : Brun Grade : Cosmétique Les colorants à bougie Laboratoire Pure Arome est une sélection de colorant de coloration en blocs de cire aux couleurs soutenues. Les pigments naturels en blocs de cire Laboratoire Pure Arome sont non toxiques et sans danger pour l'environnement. Ils sont élaborés sur des bases de pigments naturels inorganiques, de minéraux et d'oxydes de métaux. Ils ont été développés pour obtenir un nuancier aux couleurs riches. Les colorants à bougie secs Laboratoire Pure Arome offrent une bonne résistance aux rayons UV Ils se dissolvent dans les cires. Utilisation des colorant à bougie Laboratoire Pure Arome en blocs de cire : Faire fondre le colorant avec la cire. Un carré de colorant peut colorer jusqu'à 10 lbs et plus de cire.
A46: Pure Arôme | B46: Colorant à Bougie en Bloc Jaune Soleil | C46: Cires | Q46: https://www.purearome.com/fr/produit/colorant-a-bougie-en-bloc-jaune-soleil | R46: À valider | T46: 46108 | U46: Colorant à Bougie en Bloc Jaune Soleil Accueil Produits Colorant à Bougie en Bloc Jaune Soleil Colorant à Bougie en Bloc Jaune Soleil Sku: CBB-JS En stock Colorant à Bougie en Bloc Jaune Soleil Sku: CBB-JS En stock 5,99 $ CAD Produit non disponible à l'achat en ligne Partager Colorant à bougie en bloc (2 blocs) Couleur :Jaune Soleil Grade : Cosmétique Les colorants à bougie Laboratoire Pure Arome est une sélection de colorant de coloration en blocs de cire aux couleurs soutenues. Les pigments naturels en blocs de cire Laboratoire Pure Arome sont non toxiques et sans danger pour l'environnement. Ils sont élaborés sur des bases de pigments naturels inorganiques, de minéraux et d'oxydes de métaux. Ils ont été développés pour obtenir un nuancier aux couleurs riches. Les colorants à bougie secs Laboratoire Pure Arome offrent une bonne résistance aux rayons UV Ils se dissolvent dans les cires. Utilisation des colorant à bougie Laboratoire Pure Arome en blocs de cire : Faire fondre le colorant avec la cire. Un carré de colorant peut colorer jusqu'à 10 lbs et plus de cire.
A47: Pure Arôme | B47: Colorant à Bougie en Bloc Magenta | C47: Cires | Q47: https://www.purearome.com/fr/produit/colorant-a-bougie-en-bloc-magenta | R47: À valider | T47: 46108 | U47: Colorant à Bougie en Bloc Magenta Accueil Produits Colorant à Bougie en Bloc Magenta Colorant à Bougie en Bloc Magenta Sku: CBB-MG En stock Colorant à Bougie en Bloc Magenta Sku: CBB-MG En stock 5,99 $ CAD Produit non disponible à l'achat en ligne Partager Colorant à bougie en bloc (2 blocs) Couleur : Magenta Grade : Cosmétique Les colorants à bougie Laboratoire Pure Arome est une sélection de colorant de coloration en blocs de cire aux couleurs soutenues. Les pigments naturels en blocs de cire Laboratoire Pure Arome sont non toxiques et sans danger pour l'environnement. Ils sont élaborés sur des bases de pigments naturels inorganiques, de minéraux et d'oxydes de métaux. Ils ont été développés pour obtenir un nuancier aux couleurs riches. Les colorants à bougie secs Laboratoire Pure Arome offrent une bonne résistance aux rayons UV Ils se dissolvent dans les cires. Utilisation des colorant à bougie Laboratoire Pure Arome en blocs de cire : Faire fondre le colorant avec la cire. Un carré de colorant peut colorer jusqu'à 10 lbs et plus de cire.
A48: Pure Arôme | B48: Colorant à Bougie en Bloc Mauve | C48: Cires | Q48: https://www.purearome.com/fr/produit/colorant-a-bougie-en-bloc-mauve | R48: À valider | T48: 46108 | U48: Colorant à Bougie en Bloc Mauve Accueil Produits Colorant à Bougie en Bloc Mauve Colorant à Bougie en Bloc Mauve Sku: CBB-MV En stock Colorant à Bougie en Bloc Mauve Sku: CBB-MV En stock 5,99 $ CAD Produit non disponible à l'achat en ligne Partager Colorant à bougie en bloc (2 blocs) Couleur : Mauve Grade : Cosmétique Les colorants à bougie Laboratoire Pure Arome est une sélection de colorant de coloration en blocs de cire aux couleurs soutenues. Les pigments naturels en blocs de cire Laboratoire Pure Arome sont non toxiques et sans danger pour l'environnement. Ils sont élaborés sur des bases de pigments naturels inorganiques, de minéraux et d'oxydes de métaux. Ils ont été développés pour obtenir un nuancier aux couleurs riches. Les colorants à bougie secs Laboratoire Pure Arome offrent une bonne résistance aux rayons UV Ils se dissolvent dans les cires. Utilisation des colorant à bougie Laboratoire Pure Arome en blocs de cire : Faire fondre le colorant avec la cire. Un carré de colorant peut colorer jusqu'à 10 lbs et plus de cire.
A49: Pure Arôme | B49: Colorant à Bougie en Bloc Noir | C49: Cires | Q49: https://www.purearome.com/fr/produit/colorant-a-bougie-en-bloc-noir | R49: À valider | T49: 46108 | U49: Colorant à Bougie en Bloc Noir Accueil Produits Colorant à Bougie en Bloc Noir Colorant à Bougie en Bloc Noir Sku: CBB-NR En stock Colorant à Bougie en Bloc Noir Sku: CBB-NR En stock 5,99 $ CAD Produit non disponible à l'achat en ligne Partager Colorant à bougie en bloc (2 blocs) Couleur : Noir Grade : Cosmétique Les colorants à bougie Laboratoire Pure Arome est une sélection de colorant de coloration en blocs de cire aux couleurs soutenues. Les pigments naturels en blocs de cire Laboratoire Pure Arome sont non toxiques et sans danger pour l'environnement. Ils sont élaborés sur des bases de pigments naturels inorganiques, de minéraux et d'oxydes de métaux. Ils ont été développés pour obtenir un nuancier aux couleurs riches. Les colorants à bougie secs Laboratoire Pure Arome offrent une bonne résistance aux rayons UV Ils se dissolvent dans les cires. Utilisation des colorant à bougie Laboratoire Pure Arome en blocs de cire : Faire fondre le colorant avec la cire. Un carré de colorant peut colorer jusqu'à 10 lbs et plus de cire.
A50: Pure Arôme | B50: Colorant à Bougie en Bloc Orange | C50: Cires | Q50: https://www.purearome.com/fr/produit/colorant-a-bougie-en-bloc-orange | R50: À valider | T50: 46108 | U50: Colorant à Bougie en Bloc Orange Accueil Produits Colorant à Bougie en Bloc Orange Colorant à Bougie en Bloc Orange Sku: CBB-OR En stock Colorant à Bougie en Bloc Orange Sku: CBB-OR En stock 5,99 $ CAD Produit non disponible à l'achat en ligne Partager Colorant à bougie en bloc (2 blocs) Couleur : Orange Grade : Cosmétique Les colorants à bougie Laboratoire Pure Arôme est une sélection de colorant de coloration en blocs de cire aux couleurs soutenues. Les pigments naturels en blocs de cire Laboratoire Pure Arôme sont non toxiques et sans danger pour l'environnement. Ils sont élaborés sur des bases de pigments naturels inorganiques, de minéraux et d'oxydes de métaux. Ils ont été développés pour obtenir un nuancier aux couleurs riches. Les colorants à bougie sec Laboratoire Pure Arôme offrent une bonne résistance aux rayons UV Ils se dissolvent dans les cires. Utilisation des colorant à bougie Laboratoire Pure Arôme en blocs de cire : Faire fondre le colorant avec la cire. Un carré de colorant peut colorer jusqu'à 10 lbs et plus de cire.
A51: Pure Arôme | B51: Colorant à Bougie en Bloc Orange Brûlé | C51: Cires | Q51: https://www.purearome.com/fr/produit/colorant-a-bougie-en-bloc-orange-brule | R51: À valider | T51: 46108 | U51: Colorant à Bougie en Bloc Orange Brûlé Accueil Produits Colorant à Bougie en Bloc Orange Brûlé Colorant à Bougie en Bloc Orange Brûlé Sku: CBB-OB En stock Colorant à Bougie en Bloc Orange Brûlé Sku: CBB-OB En stock 5,99 $ CAD Produit non disponible à l'achat en ligne Partager Colorant à bougie en bloc (2 blocs) Couleur : Orange brûlé Grade : Cosmétique Les colorants à bougie Laboratoire Pure Arôme est une sélection de colorant de coloration en blocs de cire aux couleurs soutenues. Les pigments naturels en blocs de cire Laboratoire Pure Arôme sont non toxiques et sans danger pour l'environnement. Ils sont élaborés sur des bases de pigments naturels inorganiques, de minéraux et d'oxydes de métaux. Ils ont été développés pour obtenir un nuancier aux couleurs riches. Les colorants à bougie sec Laboratoire Pure Arôme offrent une bonne résistance aux rayons UV Ils se dissolvent dans les cires. Utilisation des colorant à bougie Laboratoire Pure Arôme en blocs de cire : Faire fondre le colorant avec la cire. Un carré de colorant peut colorer jusqu'à 10 lbs et plus de cire.
A52: Pure Arôme | B52: Colorant à Bougie en Bloc Rose | C52: Cires | Q52: https://www.purearome.com/fr/produit/colorant-a-bougie-en-bloc-rose | R52: À valider | T52: 46108 | U52: Colorant à Bougie en Bloc Rose Accueil Produits Colorant à Bougie en Bloc Rose Colorant à Bougie en Bloc Rose Sku: CBB-RS En stock Colorant à Bougie en Bloc Rose Sku: CBB-RS En stock 5,99 $ CAD Produit non disponible à l'achat en ligne Partager Colorant à bougie en bloc (2 blocs) Couleur : Rose Grade : Cosmétique Les colorants à bougie Laboratoire Pure Arôme est une sélection de colorant de coloration en blocs de cire aux couleurs soutenues. Les pigments naturels en blocs de cire Laboratoire Pure Arôme sont non toxiques et sans danger pour l'environnement. Ils sont élaborés sur des bases de pigments naturels inorganiques, de minéraux et d'oxydes de métaux. Ils ont été développés pour obtenir un nuancier aux couleurs riches. Les colorants à bougie sec Laboratoire Pure Arôme offrent une bonne résistance aux rayons UV Ils se dissolvent dans les cires. Utilisation des colorant à bougie Laboratoire Pure Arôme en blocs de cire : Faire fondre le colorant avec la cire. Un carré de colorant peut colorer jusqu'à 10 lbs et plus de cire.
A53: Pure Arôme | B53: Colorant à Bougie en Bloc Rouge | C53: Cires | Q53: https://www.purearome.com/fr/produit/colorant-a-bougie-en-bloc-rouge | R53: À valider | T53: 46108 | U53: Colorant à Bougie en Bloc Rouge Accueil Produits Colorant à Bougie en Bloc Rouge Colorant à Bougie en Bloc Rouge Sku: CBB-RG En stock Colorant à Bougie en Bloc Rouge Sku: CBB-RG En stock 5,99 $ CAD Produit non disponible à l'achat en ligne Partager Colorant à bougie en bloc (2 blocs) Couleur : Rouge Grade : Cosmétique Les colorants à bougie Laboratoire Pure Arôme est une sélection de colorant de coloration en blocs de cire aux couleurs soutenues. Les pigments naturels en blocs de cire Laboratoire Pure Arôme sont non toxiques et sans danger pour l'environnement. Ils sont élaborés sur des bases de pigments naturels inorganiques, de minéraux et d'oxydes de métaux. Ils ont été développés pour obtenir un nuancier aux couleurs riches. Les colorants à bougie secs Laboratoire Pure Arôme offrent une bonne résistance aux rayons UV Ils se dissolvent dans les cires. Utilisation des colorant à bougie Laboratoire Pure Arôme en blocs de cire : Faire fondre le colorant avec la cire. Un carré de colorant peut colorer jusqu'à 10 lbs et plus de cire.
A54: Pure Arôme | B54: Colorant à Bougie en Bloc Rouge Framboise | C54: Cires | Q54: https://www.purearome.com/fr/produit/colorant-a-bougie-en-bloc-rouge-framboise | R54: À valider | T54: 46108 | U54: Colorant à Bougie en Bloc Rouge Framboise Accueil Produits Colorant à Bougie en Bloc Rouge Framboise Colorant à Bougie en Bloc Rouge Framboise Sku: CBB-RF En stock Colorant à Bougie en Bloc Rouge Framboise Sku: CBB-RF En stock 5,99 $ CAD Produit non disponible à l'achat en ligne Partager Colorant à bougie en bloc (2 blocs) Couleur :Rouge framboise Grade : Cosmétique Les colorants à bougie Laboratoire Pure Arome est une sélection de colorant de coloration en blocs de cire aux couleurs soutenues. Les pigments naturels en blocs de cire Laboratoire Pure Arome sont non toxiques et sans danger pour l'environnement. Ils sont élaborés sur des bases de pigments naturels inorganiques, de minéraux et d'oxydes de métaux. Ils ont été développés pour obtenir un nuancier aux couleurs riches. Les colorants à bougie secs Laboratoire Pure Arome offrent une bonne résistance aux rayons UV Ils se dissolvent dans les cires. Utilisation des colorant à bougie Laboratoire Pure Arome en blocs de cire : Faire fondre le colorant avec la cire. Un carré de colorant peut colorer jusqu'à 10 lbs et plus de cire.
... A57: Pure Arôme | B57: Colorant à Bougie en Bloc Vert Outremer | C57: Cires | Q57: https://www.purearome.com/fr/produit/colorant-a-bougie-en-bloc-vert-outremer | R57: À valider | T57: 46108 | U57: Colorant à Bougie en Bloc Vert Outremer Accueil Produits Colorant à Bougie en Bloc Vert Outremer Colorant à Bougie en Bloc Vert Outremer Sku: CBB-VO En stock Colorant à Bougie en Bloc Vert Outremer Sku: CBB-VO En stock 5,99 $ CAD Produit non disponible à l'achat en ligne Partager Colorant à bougie en bloc (2 blocs) Couleur :Vert Outremer Grade : Cosmétique Les colorants à bougie Laboratoire Pure Arome est une sélection de colorant de coloration en blocs de cire aux couleurs soutenues. Les pigments naturels en blocs de cire Laboratoire Pure Arome sont non toxiques et sans danger pour l'environnement. Ils sont élaborés sur des bases de pigments naturels inorganiques, de minéraux et d'oxydes de métaux. Ils ont été développés pour obtenir un nuancier aux couleurs riches. Les colorants à bougie secs Laboratoire Pure Arome offrent une bonne résistance aux rayons UV Ils se dissolvent dans les cires. Utilisation des colorant à bougie Laboratoire Pure Arome en blocs de cire : Faire fondre le colorant avec la cire. Un carré de colorant peut colorer jusqu'à 10 lbs et plus de cire.
A58: Pure Arôme | B58: Contenant pour pastilles de cire – 6 cavités carrées | C58: Cires | Q58: https://www.purearome.com/fr/produit/contenant-pour-pastilles-de-cire-6-cavites-carrees | R58: Sans INCI | T58: 46108
A59: Pure Arôme | B59: Contenant pour pastilles de cire – 6 cavités cœur | C59: Cires | Q59: https://www.purearome.com/fr/produit/contenant-pour-pastilles-de-cire-6-cavites-coeur | R59: Sans INCI | T59: 46108
A60: Pure Arôme | B60: Contenant pour pastilles de cire – 6 cavités rondes | C60: Cires | Q60: https://www.purearome.com/fr/produit/contenant-pour-pastilles-de-cire-6-cavites-rondes | R60: Sans INCI | T60: 46108
A61: Pure Arôme | B61: Glycéryl de stéarate SE | C61: Cires | D61: Glyceryl stearate | Q61: https://www.purearome.com/fr/produit/glyceryl-de-stearate-se | R61: Propre | T61: 46108 | U61: Glycéryl de stéarate SE (Auto-émulsifiant) - Laboratoire Pure arôme - Fournissseur de matières premières cosmétiques DIY Accueil Produits Glycéryl de stéarate SE Glycéryl de stéarate SE Sku: GSSE En stock Glycéryl de stéarate SE Sku: GSSE En stock 9,95 $ CAD Produit non disponible à l'achat en ligne Partager Glycéryl de stéarate SE (Auto-émulsifiant) Inci : Glyceryl stearate CAS: 11099-07-3 / Forme : granule Découvrez les bienfaits du Glycéryl Stéarate SE (Auto-émulsifiant) Pure arôme. Aussi connu sous ces noms : Stéarate de glycérol AE, Stéarate de glycéryle SE. Émulsifiant et Stabilisant, cet ingrédient permet de mélanger des substances qui ne se mélangent pas naturellement, comme l'eau et l'huile, pour créer des crèmes, des lotions, des baumes et des gels onctueux et stables. Épaississant Secondaire (5 %) : Il apporte une texture agréable aux produits, les rendant plus visqueux et faciles à appliquer. Hydratant et Émollient (5 %) : Le Glycéryl Stéarate SE hydrate la peau en profondeur et renforce sa barrière naturelle pour une meilleure protection contre les agressions extérieures. Humectant (5 %) : Il attire et retient l'eau dans la peau, la gardant hydratée et souple pendant plusieurs heures. Ils convient à tous les types de peau, y compris les peaux sensibles. Avantages du Glycéryl Stéarate SE Polyvalent et multifonctionnel Améliore la texture et la consistance des produits Hydrate et protège la peau Renforce la barrière cutanée Sans danger pour les peaux sensibles Utilisé dans plusieurs types de cosmétiques tels que Crèmes Lotions Baumes Gels Soins du visage Soins du corps Le Glycéryl Stéarate SE est un ingrédient essentiel pour les formulateurs de cosmétiques qui recherchent des produits performants et doux pour la peau. Utilisation : En cosmétique, les concentrations peuvent varier en fonction de la formulation du produit. Voici les pourcentages d'utilisation recommandés : Émulsions eau-dans-huile (E/H) : 1 à 5% / Émulsions huile-dans-eau (H/E) : 2 à 10% / Crèmes et lotions : 1 à 4% / Baumes et gels : 2 à 6% / Soins du visage : 0,5 à 3% / Soins du corps : 1 à 5% Apparence : Veuillez noter que le produit peut parfois arriver sous une forme ou une couleur différente de celle illustrée sur la photo. Cela est hors de notre contrôle car nous travaillons avec des produits végétaux, mais nous tenons à vous assurer que le produit conserve la même efficacité et valeur. "Nous sommes engagés dans la protection de l'environnement et le respect des normes éthiques dans l'industrie cosmétique. C'est pourquoi tous nos produits de matières premières cosmétiques sont sans cruauté et n'ont pas été testés sur les animaux. Nous sommes fiers de proposer une gamme de produits respectueuse de la santé de l'environnement et éco-responsable." - À usage externe uniquement.
A62: Pure Arôme | B62: Mèches à chandelle en bois | C62: Cires | Q62: https://www.purearome.com/fr/produit/meches-a-chandelle-en-bois | R62: Sans INCI | T62: 46108
A63: Pure Arôme | B63: Mèches à chandelle HTP 104 pré-cirées avec socles | C63: Cires | Q63: https://www.purearome.com/fr/produit/meches-a-chandelle-htp-104-pre-cirees-avec-socles | R63: Sans INCI | T63: 46108
A64: Pure Arôme | B64: Mèches à chandelle HTP 105 pré-cirées avec socles | C64: Cires | Q64: https://www.purearome.com/fr/produit/meches-a-chandelle-htp-105-pre-cirees-avec-socles | R64: Sans INCI | T64: 46108
A65: Pure Arôme | B65: Mèches à chandelle HTP 126 pré-cirées avec socles | C65: Cires | Q65: https://www.purearome.com/fr/produit/meches-a-chandelle-htp-126-pre-cirees-avec-socles | R65: Sans INCI | T65: 46108
A66: Pure Arôme | B66: Mèches à chandelle HTP 73 pré-cirées avec socles | C66: Cires | Q66: https://www.purearome.com/fr/produit/meches-a-chandelle-htp-73-pre-cirees-avec-socles | R66: Sans INCI | T66: 46108
A67: Pure Arôme | B67: Mèches à chandelle HTP 83 pré-cirées avec socles | C67: Cires | Q67: https://www.purearome.com/fr/produit/meches-a-chandelle-htp-83-pre-cirees-avec-socles | R67: Sans INCI | T67: 46108
A68: Pure Arôme | B68: Mèches à chandelle HTP 93 pré-cirées avec socles | C68: Cires | Q68: https://www.purearome.com/fr/produit/meches-a-chandelle-htp-93-pre-cirees-avec-socles | R68: Sans INCI | T68: 46108
A69: Pure Arôme | B69: Olivem 1000 – Émulsifiant Naturel | C69: Cires | D69: Cetearyl Olivate, Sorbitan Olivate) | Q69: https://www.purearome.com/fr/produit/olivem-1000-emulsifiant-naturel | R69: Propre | T69: 46108 | U69: Olivem® 1000 – Émulsifiant Naturel pour Cosmétique DIY et Crèmes | Pure Arôme Accueil Produits Olivem 1000 – Émulsifiant Naturel Olivem 1000 – Émulsifiant Naturel Sku: OLIVEM En stock Olivem 1000 – Émulsifiant Naturel Sku: OLIVEM En stock 12,00 $ CAD Produit non disponible à l'achat en ligne Partager Olivem® 1000 – Émulsifiant Naturel L’ Olivem® 1000 (INCI : Cetearyl Olivate, Sorbitan Olivate) est un émulsifiant naturel dérivé de l’huile d’olive, conforme aux standards ECOCERT et COSMOS , largement utilisé par les formulateurs professionnels et les passionnés de cosmétique. Cet ingrédient polyvalent permet de créer des émulsions huile-dans-eau stables, offrant une texture soyeuse et une hydratation longue durée. Reconnu pour son excellente compatibilité avec la peau, Olivem® 1000 est idéal pour les crèmes, lotions, sérums et baumes naturels, tout en respectant les exigences des formulations écologiques. Chez Pure Arôme Laboratoire , nous vous proposons un Olivem® 1000 de qualité cosmétique premium, sans OGM, non testé sur les animaux, parfait pour les artisans conscients et les formulateurs recherchant des solutions naturelles et performantes pour leurs créations cosmétiques . Utilisations recommandées : Olivem® 1000 pour formulations cosmétiques naturelles : Émulsifiant pour crèmes, lotions, sérums, et produits de soin visage/corps. Compatible avec une large gamme de pH (3 à 8), idéal pour des formulations bien équilibrées. Conforme aux standards ECOCERT et COSMOS , parfait pour les cosmétiques naturels et bio. Olivem® 1000 pour soins maison et DIY : Idéal pour les émulsions légères ou riches, comme les crèmes hydratantes, les laits corporels, et les soins capillaires. Apporte une texture veloutée et une sensation non grasse, parfaite pour les produits végans et respectueux de l’environnement. Facile à utiliser pour les amateurs de cosmétique maison souhaitant des résultats professionnels. Caractéristiques principales : Multi-usage : Émulsifiant naturel pour cosmétiques et soins DIY. Profil écologique : Dérivé de l’huile d’olive, biodégradable, sans OGM, non testé sur les animaux. Performance : Crée des émulsions stables avec une texture soyeuse et un effet hydratant. Compatibilité cutanée : Convient à tous les types de peau, y compris les peaux sensibles. Qualité premium : Conforme aux normes strictes de Santé Canada et aux standards cosmétiques Spécifications techniques : INCI : Cetearyl Olivate, Sorbitan Olivate Autres noms : Olivem® 1000, mélange d’esters d’olive. Numéro CAS : 68953-55-9 (Cetearyl Olivate), 223706-40-9 (Sorbitan Olivate) Composition : Mélange d’esters d’acides gras d’olive et d’alcools cétylique/stéarylique. Origine : Dérivé naturel (huile d’olive). Apparence : Pastilles ou flocons blanc cassé. Odeur : Légère, caractéristique. Solubilité : Soluble dans la phase huileuse ; insoluble dans l’eau. Point de fusion : 65-75 °C. pH en solution : 4 à 8 (optimal pour émulsions cosmétiques). Dosage recommandé : 2-8 % en cosmétique (incorporer à la phase huileuse, chauffer à 70-80 °C). Provenance : Italie Mise en garde et conformité : Usage externe uniquement . Ne pas utiliser pur sur la peau ou les muqueuses. Intégrer dans une formulation cosmétique bien équilibrée. Manipuler avec des gants et des lunettes de protection dans un environnement bien ventilé. Peut causer une irritation légère en cas de contact prolongé avec la peau ou les yeux. Tenir hors de portée des enfants. Conserver dans un endroit sec, frais (15-25 °C), à l’abri de la lumière et de l’humidité. Pure Arôme Laboratoire , ne peut être tenu responsable des incidents, accidents ou réactions liés à l’utilisation ou au produit fini créé par le client. Document : FDS Olivem 1000 fr.pdf
A70: Pure Arôme | B70: Charbon activé végétal | C70: Colorants et Pigments | D70: Activated charcoal | Q70: https://www.purearome.com/fr/produit/charbon-active-vegetal | R70: Propre | T70: 46108 | U70: Charbon activé végétal en poudre Accueil Produits Charbon activé végétal Charbon activé végétal Sku: CHARBON En stock Charbon activé végétal Sku: CHARBON En stock 9,99 $ CAD Produit non disponible à l'achat en ligne Partager Charbon activé végétal poudre Inci : Activated charcoal Le charbon 100% végétal super activé Laboratoire Pure arôme propose un charbon 100% végétal issu de noix de coco totalement soluble. Pour être parfaitement efficace et avoir une surface d'absorption maximale, le charbon est obtenu en deux étapes : ° La carbonisation : on calcine du bois ou des coques de noix de coco en le chauffant à une température variant entre 600°C et 900°C en l'absence d'air. ° L'activation : le bois est recalciné aux mêmes températures mais cette fois, en présence de vapeur d'eau, d'air ou de gaz oxydants. Ceci permet le développement d'un réseau de microspores qui seront de véritables pièges à molécules indésirables. L'activation donne ainsi au charbon une capacité d'absorption pouvant dépasser les 2000 m²/g. il peut adsorber jusqu'à 97 fois son volume de gaz carbonique, 165 fois son volume d'anhydride sulfureux, 178 fois son volume d'ammoniac. Le charbon végétal super activé 100% pur et naturel et 100% soluble se présente sous forme de poudre fine à surface d'échange supérieure à 2250 m2/g. Ainsi qu'un excellent colorant pour vos savons et autres créations de produits. Boutique Pure arôme 3565 Boulevard Taschereau Saint-Hubert Qc J4T 2G2 Tél : (514) 500-5534 Courriel : [email protected] Termes et conditions Confidentialité Politique d'expédition Contact Blogue et recettes Abonnez-vous à l'infolettre Courriel S'abonner Devise – cad © 2026 Pure arôme Tous droits réservés. Boutique en ligne par Panierdachat&trade; En visitant notre site, vous acceptez l'utilisation de cookies pour améliorer la qualité de votre visite, collecter les statistiques et mesurer notre audience afin de vous proposer des services et offres adaptés. J'accepte Personnaliser
A71: Pure Arôme | B71: Colorant liquide Bleu | C71: Colorants et Pigments | D71: Food colouring | Q71: https://www.purearome.com/fr/produit/colorant-liquide-bleu | R71: Propre | T71: 46108 | U71: Colorant liquide Bleu Accueil Produits Colorants et Pigments Colorants Liquides Colorant liquide Bleu Colorant liquide Bleu Sku: CO-BLEU En stock Colorant liquide Bleu Sku: CO-BLEU En stock 6,95 $ CAD Produit non disponible à l'achat en ligne Partager Colorant liquide Bleu Inci : Food colouring Notre colorant Bleu garde votre savon à son état pur. Exemple : Pour un savon transparent, le savon gardera sa transparence. Ce colorant peut être utilisé pour la fabrication de savons (Melt and pour), les crèmes, les bombes de bain, les savons liquides, les bains moussants, les gels de douche etc. Il ne peut pas être utilisé pour la fabrication de chandelles, onguents et savons procédés à froid ou tout produit à base d'huile.
A72: Pure Arôme | B72: Colorant liquide Chocolat | C72: Colorants et Pigments | D72: Food colouring | Q72: https://www.purearome.com/fr/produit/colorant-liquide-chocolat | R72: Propre | T72: 46108 | U72: Colorant liquide Chocolat Accueil Produits Colorants et Pigments Colorants Liquides Colorant liquide Chocolat Colorant liquide Chocolat Sku: CO-CHOCO En stock Colorant liquide Chocolat Sku: CO-CHOCO En stock 6,95 $ CAD Produit non disponible à l'achat en ligne Partager Colorant liquide Chocolat Inci : Food colouring Notre colorant Chocolat garde votre savon à son état pur. Exemple : Pour un savon transparent, le savon gardera sa transparence. Ce colorant peut être utilisé pour la fabrication de savons (Melt and pour), les crèmes, les bombes de bain, les savons liquides, les bains moussants, les gels de douche etc. Il ne peut pas être utilisé pour la fabrication de chandelles, onguents et savons procédés à froid ou tout produit à base d'huile.
A73: Pure Arôme | B73: Colorant liquide Jaune | C73: Colorants et Pigments | D73: Food colouring | Q73: https://www.purearome.com/fr/produit/colorant-liquide-jaune | R73: Propre | T73: 46108 | U73: Colorant liquide Jaune Accueil Produits Colorants et Pigments Colorants Liquides Colorant liquide Jaune Colorant liquide Jaune Sku: CO-JAU Colorant liquide Jaune Sku: CO-JAU 6,95 $ CAD Produit non disponible à l'achat en ligne Partager Colorant liquide Jaune Inci : Food colouring Notre colorant Jaune garde votre savon à son état pur. Exemple : Pour un savon transparent, le savon gardera sa transparence. Ce colorant peut être utilisé pour la fabrication de savons (Melt and pour), les crèmes, les bombes de bain, les savons liquides, les bains moussants, les gels de douche etc. Il ne peut pas être utilisé pour la fabrication de chandelles, onguents et savons procédés à froid ou tout produit à base d'huile.
A74: Pure Arôme | B74: Colorant liquide Jaune d'œuf | C74: Colorants et Pigments | D74: Food colouring | Q74: https://www.purearome.com/fr/produit/colorant-liquide-jaune-d-oeuf | R74: Propre | T74: 46108 | U74: Colorant liquide jaune d&#x27;œuf Accueil Produits Colorants et Pigments Colorants Liquides Colorant liquide Jaune d'œuf Colorant liquide Jaune d'œuf Sku: CO-JOEUF En stock Colorant liquide Jaune d'œuf Sku: CO-JOEUF En stock 6,95 $ CAD Produit non disponible à l'achat en ligne Partager Colorant liquide Jaune d' œuf Inci : Food colouring Notre colorant Jaune d'œuf garde votre savon à son état pur. Exemple : Pour un savon transparent, le savon gardera sa transparence. Ce colorant peut être utilisé pour la fabrication de savons (Melt and pour), les crèmes, les bombes de bain, les savons liquides, les bains moussants, les gels de douche etc. Il ne peut pas être utilisé pour la fabrication de chandelles, onguents et savons procédés à froid ou tout produit à base d'huile.
A75: Pure Arôme | B75: Colorant liquide Mauve | C75: Colorants et Pigments | D75: Food colouring | Q75: https://www.purearome.com/fr/produit/colorant-liquide-mauve | R75: Propre | T75: 46108 | U75: Colorant liquide Mauve Accueil Produits Colorants et Pigments Colorants Liquides Colorant liquide Mauve Colorant liquide Mauve Sku: CO-MAU En stock Colorant liquide Mauve Sku: CO-MAU En stock 6,95 $ CAD Produit non disponible à l'achat en ligne Partager Colorant liquide Mauve Inci : Food colouring Notre colorant Mauve garde votre savon à son état pur. Exemple : Pour un savon transparent, le savon gardera sa transparence. Ce colorant peut être utilisé pour la fabrication de savons (Melt and pour), les crèmes, les bombes de bain, les savons liquides, les bains moussants, les gels de douche etc. Il ne peut pas être utilisé pour la fabrication de chandelles, onguents et savons procédés à froid ou tout produit à base d'huile.
A76: Pure Arôme | B76: Colorant liquide Mauve glycérine | C76: Colorants et Pigments | D76: Food colouring (and) Glycerin | Q76: https://www.purearome.com/fr/produit/colorant-liquide-mauve-glycerine | R76: Propre | T76: 46108 | U76: Colorant liquide Mauve glycérine Accueil Produits Colorants et Pigments Colorants Liquides Colorant liquide Mauve glycérine Colorant liquide Mauve glycérine Sku: CO-MAUGL En stock Colorant liquide Mauve glycérine Sku: CO-MAUGL En stock 6,95 $ CAD Produit non disponible à l'achat en ligne Partager Colorant liquide Mauve glycérine Inci : Food colouring (and) Glycerin Notre colorant Mauve glycérine peut rendre votre savon opaque, donne un mauve lilas. Exemple : Pour un savon transparent, le savon peut être moins transparent. Ce colorant peut être utilisé pour la fabrication de savons (Melt and pour), les crèmes, les bombes de bain, les savons liquides, les bains moussants, les gels de douche etc. Il ne peut pas être utilisé pour la fabrication de chandelles, onguents et savons procédés à froid ou tout produit à base d'huile.
A77: Pure Arôme | B77: Colorant liquide Orange | C77: Colorants et Pigments | D77: Food colouring | Q77: https://www.purearome.com/fr/produit/colorant-liquide-orange | R77: Propre | T77: 46108 | U77: Colorant liquide Orange Accueil Produits Colorants et Pigments Colorants Liquides Colorant liquide Orange Colorant liquide Orange Sku: CO-ORAN En stock Colorant liquide Orange Sku: CO-ORAN En stock 6,95 $ CAD Produit non disponible à l'achat en ligne Partager Colorant liquide Orange Inci : Food colouring Notre colorant Orange garde votre savon à son état pur. Exemple : Pour un savon transparent, le savon gardera sa transparence. Ce colorant peut être utilisé pour la fabrication de savons (Melt and pour), les crèmes, les bombes de bain, les savons liquides, les bains moussants, les gels de douche etc. Il ne peut pas être utilisé pour la fabrication de chandelles, onguents et savons procédés à froid ou tout produit à base d'huile.
A78: Pure Arôme | B78: Colorant liquide Rose | C78: Colorants et Pigments | D78: Food colouring | Q78: https://www.purearome.com/fr/produit/colorant-liquide-rose | R78: Propre | T78: 46108 | U78: Colorant liquide Rose Accueil Produits Colorants et Pigments Colorants Liquides Colorant liquide Rose Colorant liquide Rose Sku: CO-ROSE En stock Colorant liquide Rose Sku: CO-ROSE En stock 6,95 $ CAD Produit non disponible à l'achat en ligne Partager Colorant liquide Rose Inci : Food colouring Notre colorant Rose garde votre savon à son état pur. Exemple : Pour un savon transparent, le savon gardera sa transparence. Ce colorant peut être utilisé pour la fabrication de savons (Melt and pour), les crèmes, les bombes de bain, les savons liquides, les bains moussants, les gels de douche etc. Il ne peut pas être utilisé pour la fabrication de chandelles, onguents et savons procédés à froid ou tout produit à base d'huile.
A79: Pure Arôme | B79: Colorant liquide Rouge | C79: Colorants et Pigments | D79: Food colouring | Q79: https://www.purearome.com/fr/produit/colorant-liquide-rouge | R79: Propre | T79: 46108 | U79: Colorant liquide Rouge Accueil Produits Colorants et Pigments Colorants Liquides Colorant liquide Rouge Colorant liquide Rouge Sku: CO-ROUG En stock Colorant liquide Rouge Sku: CO-ROUG En stock 6,95 $ CAD Produit non disponible à l'achat en ligne Partager Colorant liquide Rouge Inci : Food colouring Notre colorant Rouge garde votre savon à son état pur. Exemple : Pour un savon transparent, le savon gardera sa transparence. Ce colorant peut être utilisé pour la fabrication de savons (Melt and pour), les crèmes, les bombes de bain, les savons liquides, les bains moussants, les gels de douche etc. Il ne peut pas être utilisé pour la fabrication de chandelles, onguents et savons procédés à froid ou tout produit à base d'huile.
A80: Pure Arôme | B80: Colorant liquide Rouge noël | C80: Colorants et Pigments | D80: Food colouring | Q80: https://www.purearome.com/fr/produit/colorant-liquide-rouge-noel | R80: Propre | T80: 46108 | U80: Colorant liquide rouge noël Accueil Produits Colorants et Pigments Colorants Liquides Colorant liquide Rouge noël Colorant liquide Rouge noël Sku: CO-ROUNO En stock Colorant liquide Rouge noël Sku: CO-ROUNO En stock 6,95 $ CAD Produit non disponible à l'achat en ligne Partager Colorant liquide Rouge noël Inci : Food colouring Notre colorant Rouge noël garde votre savon à son état pur. Exemple : Pour un savon transparent, le savon gardera sa transparence. Ce colorant peut être utilisé pour la fabrication de savons (Melt and pour), les crèmes, les bombes de bain, les savons liquides, les bains moussants, les gels de douche etc. Il ne peut pas être utilisé pour la fabrication de chandelles, onguents et savons procédés à froid ou tout produit à base d'huile.
... A141: Pure Arôme | B141: Millepertuis en poudre | C141: Herbes et Fleurs | D141: Hypericum perforatum flower/leaf/stem extract | Q141: https://www.purearome.com/fr/produit/millepertuis-en-poudre | R141: Propre | T141: 46108 | U141: Millepertuis en poudre – Pure Arôme Laboratoire Accueil Produits Millepertuis en poudre Millepertuis en poudre Sku: PMILPER En stock Millepertuis en poudre Sku: PMILPER En stock 11,99 $ CAD Produit non disponible à l'achat en ligne Partager Millepertuis en poudre – Pure Arôme Laboratoire La poudre de millepertuis (Hypericum perforatum) est un ingrédient 100 % naturel, de grade cosmétique, obtenu par broyage fin des parties aériennes séchées (fleurs, feuilles et tiges). D’origine bulgare, elle est reconnue pour ses propriétés apaisantes et réparatrices, traditionnellement utilisées dans les soins cutanés et bien-être. Facile à intégrer, elle est idéale pour enrichir les masques, les baumes, cataplasmes et poudres de soin. Bienfaits et utilisations Apaisante et réparatrice pour les peaux fragiles ou irritées Soutient le confort cutané et favorise la régénération Convient aux masques, aux cataplasmes, baumes et soins réparateurs 100 % naturel, riche en composés végétaux bénéfiques Parfait pour formulations artisanales et cosmétiques écoresponsables Caractéristiques techniques INCI : Hypericum perforatum flower/leaf/stem extract CAS : 84082-80-4 Origine : Bulgarie Procédé d’obtention : broyage fin des parties aériennes séchées Aspect : poudre fine vert-brun avec nuances jaunâtres Odeur : végétale, légèrement herbacée Solubilité : dispersible dans l’eau (non soluble) pH : neutre à légèrement acide selon la solution Dosage recommandé : 1 % à 30 % selon la formulation Qualité : 100 % naturel, sans OGM, biodégradable, non testé sur les animaux Conservation : à l’abri de l’air, de la lumière et de l’humidité Conseils d’utilisation La poudre de millepertuis peut être incorporée dans des masques en poudre, cataplasmes ou baumes réparateurs. Elle peut également être dispersée dans une phase aqueuse selon la formule choisie pour enrichir vos soins cosmétiques maison. Mise en garde et conformité réglementaire Usage externe uniquement – ne pas ingérer Éviter le contact direct avec les yeux À utiliser selon les bonnes pratiques de formulation cosmétique Tenir hors de portée des enfants La couleur, l’odeur ou la texture peuvent varier légèrement selon les lots, sans altérer la qualité Avant toute commercialisation, assurez-vous de respecter la réglementation en vigueur et de déposer la déclaration obligatoire des cosmétiques auprès de Santé Canada Note importante, mais tout en douceur Les informations partagées ici sont proposées avec rigueur et bienveillance, basées sur les données scientifiques et notre expérience. Elles ne remplacent pas un avis médical. Nous t’encourageons à faire des tests en petite quantité dans tes formules. Pure Arôme Laboratoire ne peut être tenu responsable des usages finaux, mais reste à tes côtés pour t’accompagner 💛.
A142: Pure Arôme | B142: Pelures citron en poudre | C142: Herbes et Fleurs | D142: Citrus Limon (Lemon) Peel Powder | E142: Citrus limonum Provenance | Q142: https://www.purearome.com/fr/produit/pelures-citron-en-poudre | R142: Bot seul | T142: 46108 | U142: Pelures de Citron en Poudre Accueil Produits Pelures citron en poudre Pelures citron en poudre Sku: CITRONP En stock Pelures citron en poudre Sku: CITRONP En stock 10,95 $ CAD Produit non disponible à l'achat en ligne Partager Pelures d'écorces de Citron Nom Botanique : Citrus limonum Provenance : Usa Forme : Poudre La poudre de citron est un réel indispensable tout comme ça grande sœur la Pelure d'orange. Elle est tonifie, nettoie et fait briller les cheveux intensément. Utilisée sur le visage, elle purifie la peau en profondeur, resserre les pores et la tonifie. Sa douce arôme fait d'elle une poudre très agréable à utiliser et elle parfume agréablement tous vos soins à base de poudres de plantes. Elle offre également une excellente alternative aux colorants. Propriétés Renforce les immunités naturelles, régularise les métabolismes Régulatrice hépatique, anti vomitive Antiseptique général et bactéricide Antivirale Tonique digestif, carminative, dépurative générale Fluidifiante sanguine, action &quot; vitamin P-like &quot;(action sur la micro-circulation, diminution de la perméabilité des capillaires et augmentation de leur résistance)
A143: Pure Arôme | B143: Pétales de calendula | C143: Herbes et Fleurs | D143: Calendula Officinalis Flower Powder | E143: Calendula officinalis | Q143: https://www.purearome.com/fr/produit/petales-de-calendula | R143: Bot seul | T143: 46108 | U143: Pétales de Calendula Accueil Produits Pétales de calendula Pétales de calendula Sku: CALF En stock Pétales de calendula Sku: CALF En stock 13,50 $ CAD Produit non disponible à l'achat en ligne Partager Calendula Nom Botanique : Calendula officinalis Forme : pétales INFUSION : Le souci officinal agit non seulement sur le système immunitaire, fait baisser la fièvre, mais apaise aussi les inflammations de la gorge, la bouche, les troubles gastriques et hépatiques. Il nettoie ainsi le foie, soulage les inflammations gastriques, et les douleurs prémenstruelles. Un produit super pour la confection de savon, sel et bombe de bain. Ces feuilles ajouterons une touche de couleur à vos produits de confection.
A144: Pure Arôme | B144: Pétales de roses | C144: Herbes et Fleurs | D144: Rosa × damascena Flower Powder | E144: Rosa ×damascena | Q144: https://www.purearome.com/fr/produit/petales-de-roses | R144: Bot seul | T144: 46108 | U144: Fleurs Pétales de Roses Accueil Produits Pétales de roses Pétales de roses Sku: ROFL En rupture ! De retour bientôt Pétales de roses Sku: ROFL En rupture ! De retour bientôt 9,95 $ CAD Produit non disponible à l'achat en ligne Partager Rose de damas Nom Botanique : Rosa ×damascena Forme : Pétales Les pétales de roses en infusion s'avère être un excellent relaxant, peuvent être aussi utilisés pour décorer les assiettes, la table et les cocktails. En alimentation, osez en rajouter dans des biscuits, du glaçage, des beignes ou même dans une quiche. Soyez inventif et original, les possibilités sont infinies en cuisine. Sortez votre esprit romantique et décorez votre bain de pétales de rose. ça sent tellement bon la rose, pourquoi pas un pot-pourri? Un produit super pour la confection de savon, sel et bombe de bain. Ces feuilles ajouterons une touche romantique à vos produits de confection.
A145: Pure Arôme | B145: Pétales de roses en poudre | C145: Herbes et Fleurs | D145: Rosa × damascena Flower Powder | E145: Rosa ×damascena | Q145: https://www.purearome.com/fr/produit/petales-de-roses-en-poudre | R145: Bot seul | T145: 46108 | U145: Pétales de roses en poudre Accueil Produits Pétales de roses en poudre Pétales de roses en poudre Sku: ROSES-POWDER En stock Pétales de roses en poudre Sku: ROSES-POWDER En stock 10,95 $ CAD Produit non disponible à l'achat en ligne Partager Rose de damas Nom Botanique : Rosa ×damascena Forme : Poudre Les pétales de roses en infusion s'avère être un excellent relaxant, peuvent être aussi utilisés pour décorer les assiettes, la table et les cocktails. En alimentation, osez en rajouter dans des biscuits, du glaçage, des beignes ou même dans une quiche. Soyez inventif et original, les possibilités sont infinies en cuisine. ça sent tellement bon la rose, pourquoi pas un pot-pourri? Un produit super pour la confection de savon, sel et bombe de bain. Ces feuilles ajouterons une touche romantique à vos produits de confection.
